Workbook
Name FintiOwnerList: OwnerLists!$A$2:$A$5
Name FintiOwnerCol: 'Dealer Master'!$BZ$5:$BZ$1021
Name ReadyForRateSheetsCol: 'Dealer Master'!$CA$5:$CA$1021
Name ShawHoldCol: 'Dealer Master'!$CB$5:$CB$1021

Sheet Onboarding Procedures
A1: HOME IMPROVEMENT DEALER ONBOARDING - THE PROCESS
A2: Built from Shawn's Sept 1, 2026 walkthroughs and organized around the Dealer Master tracker: every merchant sits in one Overall Status, and this page tells you what that status means, what you do, and what you type. Updated Sept 2, 2026.
A4: NEW ONBOARDING REP - GET SET UP (DAY 1)
A5: 1. Access | C5: Get your @getfinti.com mailbox, access to the shared merchantonboarding@getfinti.com inbox (all lender and dealer email lives there - always cc it), a login to the Finti portal (app.getfinti.com) with Merchants access, and edit rights to this workbook (Microsoft 365 > Excel > Home Improvement Boarding Tracker V2).
A6: 2. Read these tabs | C6: This tab top to bottom, then DEALER MASTER - HOW TO at the bottom (what the colors mean and what you type), then the SUNLIGHT / SERVICE / Foundation tabs (how to submit to each lender and who to contact). Add yourself to the rep list on the Add Merchant tab if you are missing.
A7: 3. Shadow one merchant | C7: Open a dealer that is already LIVE DLR on Dealer Master and walk it backwards: its row here, its record in the Finti portal (application pages 1-5, Store / Location, Provider credentials), and the email thread in merchantonboarding. That is the whole process end to end.
A8: 4. Know the people | C8: Shawn Hanks - onboarding lead, lender relationships, on the first training calls. Brittany (Brit) - onboarding ops, works from merchantonboarding. Brittany Coutu - Rate Sheet Manager. Jennifer - Service Finance. Jessica Gill / Kobe - Foundation. Alan - Finti portal / dev. Steve - sales leadership.
A9: 5. Email habits | C9: Send from your own @getfinti address, always cc merchantonboarding, cc the sales rep except on sensitive questions (revenue, socials). Draft with Copilot from previously sent emails. Never email a dealer from memory - open their row first, and log the date in Last Status Update Emailed after you send.
A10: 6. Your first week | C10: Day 1: setup + shadow. Day 2: run the EVERY DAY loop with Brit and work Waiting on Dealer rows. Day 3+: take new merchants in the Finti portal start to finish. Ask Shawn before your first lender submission and your first credential load.
A12: EVERY DAY - THREE CHECKS, IN THIS ORDER
A13: 1. Finti portal > Merchants | C13: New merchants are at the top. Anything you have not touched is job #1 - approve it, review it, and get it onto Dealer Master today. Nobody in the company should see a red stoplight.
A14: 2. Dealer Master | C14: Black (Priority 1) rows first, then orange cells (someone needs to move), then Days Since Update - anything 3+ days old gets a follow-up today.
A15: 3. merchantonboarding inbox | C15: Look for lender credentials / API keys, lender questions, or a dealer saying "done." Each one moves a merchant to its next status below.
A16: The one rule | C16: Whenever you do anything for a dealer, update its row right then: lender status, Merchant To-Do, date emailed. If it is not on the sheet, nobody knows.
A18: THE PROCESS - ONE ROW PER OVERALL STATUS ON DEALER MASTER
A19: Overall Status | B19: What it means | C19: What you do | D19: What you type on Dealer Master
A20: NEW (in Finti portal, not on the sheet yet) | B20: A merchant finished page 1 of the application and appeared at the top of the Finti portal. | C20: 1. Approve them as a dealer. Click Edit and walk pages 1-5. Note every missing item - each becomes a line in your email. 2. Check which lenders the rep selected and whether any were bypassed (dealer already has that lender - never resubmit those). 3. Pages 1-2: owner as primary contact, revenue and years in business make sense (odd numbers -> email Steve). Page 3: website + review link (Google them if blank). Page 4: two bank statements + voided check (voided check goes in the Articles of Incorporation slot). Page 5: boxes, signatures, Save and Continue, close -> three DocuSigns go out. 4. Set up the Store / Location if it is missing (Merchant > Store: same as corporate, business name in both name fields, owner contact, bank routing + account) - without it the dealer cannot log back in. 5. Add them on the Add Merchant tab. | D20: Add Merchant tab: name, contacts, vertical, rep, Priority 1-3, Application Date, Merchant To-Do = the list of what is missing. Each lender: Not Started, N/A (not applying / Chowder non-HVAC), or No Min RQ (does not meet that lender's minimums). The row now reads Waiting on Dealer (if a To-Do is open) or Application Submitted.
A21: WAITING ON DEALER | B21: The dealer owes us something (To-Do box unchecked). This is the status Shawn wants worked hardest - the ball is in the dealer's court and only we can push it. | C21: 1. Email the dealer the Action Required email (template 1): every missing item, which page it is on, use Forgot Password, Save and Continue on every page, sign the DocuSigns, reply when done. 2. In the Finti portal flip the stoplight red -> yellow and post "@rep@getfinti.com - application incomplete, emailed dealer [date]". 3. No reply in 3 days? Send the same email again. Repeat every 3 days until they respond (Shawn wants this automated). 4. When the dealer says done, re-check pages 1-5 and DocuSign. Still missing something? Repeat step 1. | D21: Merchant To-Do = what they still owe. Last Status Update Emailed = today, every time you email. Everything landed? Tick the To-Do Done box - the row stops being orange and moves to Application Submitted / Waiting on Lender.
A22: APPLICATION SUBMITTED / WAITING ON LENDER | B22: Application Submitted: complete, but at least one lender is still Not Started. Waiting on Lender: submitted, waiting on the lender's ~2-week due diligence. | C22: 1. Submit to each lender that is Not Started, using the instructions on the SUNLIGHT / SERVICE / Foundation tabs. Existing-lender dealers: bypass, and ask them for their dealer / merchant ID instead. 2. Email the dealer the Submitted email (template 2) and update the stoplight + @ the rep. 3. Service Finance only: email Jennifer the SAME DAY - "we submitted [dealer], is it in your system?" (submissions have gone missing before). 4. Watch merchantonboarding for lender questions; answer them or forward to the dealer the same day. 5. Credentials / API keys arrive -> record them on Dealer Details, then Finti > Merchants > dealer > Location > Provider > Add Provider (strip spaces from the key; Foundation username = dealer ID; leave Valid Till). Do NOT tell the dealer yet. | D22: Each lender: Submitted when you submit; Approved when the credentials are loaded; Declined if the lender says no. Last Status Update Emailed = date of the submitted email. All applied lenders Approved -> the row moves to Rate Sheet on its own.
A23: RATE SHEET | B23: Every applied lender is approved and loaded in Finti. Brittany Coutu's queue - the dealer needs to pick rates before anyone can be trained. | C23: 1. Email Brittany Coutu (template 4) with Shawn and the sales rep on the thread: credentials are in Finti, please send the rate sheets, and once the dealer responds set up the lender and get them training-ready. 2. Optional: tell the dealer "Congratulations - next step is Brittany sending you the [lender] rate sheet to select your rates." 3. Order matters: Brittany sends rates -> dealer selects -> Brittany builds the rate sheet and loads the programs. Never ask her to "set them up" first. A dealer with a better rate sheet of their own keeps it. | D23: Rate Sheet = Yes for each lender once Brittany has built it. Programs Loaded = Yes when the programs are in Finti. The row moves to Training on its own.
A24: TRAINING | B24: Rate sheets are built; the dealer has not been trained. Nothing can go live before training. | C24: 1. Rate sheet meeting (Brittany Coutu + you + the sales rep) with the dealer's top person: connect the rate sheets and show them how to add users. 2. Dealer adds their users and sends their reps logins. 3. Training meeting with the dealer's reps - the sales rep attends, Shawn on the first few. | D24: Training = Yes for each lender once its training is done. Every applied lender Active + Rate Sheet Yes + Training Yes -> the row reads LIVE DLR.
A25: ACTIVE / LIVE DLR | B25: Active: at least one lender is live. LIVE DLR: every applied lender is live, rate-sheeted and trained - onboarding is finished. | C25: 1. Tell the dealer they are live and can run applications. Set the stoplight to green and @ the rep. 2. Tick the To-Do box and log the date. 3. Anything still Approved-but-not-Active means one lender is behind - chase that lender's rate sheet or training, not the dealer. | D25: Lender = Active once it is turned on. Live flags are automatic. Nothing else to type - the row is done.
A26: DEAD | B26: Every real lender declined (N/A and No Min RQ do not count). One approval anywhere means a dealer is never Dead. | C26: Stop working it. Tell the rep. Do not re-excite the dealer until a new lender joins or their numbers change - then set the lender back to Not Started (or No Min RQ -> Not Started) and it re-enters the process. | D26: Lender = Declined for each lender that said no. The row turns red on its own.
A28: PRIORITY - SET IT ON EVERY MERCHANT
A29: 1 - Top (black row) | C29: Connected to RoofLink, SalesRabbit or another channel partner sending a lot of business; OR a big account (about $1M a month in financing already); OR Steve / leadership asks. Work these first, every day.
A30: 2 - Middle | C30: North of $1M a year in revenue and at least a year in business (ideally two or more).
A31: 3 - Small | C31: Mom-and-pop: about $1M a year or less, maybe under a year old. Will not meet most lender minimums - submit to Foundation only.
A33: STOPLIGHT IN THE FINTI PORTAL - WHAT THE SALES REP SEES
A34: Red / Yellow / Green | C34: Red = untouched (nobody should ever see it). Yellow = in process - set it the moment you start, and update the message at each status change. Green = live.
A35: Tagging the rep | C35: Tagging @rep@getfinti.com texts and emails them - do it at every status change. Reps cannot see this sheet; the stoplight is how they find out. Most problems sit with the merchant, not the rep - email the merchant directly and use the stoplight to keep the rep informed.
A37: LENDER CHEAT SHEET
A38: The stack | C38: One prime, one near-prime, one sub-prime per dealer where applicable - not every lender. Never submit a new application to a lender the dealer already has; bypass it and use their existing dealer ID.
A39: Service Finance (prime) | C39: Needs a web presence, ~1 year in business, ~$1M revenue; asks for a license number. Email Jennifer the same day you submit. After approval, get the Service Finance Merchant ID - that is all Finti needs to add the provider.
A40: Sunlight (prime / near-prime) | C40: ~2 years in business plus revenue minimums; needs two bank statements and a voided check. No submission issues so far.
A41: Foundation (sub-prime) | C41: No minimums - every dealer can go here; Priority 3 goes ONLY here. Needs a dealer email. Foundation emails the dealer directly for anything missing. Credentials come from Jessica Gill; username = dealer ID.
A42: Chowder / US Bank | C42: Chowder: HVAC only, always last in the stack, N/A for everyone else (the sheet does this). US Bank: newest lender, same flow as the others.
A43: Does not qualify | C43: Mark that lender No Min RQ, not Declined - it can be applied later when the dealer grows.
A45: EMAIL TEMPLATES (adjust the list for each dealer)
A46: 1. Action required (Waiting on Dealer) | C46: Subject: Action required: complete your Finti application Thank you for applying with Finti. We have reviewed your application and just need a few final items before we can continue. Please log into app.getfinti.com (use Forgot Password if needed) and complete the following: - Page 3 (Insights): [fields], plus your current website and your review / reputation link. - Page 4 (Documents): your two most recent bank statements and a voided check (upload the voided check in the Articles of Incorporation section). - Page 5 (Agreements): all signature fields and certification boxes, then Save and Continue and close the page. - Sign the three DocuSign agreements you will receive after page 5. Once everything is complete, please reply to this email and we will submit you to the lenders right away.
A47: 2. Submitted (Waiting on Lender) | C47: We have submitted you to [lenders]. Please be on the lookout for emails and phone calls from the lenders as they complete their due diligence - on average about two weeks. Please be responsive and quick with anything they ask for so we can expedite the process, and let us know as soon as you hear of your approval.
A48: 3. Service Finance check (same day) | C48: To Jennifer: "We submitted [dealer] today - can you confirm it is showing in your system?"
A49: 4. Rate sheet handoff (Rate Sheet) | C49: To Brittany Coutu, Shawn and the sales rep on the thread: "[Lender] has set up [dealer] and the API credentials are in Finti. Please send the rate sheets to the dealer; once they respond, set up [lender], get them ready for training, and let us know when that is done. [Rep] is on this thread and will be on the training."
A50: Canned docs | C50: Home Improvement Welcome email.docx (welcome / almost-there). Lender submission steps and contacts: SUNLIGHT, SERVICE and Foundation tabs.
A52: DAILY TEAM UPDATE TEMPLATE
A53: Hi Team, Here’s an update from today:
A54: Category | B54: Update
A55: API Keys Uploaded | B55: None
A56: New Merchants Added | B56: None
A57: Applications Submitted | B57: Vet Home Restoration LLC - Frontline Heating and Air (Chowder)
A58: Welcome Emails Sent | B58: None
A59: New Lender Emails Sent | B59: None
A60: AFF Integration Emails Sent | B60: None
A61: POP Sent | B61: None
A63: DEALER MASTER - HOW TO
B64: Not Started / Waiting on Dealer | D64: Action queue - somebody needs to move
B65: Submitted / Waiting on Lender / App Submitted | D65: Waiting on someone else
B66: Approved / Active / Rate Sheet | D66: Moving
B67: Declined / Dead / stale day counter | D67: Stopped, or 3+ days without an update email
B68: N/A / No Min RQ | D68: Not in play
B69: Black row = Priority 1 | D69: Work these first
B70: Greyed To-Do text | D70: Done box checked - the dealer owes nothing
A71: YOU TYPE ONLY THESE FIVE - THE SHEET DERIVES THE REST
A72: Lender statuses / Merchant To-Do note + its Done box / Live flags / Priority 1-3 / Last Status Update Emailed
A73: Automatic: Overall Status, every color, Days Since Update, Lenders Live, the Chowder default. Never type in those columns. Never paint colors by hand.
A74: ADD A NEW MERCHANT | D74: WORK EXISTING MERCHANTS
A75: 1. Fill the row: name, contacts, vertical, priority | D75: 1. Scan the tiles - orange is your queue, black rows first
A76: 2. Set each lender: Not Started, N/A, or No Min RQ | D76: 2. Lender answered? Set the cell. Flip Live to Yes once running
A77: 3. Write the To-Do; tick its box when every doc lands | D77: 3. Docs landed? Update the note and tick the box
A78: 4. Log Application Date + every update email date | D78: 4. All Approved = Rate Sheet / one Active + Live = Active / all Declined or N-A = Dead
A79: ADD A NEW LENDER
A80: Insert three columns (Status, Rate Sheet, Training) to the LEFT of Merchant To-Do, right after the last lender triplet. Copy the dropdowns and color rules from an existing lender, label Min Rq in rows 2-3, then add the new lender to the Lenders Live and Overall Status formulas and the Add Merchant script.

Sheet README - Start Here
B1: Dealer Boarding Tracker — Evan's Draft
B2: Built from scratch in a blank workbook, for team review.
B4: DRAFT. Separate file. The shared tracker in Shawn's OneDrive has not been touched.
B6: Nothing was lost
B7: All 2616 non-empty cells from all 11 tabs of the original workbook are accounted for in this file. The 'Data Check' tab is the receipt. Merchant data is split between the new Dealer Master (short, color-coded status) and Dealer Details (the original wording, verbatim, with the original row number beside it). The reference tabs are flattened onto 'Lender Reference', and the 32 screenshots are transcribed on 'Screenshot Text'. The original workbook, images and all, is untouched and remains the archive.
B9: What's new on Dealer Master
B10: • Merchant To-Do — the single 'what happens next' column, seeded with the original notes.
B11: • Last Status Update Emailed — when you last emailed the merchant an update.
B12: • Days Since Update — fills in on its own; amber past 14 days, red past 30, counted at the top.
B13: • A Live toggle per lender (SF / SL / FF / CW / USB), separate from application status, so 'approved' and 'actually switched on' stop sharing a cell.
B14: • Lenders Live — how many of the five are live for that merchant.
B15: • POP Sent is a Yes/No toggle.
... B51: 3. On approval I can make this the shared file, or apply the structure to the existing one.

Sheet Add Merchant
A1: ADD A NEW MERCHANT
A2: Fill in the yellow cells, then click the Add Merchant button. Required: Legal Business Name, Email, and at least one lender set to Yes. The row is added to Dealer Master with every column defaulted, then this form clears. | D2: Added JAAR BUILDERS to Dealer Master row 52 (lenders: SF, FF). Overall Status: Application Submitted | I2: STATE PICKER - tick every state this dealer is active in
I3: FALSE | J3: Nationwide (all 50) - overrides the ticks below | S3: MANUAL REP LIST - add reps here who are not on a merchant yet
A4: Legal Business Name * | D4: Existing reps (auto - add new reps in the MANUAL REP LIST, column S) | E4: Rep email | G4: Channel partners (dropdown source) | S4: Rep | T4: Rep email
A5: DBA | D5: {=IFERROR(_xlfn._xlws.SORT(_xlfn.UNIQUE(_xlfn._xlws.FILTER(_xlfn.VSTACK('Dealer Master'!G5:G1028,S5:S104),_xlfn.VSTACK('Dealer Master'!G5:G1028,S5:S104)<>""))),"")} -> Brayden Page | E5: {=IFERROR(_xlfn.XLOOKUP(_xlfn.ANCHORARRAY(D5),_xlfn.VSTACK('Dealer Master'!G5:G1028,S5:S104),_xlfn.VSTACK('Dealer Master'!H5:H1028,T5:T104),""),"")} -> Brayden.page@getfinti.com | G5: {=IFERROR(_xlfn._xlws.SORT(_xlfn.UNIQUE(_xlfn._xlws.FILTER('Dealer Master'!C5:C1028,'Dealer Master'!C5:C1028<>""))),"")} -> Sales Rabbit | I5: FALSE | J5: AL | K5: Alabama | L5: FALSE | M5: LA | N5: Louisiana | O5: FALSE | P5: OH | Q5: Ohio | S5: Mark Robichaud | T5: markchmand@gmail.com
A6: Merchant Name (contact) | D6: chris Shipley | E6: chris@getfinti.com | I6: FALSE | J6: AK | K6: Alaska | L6: FALSE | M6: ME | N6: Maine | O6: FALSE | P6: OK | Q6: Oklahoma | S6: Ethan Meturi | T6: Ethan.meturi@getfinti.com
A7: Phone # | D7: Clint Cowley | E7: sales@gowefund.com, clint@gowefund.com | I7: FALSE | J7: AZ | K7: Arizona | L7: FALSE | M7: MD | N7: Maryland | O7: FALSE | P7: OR | Q7: Oregon | S7: chris Shipley | T7: chris@getfinti.com
A8: Email * | D8: David Yates | E8: David.yates@getfinti.com | I8: FALSE | J8: AR | K8: Arkansas | L8: FALSE | M8: MA | N8: Massachusetts | O8: FALSE | P8: PA | Q8: Pennsylvania | S8: Brayden Page | T8: Brayden.page@getfinti.com
A9: Rep | D9: Doug Yates | E9: doug.yates@getfinti.com | I9: FALSE | J9: CA | K9: California | L9: FALSE | M9: MI | N9: Michigan | O9: FALSE | P9: RI | Q9: Rhode Island | S9: Payden Yates | T9: Payden.yates@getfinti.com
A10: Rep Email | B10: =IFERROR(VLOOKUP($B$9,$D$5:$E$500,2,FALSE),"") | D10: Ethan Meturi | E10: Ethan.meturi@getfinti.com | I10: FALSE | J10: CO | K10: Colorado | L10: FALSE | M10: MN | N10: Minnesota | O10: FALSE | P10: SC | Q10: South Carolina | S10: Doug Yates | T10: Doug.Yates@getfinti.com
A11: Vertical | D11: Evan Young | E11: evanyoung@getfinti.com | I11: FALSE | J11: CT | K11: Connecticut | L11: FALSE | M11: MS | N11: Mississippi | O11: FALSE | P11: SD | Q11: South Dakota | S11: sales Rabbit | T11: sales rabbit
A12: Priority (1-3) | D12: Gentry Knight | E12: gentryknight2010@icloud.com | I12: FALSE | J12: DE | K12: Delaware | L12: FALSE | M12: MO | N12: Missouri | O12: FALSE | P12: TN | Q12: Tennessee
A13: Application Date | B13: =TODAY() -> 46288 | D13: Heriberto Rivera | E13: yennikayadiel@gmail.com | I13: FALSE | J13: FL | K13: Florida | L13: FALSE | M13: MT | N13: Montana | O13: FALSE | P13: TX | Q13: Texas
A14: LENDERS TO SUBMIT (Yes/No) | D14: Kyle Fransen | E14: kyle@getfinti.com | I14: FALSE | J14: GA | K14: Georgia | L14: FALSE | M14: NE | N14: Nebraska | O14: FALSE | P14: UT | Q14: Utah
A15: Service Finance | B15: No | D15: Mark Robichaud | E15: markchmand@gmail.com | I15: FALSE | J15: HI | K15: Hawaii | L15: FALSE | M15: NV | N15: Nevada | O15: FALSE | P15: VT | Q15: Vermont
A16: Sunlight | B16: No | D16: Payden Yates | E16: payden.yates@getfinti.com | I16: FALSE | J16: ID | K16: Idaho | L16: FALSE | M16: NH | N16: New Hampshire | O16: FALSE | P16: VA | Q16: Virginia
A17: Foundation | B17: No | D17: Rob Garcia | E17: robsudden24@icloud.com | I17: FALSE | J17: IL | K17: Illinois | L17: FALSE | M17: NJ | N17: New Jersey | O17: FALSE | P17: WA | Q17: Washington
A18: Chowder (auto: HVAC only) | B18: =IF(ISNUMBER(SEARCH("HVAC",B11)),"Yes","No") -> No | D18: Ryan Tall | E18: ryantall11@gmail.com | I18: FALSE | J18: IN | K18: Indiana | L18: FALSE | M18: NM | N18: New Mexico | O18: FALSE | P18: WV | Q18: West Virginia
A19: US Bank | B19: No | D19: sales Rabbit | E19: sales rabbit | I19: FALSE | J19: IA | K19: Iowa | L19: FALSE | M19: NY | N19: New York | O19: FALSE | P19: WI | Q19: Wisconsin
A20: Merchant To-Do | D20: Scott Coombs | E20: scottbcoombs@gmail.com | I20: FALSE | J20: KS | K20: Kansas | L20: FALSE | M20: NC | N20: North Carolina | O20: FALSE | P20: WY | Q20: Wyoming
A21: Channel Partner | D21: Scott Williams | E21: scott.williams.aftr@gmail.com | I21: FALSE | J21: KY | K21: Kentucky | L21: FALSE | M21: ND | N21: North Dakota | O21: FALSE | P21: DC | Q21: Washington DC
A22: States Active | B22: {=IF((I3<>"")*(UPPER(I3&"")<>"FALSE"),"Nationwide",_xlfn.TEXTJOIN(", ",TRUE,_xlfn.TEXTJOIN(", ",TRUE,IF((I5:I21<>"")*(UPPER(I5:I21&"")<>"FALSE"),J5:J21,"")),_xlfn.TEXTJOIN(", ",TRUE,IF((L5:L21<>"")*(UPPER(L5:L21&"")<>"FALSE"),M5:M21,"")),_xlfn.TEXTJOIN(", ",TRUE,IF((O5:O21<>"")*(UPPER(O5:O21&"")<>"FALSE"),P5:P21,""))))} | D22: Shawn Hanks | E22: Shawn@getfinti.com
A23: Tick the boxes in the STATE PICKER to the right (columns I-Q). | D23: Spencer Gradley | E23: spencer.gradley@getfinti.com
D24: Spencer Jackson | E24: app.sj@icloud.com
D25: Steve Stonebraker | E25: stonebraker@getfinti.com
D26: Trevor Young | E26: Trevor.young@getfinti.com
D27: Tyler Mickelsen | E27: tyler@getfinti.com
D28: Tyler Story | E28: tylerstory32@gmail.com
A29: Finti Owner | B29: Unassigned
A31: Same dropdown as Dealer Master. Run Add Merchant is an existing Office Script button, not VBA, and it does not copy this cell. Set Finti Owner on the new Dealer Master row. Blank counts as Unassigned.
A32: =IF($B$18="Yes","CHOWDER APPLICATION INFORMATION","Chowder section appears when Vertical includes HVAC") -> Chowder section appears when Vertical includes HVAC
A33: Chowder Status | B33: =IF($B$18<>"Yes","",_xlfn.LET(_xlpm.m,_xlfn.TEXTJOIN(", ",TRUE,IF(TRIM(B36&"")="","License Holder",""),IF(TRIM(B37&"")="","License #",""),IF(TRIM(B38&"")="","EIN",""),IF(TRIM(B40&"")="","Website",""),IF(TRIM(B41&"")="","Address",""),IF(TRIM(B43&"")="","Contact First Name",""),IF(TRIM(B44&"")="","Contact Last Name",""),IF(TRIM(B46&"")="","Contact Email",""),IF(TRIM(B48&"")="","Owner First Name",""),IF(TRIM(B49&"")="","Owner Last Name",""),IF(TRIM(B51&"")="","Owner Email",""),IF(TRIM(B53&"")="","Bank Name",""),IF(TRIM(B54&"")="","Routing #",""),IF(TRIM(B55&"")="","Account #",""),IF(B57<>TRUE,"Business Registration doc",""),IF(B58<>TRUE,"HVAC License doc",""),IF(B59<>TRUE,"Voided Check doc",""),IF(AND(TRIM(B38&"")<>"",LEN(SUBSTITUTE(SUBSTITUTE(B38&"","-","")," ",""))<>9),"EIN must be 9 digits",""),IF(AND(TRIM(B54&"")<>"",NOT(AND(LEN(TRIM(B54&""))=9,ISNUMBER(--TRIM(B54&""))))),"Routing # must be 9 digits",""),IF(AND(TRIM(B46&"")<>"",ISERROR(SEARCH("@",B46))),"Contact Email invalid",""),IF(AND(TRIM(B51&"")<>"",ISERROR(SEARCH("@",B51))),"Owner Email invalid","")),IF(_xlpm.m="","READY FOR CHOWDER SUBMISSION","MISSING REQUIRED INFORMATION: "&_xlpm.m)))
A34: BUSINESS INFORMATION
A35: Legal Entity Type
A36: HVAC License Holder Name *
A37: HVAC License Number *
A38: Tax ID / EIN *
A39: Business Start Year
A40: Website *
A41: Business Address *
A42: PRIMARY CONTACT
A43: Primary Contact First Name *
A44: Primary Contact Last Name *
A45: Primary Contact Phone
... A56: DOCUMENT CHECKLIST
A57: Business Registration Rec'd * | B57: FALSE
A58: HVAC License Received * | B58: FALSE
A59: Voided Check Received * | B59: FALSE
A61: CHOWDER APPLICATION EMAIL | B61: Copy Chowder Email selects the body - then Cmd+C / Ctrl+C
A62: Subject | B62: =IF($B$18<>"Yes","","New Chowder Merchant Onboarding - "&TRIM($B$4&""))
A63: {=IF($B$18<>"Yes","",_xlfn.VSTACK("Hello William,","","Please see the new Chowder merchant onboarding request below.","","Legal Name:",TRIM($B$4&""),"DBA:",TRIM($B$5&""),"Legal Entity:",TRIM($B$35&""),"HVAC License Holder:",TRIM($B$36&""),"HVAC License Number:",TRIM($B$37&""),"Tax ID:",TRIM($B$38&""),"Products Offered:",TRIM($B$11&""),"Address:",TRIM($B$41&""),"Business Start Year:",TRIM($B$39&""),"Website:",TRIM($B$40&""),"Primary Contact:",TRIM($B$43&" "&$B$44),"Primary Contact Phone:",TRIM($B$45&""),"Primary Contact Email:",TRIM($B$46&""),"Business Owner:",TRIM($B$48&" "&$B$49),"Owner Phone:",TRIM($B$50&""),"Owner Email:",TRIM($B$51&""),"Bank Name:",TRIM($B$53&""),"Routing Number:",TRIM($B$54&""),"Account Number:",TRIM($B$55&""),"","Attached Documents:","- Business Registration","- HVAC License","- Voided Check","","Please let us know if anything additional is required.","","Thank you,","Merchant Onboarding","Finti"))}

Sheet Dealer Master
A1: At a glance: | BA1: DEFAULT
A2: SORT: DEFAULT ORDER | I2: ="Waiting on Dealer: "&COUNTIF(DealerMaster[Overall Status],"Waiting on Dealer") -> Waiting on Dealer: 16 | K2: ="Waiting on Lender: "&COUNTIF(DealerMaster[Overall Status],"Waiting on Lender") -> Waiting on Lender: 13 | L2: ="App Submitted: "&COUNTIF(DealerMaster[Overall Status],"Application Submitted") -> App Submitted: 2 | M2: ="Rate Sheet: "&COUNTIF(DealerMaster[Overall Status],"Rate Sheet") -> Rate Sheet: 3 | O2: ="LIVE DLR: "&COUNTIF(DealerMaster[Overall Status],"LIVE DLR") -> LIVE DLR: 4 | P2: Min Rq | T2: Min Rq | X2: Min Rq | AB2: Min Rq | AF2: Min Rq | BZ2: Existing dealers are Unassigned. Do not guess an owner. Rep is not Finti Owner.
I3: ="Active: "&COUNTIF(DealerMaster[Overall Status],"Active") -> Active: 3 | K3: ="Dead: "&COUNTIF(DealerMaster[Overall Status],"Dead") -> Dead: 4 | L3: ="P1 open To-Do: "&COUNTIFS(DealerMaster[Priority],1,DealerMaster[Merchant To-Do],"<>",DealerMaster[To-Do Done],FALSE) -> P1 open To-Do: 5 | M3: ="No update >3d: "&COUNTIFS(DealerMaster[Days Since Update],">3",DealerMaster[Overall Status],"<>Active",DealerMaster[Overall Status],"<>Dead",DealerMaster[Overall Status],"<>LIVE DLR") -> No update >3d: 11 | O3: ="Training: "&COUNTIF(DealerMaster[Overall Status],"Training") -> Training: 1 | P3: 1 Yr | R3: Rate Sheet | S3: Training | T3: 2 Yr $1M | V3: Rate sheet | W3: Training | X3: No Min Rq | Z3: Rate Sheet | AA3: Training | AB3: No Min Rq | AD3: Rate sheet | AE3: Training | AF3: 1 Yr | AI3: Training
A4: Legal Business Name | B4: DBA | C4: Channel Partner | D4: Merchant Name | E4: Phone # | F4: Email | G4: Rep | H4: Rep Email | I4: Vertical | J4: States Active | K4: Priority | L4: Overall Status | M4: Application Date | N4: Welcome Email Sent | O4: Lender Order | P4: Service Finance | Q4: SF Submitted | R4: SF Rate Sheet | S4: SF Training | T4: Sunlight | U4: SL Submitted | V4: SL Rate Sheet | W4: SL Training | X4: Foundation | Y4: FF Submitted | Z4: FF Rate Sheet | AA4: FF Training | AB4: Chowder | AC4: CH Submitted | AD4: CH Rate Sheet | AE4: CH Training | AF4: US Bank | AG4: USB Submitted | AH4: USB Rate Sheet | AI4: USB Training | AJ4: Merchant To-Do | AK4: To-Do Done | AL4: Lenders Live | AM4: Last Status Update Emailed | AN4: Days Since Update | AO4: Divider | AP4: Service Finance API Code | AQ4: Service Finance States Active | AR4: Sunlight API Code | AS4: Sunlight States Active | AT4: Foundation API Code | AU4: Foundation States Active | AV4: Chowder API Code | AW4: Chowder States Active | AX4: US Bank API Code | AY4: US Bank States Active | AZ4: Divider 2 | BA4: Sort Key | BB4: Sort Temp | BC4: Divider 3 | BD4: CH Legal Entity Type | BE4: CH License Holder | BF4: CH License Number | BG4: CH EIN | BH4: CH Business Start Year | BI4: CH Website | BJ4: CH Business Address | BK4: CH Contact First Name | BL4: CH Contact Last Name | BM4: CH Contact Phone | BN4: CH Contact Email | BO4: CH Owner First Name | BP4: CH Owner Last Name | BQ4: CH Owner Phone | BR4: CH Owner Email | BS4: CH Bank Name | BT4: CH Routing Number | BU4: CH Account Number | BV4: CH Doc Business Registration | BW4: CH Doc HVAC License | BX4: CH Doc Voided Check | BY4: CH Info Saved | BZ4: Finti Owner | CA4: Ready for rate sheets | CB4: Shaw Hold | CC4: Handoff note
A5: Vivid Windows LLC | B5: Vivid Windows | D5: Biss Larsen | E5: 801-557-9860 | F5: biss.larsen@vividwindows.com | G5: Kyle Fransen | H5: kyle@getfinti.com | I5: windows | L5: =IF($A5="","",_xlfn.LET(_xlpm.ns,(--($P5="Ready 2 Submit"))+(--($T5="Ready 2 Submit"))+(--($X5="Ready 2 Submit"))+(--($AB5="Ready 2 Submit"))+(--($AF5="Ready 2 Submit")),_xlpm.wd,(--($P5="Waiting on Dealer"))+(--($T5="Waiting on Dealer"))+(--($X5="Waiting on Dealer"))+(--($AB5="Waiting on Dealer"))+(--($AF5="Waiting on Dealer")),_xlpm.sb,(--($P5="Submitted"))+(--($T5="Submitted"))+(--($X5="Submitted"))+(--($AB5="Submitted"))+(--($AF5="Submitted")),_xlpm.ap,(--($P5="Approved"))+(--($T5="Approved"))+(--($X5="Approved"))+(--($AB5="Approved"))+(--($AF5="Approved")),_xlpm.ac,(--($P5="Active"))+(--($T5="Active"))+(--($X5="Active"))+(--($AB5="Active"))+(--($AF5="Active")),_xlpm.dc,(--($P5="Declined"))+(--($T5="Declined"))+(--($X5="Declined"))+(--($AB5="Declined"))+(--($AF5="Declined")),_xlpm.aRS,(--($P5="Active"))*(--($R5="Yes"))+(--($T5="Active"))*(--($V5="Yes"))+(--($X5="Active"))*(--($Z5="Yes"))+(--($AB5="Active"))*(--($AD5="Yes"))+(--($AF5="Active"))*(--($AH5="Yes")),_xlpm.aDn,(--($P5="Active"))*(--($R5="Yes"))*(--((($S5="Yes")+($S5=TRUE))>0))+(--($T5="Active"))*(--($V5="Yes"))*(--((($W5="Yes")+($W5=TRUE))>0))+(--($X5="Active"))*(--($Z5="Yes"))*(--((($AA5="Yes")+($AA5=TRUE))>0))+(--($AB5="Active"))*(--($AD5="Yes"))*(--((($AE5="Yes")+($AE5=TRUE))>0))+(--($AF5="Active"))*(--($AH5="Yes"))*(--((($AI5="Yes")+($AI5=TRUE))>0)),_xlpm.inPlay,_xlpm.ns+_xlpm.wd+_xlpm.sb+_xlpm.ap,IF(AND(_xlpm.ac>0,_xlpm.inPlay=0,_xlpm.aDn=_xlpm.ac),"LIVE DLR",IF(AND(_xlpm.aRS>0,_xlpm.aDn<_xlpm.aRS),"Training",IF(_xlpm.aRS>0,"Active",IF(AND(_xlpm.dc>0,_xlpm.inPlay+_xlpm.ac=0),"Dead",IF(OR($CA5="Yes",$CA5=TRUE),"Rate Sheet",IF(AND($AJ5<>"",$AK5=FALSE),"Waiting on Dealer",IF(_xlpm.sb>0,"Waiting on Lender",IF(AND(_xlpm.ap+_xlpm.ac>0,_xlpm.ns+_xlpm.wd=0),"Rate Sheet","Application Submitted")))))))))) -> LIVE DLR | M5: 46107 | N5: 46280 | O5: 1. Sunlight, 2. Service Finance, 3. Foundation Finance | P5: Active | Q5: 46274 | R5: Yes | S5: Yes | T5: Active | U5: 46274 | V5: Yes | W5: Yes | X5: Active | Y5: 46108 | Z5: Yes | AA5: Yes | AB5: N/A | AC5: =IF(OR(AC5="",AC5=0),IF($AB5="Submitted",TODAY(),""),AC5) | AD5: No | AE5: No | AF5: N/A | AG5: =IF(OR(AG5="",AG5=0),IF($AF5="Submitted",TODAY(),""),AG5) | AH5: No | AI5: No | AJ5: Active | AK5: TRUE | AL5: {=IF($A5="","",SUMPRODUCT((CHOOSE({1,2,3,4,5},$R5,$V5,$Z5,$AD5,$AH5)="Yes")*(((CHOOSE({1,2,3,4,5},$S5,$W5,$AA5,$AE5,$AI5)="Yes")+(CHOOSE({1,2,3,4,5},$S5,$W5,$AA5,$AE5,$AI5)=TRUE))>0)))} -> 3 | AN5: =IF(OR($A5="",$AM5=""),"",TODAY()-$AM5) | AP5: 227125330 | AR5: vividwindows-finti@sunlightfinancial.com; 800339 | AS5: ID, MT, WY, UT | pending: NV, CA | AT5: 35206000 | BA5: 1 | BZ5: Unassigned | CA5: No | CB5: =IF($A5="","",_xlfn.LET(_xlpm.sfp,AND($P5<>"",$P5<>"N/A",$P5<>"No Min RQ"),_xlpm.slp,AND($T5<>"",$T5<>"N/A",$T5<>"No Min RQ"),_xlpm.ffp,AND($X5<>"",$X5<>"N/A",$X5<>"No Min RQ"),_xlpm.chp,AND($AB5<>"",$AB5<>"N/A",$AB5<>"No Min RQ"),_xlpm.usp,AND($AF5<>"",$AF5<>"N/A",$AF5<>"No Min RQ"),_xlpm.n,_xlpm.sfp+_xlpm.slp+_xlpm.ffp+_xlpm.chp+_xlpm.usp,_xlpm.sub,(_xlpm.sfp*($P5="Submitted"))+(_xlpm.slp*($T5="Submitted"))+(_xlpm.ffp*($X5="Submitted"))+(_xlpm.chp*($AB5="Submitted"))+(_xlpm.usp*($AF5="Submitted")),_xlpm.term,(_xlpm.sfp*OR($P5="Approved",$P5="Declined"))+(_xlpm.slp*OR($T5="Approved",$T5="Declined"))+(_xlpm.ffp*OR($X5="Approved",$X5="Declined"))+(_xlpm.chp*OR($AB5="Approved",$AB5="Declined"))+(_xlpm.usp*OR($AF5="Approved",$AF5="Declined")),IF(_xlpm.n=0,"No applicable lenders",IF(_xlpm.sub>0,"Stays with Shaw - lender still Submitted",IF(_xlpm.term=_xlpm.n,"Clear - all applicable lenders Approved or Declined","Stays with Shaw - not all lenders Approved or Declined")))))
A6: Alta Water Bountiful LLC | B6: Water Protection 0ne | D6: Jonathan Ebert | E6: 801-450-5618 | F6: jono@drinkaltawater.com | G6: Kyle Fransen | H6: kyle@getfinti.com | I6: Water Treatment | L6: =IF($A6="","",_xlfn.LET(_xlpm.ns,(--($P6="Ready 2 Submit"))+(--($T6="Ready 2 Submit"))+(--($X6="Ready 2 Submit"))+(--($AB6="Ready 2 Submit"))+(--($AF6="Ready 2 Submit")),_xlpm.wd,(--($P6="Waiting on Dealer"))+(--($T6="Waiting on Dealer"))+(--($X6="Waiting on Dealer"))+(--($AB6="Waiting on Dealer"))+(--($AF6="Waiting on Dealer")),_xlpm.sb,(--($P6="Submitted"))+(--($T6="Submitted"))+(--($X6="Submitted"))+(--($AB6="Submitted"))+(--($AF6="Submitted")),_xlpm.ap,(--($P6="Approved"))+(--($T6="Approved"))+(--($X6="Approved"))+(--($AB6="Approved"))+(--($AF6="Approved")),_xlpm.ac,(--($P6="Active"))+(--($T6="Active"))+(--($X6="Active"))+(--($AB6="Active"))+(--($AF6="Active")),_xlpm.dc,(--($P6="Declined"))+(--($T6="Declined"))+(--($X6="Declined"))+(--($AB6="Declined"))+(--($AF6="Declined")),_xlpm.aRS,(--($P6="Active"))*(--($R6="Yes"))+(--($T6="Active"))*(--($V6="Yes"))+(--($X6="Active"))*(--($Z6="Yes"))+(--($AB6="Active"))*(--($AD6="Yes"))+(--($AF6="Active"))*(--($AH6="Yes")),_xlpm.aDn,(--($P6="Active"))*(--($R6="Yes"))*(--((($S6="Yes")+($S6=TRUE))>0))+(--($T6="Active"))*(--($V6="Yes"))*(--((($W6="Yes")+($W6=TRUE))>0))+(--($X6="Active"))*(--($Z6="Yes"))*(--((($AA6="Yes")+($AA6=TRUE))>0))+(--($AB6="Active"))*(--($AD6="Yes"))*(--((($AE6="Yes")+($AE6=TRUE))>0))+(--($AF6="Active"))*(--($AH6="Yes"))*(--((($AI6="Yes")+($AI6=TRUE))>0)),_xlpm.inPlay,_xlpm.ns+_xlpm.wd+_xlpm.sb+_xlpm.ap,IF(AND(_xlpm.ac>0,_xlpm.inPlay=0,_xlpm.aDn=_xlpm.ac),"LIVE DLR",IF(AND(_xlpm.aRS>0,_xlpm.aDn<_xlpm.aRS),"Training",IF(_xlpm.aRS>0,"Active",IF(AND(_xlpm.dc>0,_xlpm.inPlay+_xlpm.ac=0),"Dead",IF(OR($CA6="Yes",$CA6=TRUE),"Rate Sheet",IF(AND($AJ6<>"",$AK6=FALSE),"Waiting on Dealer",IF(_xlpm.sb>0,"Waiting on Lender",IF(AND(_xlpm.ap+_xlpm.ac>0,_xlpm.ns+_xlpm.wd=0),"Rate Sheet","Application Submitted")))))))))) -> LIVE DLR | M6: 46195 | N6: 46280 | P6: Declined | Q6: =IF(OR(Q6="",Q6=0),IF($P6="Submitted",TODAY(),""),Q6) | S6: No | T6: Declined | U6: =IF(OR(U6="",U6=0),IF($T6="Submitted",TODAY(),""),U6) | V6: No | W6: No | X6: Active | Y6: 46219 | Z6: Yes | AA6: Yes | AB6: N/A | AC6: =IF(OR(AC6="",AC6=0),IF($AB6="Submitted",TODAY(),""),AC6) | AD6: No | AE6: No | AF6: Active | AG6: 46274 | AH6: Yes | AI6: Yes | AJ6: 7/28 sent jono an email with Foundations rate sheet letting him know we can get started with them and asking him to pick the programs he wants to offer. | AK6: TRUE | AL6: {=IF($A6="","",SUMPRODUCT((CHOOSE({1,2,3,4,5},$R6,$V6,$Z6,$AD6,$AH6)="Yes")*(((CHOOSE({1,2,3,4,5},$S6,$W6,$AA6,$AE6,$AI6)="Yes")+(CHOOSE({1,2,3,4,5},$S6,$W6,$AA6,$AE6,$AI6)=TRUE))>0)))} -> 2 | AN6: =IF(OR($A6="",$AM6=""),"",TODAY()-$AM6) | AT6: 21174000 | AX6: 8047342103 | BA6: 2 | BZ6: Unassigned | CA6: No | CB6: =IF($A6="","",_xlfn.LET(_xlpm.sfp,AND($P6<>"",$P6<>"N/A",$P6<>"No Min RQ"),_xlpm.slp,AND($T6<>"",$T6<>"N/A",$T6<>"No Min RQ"),_xlpm.ffp,AND($X6<>"",$X6<>"N/A",$X6<>"No Min RQ"),_xlpm.chp,AND($AB6<>"",$AB6<>"N/A",$AB6<>"No Min RQ"),_xlpm.usp,AND($AF6<>"",$AF6<>"N/A",$AF6<>"No Min RQ"),_xlpm.n,_xlpm.sfp+_xlpm.slp+_xlpm.ffp+_xlpm.chp+_xlpm.usp,_xlpm.sub,(_xlpm.sfp*($P6="Submitted"))+(_xlpm.slp*($T6="Submitted"))+(_xlpm.ffp*($X6="Submitted"))+(_xlpm.chp*($AB6="Submitted"))+(_xlpm.usp*($AF6="Submitted")),_xlpm.term,(_xlpm.sfp*OR($P6="Approved",$P6="Declined"))+(_xlpm.slp*OR($T6="Approved",$T6="Declined"))+(_xlpm.ffp*OR($X6="Approved",$X6="Declined"))+(_xlpm.chp*OR($AB6="Approved",$AB6="Declined"))+(_xlpm.usp*OR($AF6="Approved",$AF6="Declined")),IF(_xlpm.n=0,"No applicable lenders",IF(_xlpm.sub>0,"Stays with Shaw - lender still Submitted",IF(_xlpm.term=_xlpm.n,"Clear - all applicable lenders Approved or Declined","Stays with Shaw - not all lenders Approved or Declined")))))
A7: Dirty Fence and Concrete | B7: Dirty Fence and Concrete | D7: Gentry Knight | E7: 801-389-4788 | F7: gentryknight2010@icloud.com | G7: Gentry Knight | H7: gentryknight2010@icloud.com | I7: Fencing | K7: 3 | L7: =IF($A7="","",_xlfn.LET(_xlpm.ns,(--($P7="Ready 2 Submit"))+(--($T7="Ready 2 Submit"))+(--($X7="Ready 2 Submit"))+(--($AB7="Ready 2 Submit"))+(--($AF7="Ready 2 Submit")),_xlpm.wd,(--($P7="Waiting on Dealer"))+(--($T7="Waiting on Dealer"))+(--($X7="Waiting on Dealer"))+(--($AB7="Waiting on Dealer"))+(--($AF7="Waiting on Dealer")),_xlpm.sb,(--($P7="Submitted"))+(--($T7="Submitted"))+(--($X7="Submitted"))+(--($AB7="Submitted"))+(--($AF7="Submitted")),_xlpm.ap,(--($P7="Approved"))+(--($T7="Approved"))+(--($X7="Approved"))+(--($AB7="Approved"))+(--($AF7="Approved")),_xlpm.ac,(--($P7="Active"))+(--($T7="Active"))+(--($X7="Active"))+(--($AB7="Active"))+(--($AF7="Active")),_xlpm.dc,(--($P7="Declined"))+(--($T7="Declined"))+(--($X7="Declined"))+(--($AB7="Declined"))+(--($AF7="Declined")),_xlpm.aRS,(--($P7="Active"))*(--($R7="Yes"))+(--($T7="Active"))*(--($V7="Yes"))+(--($X7="Active"))*(--($Z7="Yes"))+(--($AB7="Active"))*(--($AD7="Yes"))+(--($AF7="Active"))*(--($AH7="Yes")),_xlpm.aDn,(--($P7="Active"))*(--($R7="Yes"))*(--((($S7="Yes")+($S7=TRUE))>0))+(--($T7="Active"))*(--($V7="Yes"))*(--((($W7="Yes")+($W7=TRUE))>0))+(--($X7="Active"))*(--($Z7="Yes"))*(--((($AA7="Yes")+($AA7=TRUE))>0))+(--($AB7="Active"))*(--($AD7="Yes"))*(--((($AE7="Yes")+($AE7=TRUE))>0))+(--($AF7="Active"))*(--($AH7="Yes"))*(--((($AI7="Yes")+($AI7=TRUE))>0)),_xlpm.inPlay,_xlpm.ns+_xlpm.wd+_xlpm.sb+_xlpm.ap,IF(AND(_xlpm.ac>0,_xlpm.inPlay=0,_xlpm.aDn=_xlpm.ac),"LIVE DLR",IF(AND(_xlpm.aRS>0,_xlpm.aDn<_xlpm.aRS),"Training",IF(_xlpm.aRS>0,"Active",IF(AND(_xlpm.dc>0,_xlpm.inPlay+_xlpm.ac=0),"Dead",IF(OR($CA7="Yes",$CA7=TRUE),"Rate Sheet",IF(AND($AJ7<>"",$AK7=FALSE),"Waiting on Dealer",IF(_xlpm.sb>0,"Waiting on Lender",IF(AND(_xlpm.ap+_xlpm.ac>0,_xlpm.ns+_xlpm.wd=0),"Rate Sheet","Application Submitted")))))))))) -> Active | M7: 46202 | N7: 46280 | P7: Declined | Q7: =IF(OR(Q7="",Q7=0),IF($P7="Submitted",TODAY(),""),Q7) | R7: No | S7: No | T7: Declined | U7: =IF(OR(U7="",U7=0),IF($T7="Submitted",TODAY(),""),U7) | V7: No | W7: No | X7: Active | Y7: 46217 | Z7: Yes | AA7: Yes | AB7: N/A | AC7: =IF(OR(AC7="",AC7=0),IF($AB7="Submitted",TODAY(),""),AC7) | AD7: No | AE7: No | AF7: Submitted | AG7: 46275 | AH7: No | AI7: No | AJ7: US Bank needs financial statements | AK7: FALSE | AL7: {=IF($A7="","",SUMPRODUCT((CHOOSE({1,2,3,4,5},$R7,$V7,$Z7,$AD7,$AH7)="Yes")*(((CHOOSE({1,2,3,4,5},$S7,$W7,$AA7,$AE7,$AI7)="Yes")+(CHOOSE({1,2,3,4,5},$S7,$W7,$AA7,$AE7,$AI7)=TRUE))>0)))} -> 1 | AM7: 46287 | AN7: =IF(OR($A7="",$AM7=""),"",TODAY()-$AM7) -> 1 | AT7: 36161000 | BA7: 3 | BZ7: Unassigned | CA7: No | CB7: =IF($A7="","",_xlfn.LET(_xlpm.sfp,AND($P7<>"",$P7<>"N/A",$P7<>"No Min RQ"),_xlpm.slp,AND($T7<>"",$T7<>"N/A",$T7<>"No Min RQ"),_xlpm.ffp,AND($X7<>"",$X7<>"N/A",$X7<>"No Min RQ"),_xlpm.chp,AND($AB7<>"",$AB7<>"N/A",$AB7<>"No Min RQ"),_xlpm.usp,AND($AF7<>"",$AF7<>"N/A",$AF7<>"No Min RQ"),_xlpm.n,_xlpm.sfp+_xlpm.slp+_xlpm.ffp+_xlpm.chp+_xlpm.usp,_xlpm.sub,(_xlpm.sfp*($P7="Submitted"))+(_xlpm.slp*($T7="Submitted"))+(_xlpm.ffp*($X7="Submitted"))+(_xlpm.chp*($AB7="Submitted"))+(_xlpm.usp*($AF7="Submitted")),_xlpm.term,(_xlpm.sfp*OR($P7="Approved",$P7="Declined"))+(_xlpm.slp*OR($T7="Approved",$T7="Declined"))+(_xlpm.ffp*OR($X7="Approved",$X7="Declined"))+(_xlpm.chp*OR($AB7="Approved",$AB7="Declined"))+(_xlpm.usp*OR($AF7="Approved",$AF7="Declined")),IF(_xlpm.n=0,"No applicable lenders",IF(_xlpm.sub>0,"Stays with Shaw - lender still Submitted",IF(_xlpm.term=_xlpm.n,"Clear - all applicable lenders Approved or Declined","Stays with Shaw - not all lenders Approved or Declined")))))
A8: Vet Home Restoration LLC | B8: Frontline Heating and Air | D8: Travis Fincher | E8: 435-525-0050 | F8: travis@frontlineair.com | G8: Steve Stonebraker | H8: stonebraker@getfinti.com | I8: HVAC Equipment, air and water quality | L8: =IF($A8="","",_xlfn.LET(_xlpm.ns,(--($P8="Ready 2 Submit"))+(--($T8="Ready 2 Submit"))+(--($X8="Ready 2 Submit"))+(--($AB8="Ready 2 Submit"))+(--($AF8="Ready 2 Submit")),_xlpm.wd,(--($P8="Waiting on Dealer"))+(--($T8="Waiting on Dealer"))+(--($X8="Waiting on Dealer"))+(--($AB8="Waiting on Dealer"))+(--($AF8="Waiting on Dealer")),_xlpm.sb,(--($P8="Submitted"))+(--($T8="Submitted"))+(--($X8="Submitted"))+(--($AB8="Submitted"))+(--($AF8="Submitted")),_xlpm.ap,(--($P8="Approved"))+(--($T8="Approved"))+(--($X8="Approved"))+(--($AB8="Approved"))+(--($AF8="Approved")),_xlpm.ac,(--($P8="Active"))+(--($T8="Active"))+(--($X8="Active"))+(--($AB8="Active"))+(--($AF8="Active")),_xlpm.dc,(--($P8="Declined"))+(--($T8="Declined"))+(--($X8="Declined"))+(--($AB8="Declined"))+(--($AF8="Declined")),_xlpm.aRS,(--($P8="Active"))*(--($R8="Yes"))+(--($T8="Active"))*(--($V8="Yes"))+(--($X8="Active"))*(--($Z8="Yes"))+(--($AB8="Active"))*(--($AD8="Yes"))+(--($AF8="Active"))*(--($AH8="Yes")),_xlpm.aDn,(--($P8="Active"))*(--($R8="Yes"))*(--((($S8="Yes")+($S8=TRUE))>0))+(--($T8="Active"))*(--($V8="Yes"))*(--((($W8="Yes")+($W8=TRUE))>0))+(--($X8="Active"))*(--($Z8="Yes"))*(--((($AA8="Yes")+($AA8=TRUE))>0))+(--($AB8="Active"))*(--($AD8="Yes"))*(--((($AE8="Yes")+($AE8=TRUE))>0))+(--($AF8="Active"))*(--($AH8="Yes"))*(--((($AI8="Yes")+($AI8=TRUE))>0)),_xlpm.inPlay,_xlpm.ns+_xlpm.wd+_xlpm.sb+_xlpm.ap,IF(AND(_xlpm.ac>0,_xlpm.inPlay=0,_xlpm.aDn=_xlpm.ac),"LIVE DLR",IF(AND(_xlpm.aRS>0,_xlpm.aDn<_xlpm.aRS),"Training",IF(_xlpm.aRS>0,"Active",IF(AND(_xlpm.dc>0,_xlpm.inPlay+_xlpm.ac=0),"Dead",IF(OR($CA8="Yes",$CA8=TRUE),"Rate Sheet",IF(AND($AJ8<>"",$AK8=FALSE),"Waiting on Dealer",IF(_xlpm.sb>0,"Waiting on Lender",IF(AND(_xlpm.ap+_xlpm.ac>0,_xlpm.ns+_xlpm.wd=0),"Rate Sheet","Application Submitted")))))))))) -> LIVE DLR | M8: 46202 | N8: 46280 | O8: 1. Service Finance, 2. Sunlight, 3. Foundation Finance | P8: Active | Q8: 46274 | R8: Yes | S8: Yes | T8: Active | U8: 46274 | V8: Yes | W8: Yes | X8: Active | Y8: 46143 | Z8: Yes | AA8: Yes | AB8: Active | AC8: 46274 | AD8: Yes | AE8: Yes | AF8: N/A | AG8: =IF(OR(AG8="",AG8=0),IF($AF8="Submitted",TODAY(),""),AG8) | AH8: No | AI8: No | AJ8: Complete | AK8: TRUE | AL8: {=IF($A8="","",SUMPRODUCT((CHOOSE({1,2,3,4,5},$R8,$V8,$Z8,$AD8,$AH8)="Yes")*(((CHOOSE({1,2,3,4,5},$S8,$W8,$AA8,$AE8,$AI8)="Yes")+(CHOOSE({1,2,3,4,5},$S8,$W8,$AA8,$AE8,$AI8)=TRUE))>0)))} -> 4 | AN8: =IF(OR($A8="",$AM8=""),"",TODAY()-$AM8) | AP8: 203125329 | AR8: frontline-finti@sunlightfinancial.com; 418327 | AS8: UT | AT8: 35536000 | AU8: UT, NV, AZ | AV8: 4112997000246468065 | BA8: 4 | BZ8: Unassigned | CA8: No | CB8: =IF($A8="","",_xlfn.LET(_xlpm.sfp,AND($P8<>"",$P8<>"N/A",$P8<>"No Min RQ"),_xlpm.slp,AND($T8<>"",$T8<>"N/A",$T8<>"No Min RQ"),_xlpm.ffp,AND($X8<>"",$X8<>"N/A",$X8<>"No Min RQ"),_xlpm.chp,AND($AB8<>"",$AB8<>"N/A",$AB8<>"No Min RQ"),_xlpm.usp,AND($AF8<>"",$AF8<>"N/A",$AF8<>"No Min RQ"),_xlpm.n,_xlpm.sfp+_xlpm.slp+_xlpm.ffp+_xlpm.chp+_xlpm.usp,_xlpm.sub,(_xlpm.sfp*($P8="Submitted"))+(_xlpm.slp*($T8="Submitted"))+(_xlpm.ffp*($X8="Submitted"))+(_xlpm.chp*($AB8="Submitted"))+(_xlpm.usp*($AF8="Submitted")),_xlpm.term,(_xlpm.sfp*OR($P8="Approved",$P8="Declined"))+(_xlpm.slp*OR($T8="Approved",$T8="Declined"))+(_xlpm.ffp*OR($X8="Approved",$X8="Declined"))+(_xlpm.chp*OR($AB8="Approved",$AB8="Declined"))+(_xlpm.usp*OR($AF8="Approved",$AF8="Declined")),IF(_xlpm.n=0,"No applicable lenders",IF(_xlpm.sub>0,"Stays with Shaw - lender still Submitted",IF(_xlpm.term=_xlpm.n,"Clear - all applicable lenders Approved or Declined","Stays with Shaw - not all lenders Approved or Declined")))))
A9: Vantage Point Roofing LLC | B9: VP Roofing | D9: Jacob Fullmer | E9: 801-889-8609 | F9: jake@vproofing.com | G9: Steve Stonebraker | H9: stonebraker@getfinti.com | L9: =IF($A9="","",_xlfn.LET(_xlpm.ns,(--($P9="Ready 2 Submit"))+(--($T9="Ready 2 Submit"))+(--($X9="Ready 2 Submit"))+(--($AB9="Ready 2 Submit"))+(--($AF9="Ready 2 Submit")),_xlpm.wd,(--($P9="Waiting on Dealer"))+(--($T9="Waiting on Dealer"))+(--($X9="Waiting on Dealer"))+(--($AB9="Waiting on Dealer"))+(--($AF9="Waiting on Dealer")),_xlpm.sb,(--($P9="Submitted"))+(--($T9="Submitted"))+(--($X9="Submitted"))+(--($AB9="Submitted"))+(--($AF9="Submitted")),_xlpm.ap,(--($P9="Approved"))+(--($T9="Approved"))+(--($X9="Approved"))+(--($AB9="Approved"))+(--($AF9="Approved")),_xlpm.ac,(--($P9="Active"))+(--($T9="Active"))+(--($X9="Active"))+(--($AB9="Active"))+(--($AF9="Active")),_xlpm.dc,(--($P9="Declined"))+(--($T9="Declined"))+(--($X9="Declined"))+(--($AB9="Declined"))+(--($AF9="Declined")),_xlpm.aRS,(--($P9="Active"))*(--($R9="Yes"))+(--($T9="Active"))*(--($V9="Yes"))+(--($X9="Active"))*(--($Z9="Yes"))+(--($AB9="Active"))*(--($AD9="Yes"))+(--($AF9="Active"))*(--($AH9="Yes")),_xlpm.aDn,(--($P9="Active"))*(--($R9="Yes"))*(--((($S9="Yes")+($S9=TRUE))>0))+(--($T9="Active"))*(--($V9="Yes"))*(--((($W9="Yes")+($W9=TRUE))>0))+(--($X9="Active"))*(--($Z9="Yes"))*(--((($AA9="Yes")+($AA9=TRUE))>0))+(--($AB9="Active"))*(--($AD9="Yes"))*(--((($AE9="Yes")+($AE9=TRUE))>0))+(--($AF9="Active"))*(--($AH9="Yes"))*(--((($AI9="Yes")+($AI9=TRUE))>0)),_xlpm.inPlay,_xlpm.ns+_xlpm.wd+_xlpm.sb+_xlpm.ap,IF(AND(_xlpm.ac>0,_xlpm.inPlay=0,_xlpm.aDn=_xlpm.ac),"LIVE DLR",IF(AND(_xlpm.aRS>0,_xlpm.aDn<_xlpm.aRS),"Training",IF(_xlpm.aRS>0,"Active",IF(AND(_xlpm.dc>0,_xlpm.inPlay+_xlpm.ac=0),"Dead",IF(OR($CA9="Yes",$CA9=TRUE),"Rate Sheet",IF(AND($AJ9<>"",$AK9=FALSE),"Waiting on Dealer",IF(_xlpm.sb>0,"Waiting on Lender",IF(AND(_xlpm.ap+_xlpm.ac>0,_xlpm.ns+_xlpm.wd=0),"Rate Sheet","Application Submitted")))))))))) -> LIVE DLR | M9: 46209 | N9: 46209 | O9: 1. Service Finance, 2. Sunlight, 3. Foundation Finance | P9: Active | Q9: 46274 | R9: Yes | S9: Yes | T9: Active | U9: 46274 | V9: Yes | W9: Yes | X9: Active | Y9: 45908 | Z9: Yes | AA9: Yes | AB9: N/A | AC9: =IF(OR(AC9="",AC9=0),IF($AB9="Submitted",TODAY(),""),AC9) | AD9: No | AE9: No | AF9: N/A | AG9: =IF(OR(AG9="",AG9=0),IF($AF9="Submitted",TODAY(),""),AG9) | AH9: No | AI9: No | AJ9: Active | AK9: TRUE | AL9: {=IF($A9="","",SUMPRODUCT((CHOOSE({1,2,3,4,5},$R9,$V9,$Z9,$AD9,$AH9)="Yes")*(((CHOOSE({1,2,3,4,5},$S9,$W9,$AA9,$AE9,$AI9)="Yes")+(CHOOSE({1,2,3,4,5},$S9,$W9,$AA9,$AE9,$AI9)=TRUE))>0)))} -> 3 | AN9: =IF(OR($A9="",$AM9=""),"",TODAY()-$AM9) | AP9: 227125332 | AR9: vproofing-finti@sunlightfinancial.com; 407469 | AT9: 33844000 | BA9: 5 | BZ9: Unassigned | CA9: No | CB9: =IF($A9="","",_xlfn.LET(_xlpm.sfp,AND($P9<>"",$P9<>"N/A",$P9<>"No Min RQ"),_xlpm.slp,AND($T9<>"",$T9<>"N/A",$T9<>"No Min RQ"),_xlpm.ffp,AND($X9<>"",$X9<>"N/A",$X9<>"No Min RQ"),_xlpm.chp,AND($AB9<>"",$AB9<>"N/A",$AB9<>"No Min RQ"),_xlpm.usp,AND($AF9<>"",$AF9<>"N/A",$AF9<>"No Min RQ"),_xlpm.n,_xlpm.sfp+_xlpm.slp+_xlpm.ffp+_xlpm.chp+_xlpm.usp,_xlpm.sub,(_xlpm.sfp*($P9="Submitted"))+(_xlpm.slp*($T9="Submitted"))+(_xlpm.ffp*($X9="Submitted"))+(_xlpm.chp*($AB9="Submitted"))+(_xlpm.usp*($AF9="Submitted")),_xlpm.term,(_xlpm.sfp*OR($P9="Approved",$P9="Declined"))+(_xlpm.slp*OR($T9="Approved",$T9="Declined"))+(_xlpm.ffp*OR($X9="Approved",$X9="Declined"))+(_xlpm.chp*OR($AB9="Approved",$AB9="Declined"))+(_xlpm.usp*OR($AF9="Approved",$AF9="Declined")),IF(_xlpm.n=0,"No applicable lenders",IF(_xlpm.sub>0,"Stays with Shaw - lender still Submitted",IF(_xlpm.term=_xlpm.n,"Clear - all applicable lenders Approved or Declined","Stays with Shaw - not all lenders Approved or Declined")))))
A10: Mahan Home & Commercial Services, LLC | B10: Mahan Roofing | C10: Sales Rabbit | D10: Jesse Mahan | E10: 817-773-8524 | F10: jesse@mahanhcs.com | G10: Steve Stonebraker | H10: stonebraker@getfinti.com | I10: residential & commercial roofing | K10: 1 | L10: =IF($A10="","",_xlfn.LET(_xlpm.ns,(--($P10="Ready 2 Submit"))+(--($T10="Ready 2 Submit"))+(--($X10="Ready 2 Submit"))+(--($AB10="Ready 2 Submit"))+(--($AF10="Ready 2 Submit")),_xlpm.wd,(--($P10="Waiting on Dealer"))+(--($T10="Waiting on Dealer"))+(--($X10="Waiting on Dealer"))+(--($AB10="Waiting on Dealer"))+(--($AF10="Waiting on Dealer")),_xlpm.sb,(--($P10="Submitted"))+(--($T10="Submitted"))+(--($X10="Submitted"))+(--($AB10="Submitted"))+(--($AF10="Submitted")),_xlpm.ap,(--($P10="Approved"))+(--($T10="Approved"))+(--($X10="Approved"))+(--($AB10="Approved"))+(--($AF10="Approved")),_xlpm.ac,(--($P10="Active"))+(--($T10="Active"))+(--($X10="Active"))+(--($AB10="Active"))+(--($AF10="Active")),_xlpm.dc,(--($P10="Declined"))+(--($T10="Declined"))+(--($X10="Declined"))+(--($AB10="Declined"))+(--($AF10="Declined")),_xlpm.aRS,(--($P10="Active"))*(--($R10="Yes"))+(--($T10="Active"))*(--($V10="Yes"))+(--($X10="Active"))*(--($Z10="Yes"))+(--($AB10="Active"))*(--($AD10="Yes"))+(--($AF10="Active"))*(--($AH10="Yes")),_xlpm.aDn,(--($P10="Active"))*(--($R10="Yes"))*(--((($S10="Yes")+($S10=TRUE))>0))+(--($T10="Active"))*(--($V10="Yes"))*(--((($W10="Yes")+($W10=TRUE))>0))+(--($X10="Active"))*(--($Z10="Yes"))*(--((($AA10="Yes")+($AA10=TRUE))>0))+(--($AB10="Active"))*(--($AD10="Yes"))*(--((($AE10="Yes")+($AE10=TRUE))>0))+(--($AF10="Active"))*(--($AH10="Yes"))*(--((($AI10="Yes")+($AI10=TRUE))>0)),_xlpm.inPlay,_xlpm.ns+_xlpm.wd+_xlpm.sb+_xlpm.ap,IF(AND(_xlpm.ac>0,_xlpm.inPlay=0,_xlpm.aDn=_xlpm.ac),"LIVE DLR",IF(AND(_xlpm.aRS>0,_xlpm.aDn<_xlpm.aRS),"Training",IF(_xlpm.aRS>0,"Active",IF(AND(_xlpm.dc>0,_xlpm.inPlay+_xlpm.ac=0),"Dead",IF(OR($CA10="Yes",$CA10=TRUE),"Rate Sheet",IF(AND($AJ10<>"",$AK10=FALSE),"Waiting on Dealer",IF(_xlpm.sb>0,"Waiting on Lender",IF(AND(_xlpm.ap+_xlpm.ac>0,_xlpm.ns+_xlpm.wd=0),"Rate Sheet","Application Submitted")))))))))) -> Waiting on Lender | M10: 46219 | N10: 46219 | P10: Submitted | Q10: 46279 | R10: No | S10: No | T10: Declined | U10: =IF(OR(U10="",U10=0),IF($T10="Submitted",TODAY(),""),U10) | V10: No | W10: No | X10: Active | Y10: 46219 | Z10: No | AA10: No | AB10: N/A | AC10: =IF(OR(AC10="",AC10=0),IF($AB10="Submitted",TODAY(),""),AC10) | AD10: No | AE10: No | AF10: N/A | AG10: =IF(OR(AG10="",AG10=0),IF($AF10="Submitted",TODAY(),""),AG10) | AH10: No | AI10: No | AJ10: Sent to lenders and sent dlr "lenders submitted" email. | AK10: TRUE | AL10: {=IF($A10="","",SUMPRODUCT((CHOOSE({1,2,3,4,5},$R10,$V10,$Z10,$AD10,$AH10)="Yes")*(((CHOOSE({1,2,3,4,5},$S10,$W10,$AA10,$AE10,$AI10)="Yes")+(CHOOSE({1,2,3,4,5},$S10,$W10,$AA10,$AE10,$AI10)=TRUE))>0)))} -> 0 | AM10: 46279 | AN10: =IF(OR($A10="",$AM10=""),"",TODAY()-$AM10) -> 9 | AT10: 36159000 | BA10: 6 | BZ10: Unassigned | CA10: No | CB10: =IF($A10="","",_xlfn.LET(_xlpm.sfp,AND($P10<>"",$P10<>"N/A",$P10<>"No Min RQ"),_xlpm.slp,AND($T10<>"",$T10<>"N/A",$T10<>"No Min RQ"),_xlpm.ffp,AND($X10<>"",$X10<>"N/A",$X10<>"No Min RQ"),_xlpm.chp,AND($AB10<>"",$AB10<>"N/A",$AB10<>"No Min RQ"),_xlpm.usp,AND($AF10<>"",$AF10<>"N/A",$AF10<>"No Min RQ"),_xlpm.n,_xlpm.sfp+_xlpm.slp+_xlpm.ffp+_xlpm.chp+_xlpm.usp,_xlpm.sub,(_xlpm.sfp*($P10="Submitted"))+(_xlpm.slp*($T10="Submitted"))+(_xlpm.ffp*($X10="Submitted"))+(_xlpm.chp*($AB10="Submitted"))+(_xlpm.usp*($AF10="Submitted")),_xlpm.term,(_xlpm.sfp*OR($P10="Approved",$P10="Declined"))+(_xlpm.slp*OR($T10="Approved",$T10="Declined"))+(_xlpm.ffp*OR($X10="Approved",$X10="Declined"))+(_xlpm.chp*OR($AB10="Approved",$AB10="Declined"))+(_xlpm.usp*OR($AF10="Approved",$AF10="Declined")),IF(_xlpm.n=0,"No applicable lenders",IF(_xlpm.sub>0,"Stays with Shaw - lender still Submitted",IF(_xlpm.term=_xlpm.n,"Clear - all applicable lenders Approved or Declined","Stays with Shaw - not all lenders Approved or Declined")))))
A11: Tetra Walls, Inc. | B11: Tetra | D11: Trevor Taves | E11: 319-540-9542 | F11: trevor@tavesco.com | G11: Steve Stonebraker | H11: stonebraker@getfinti.com | I11: HVAC | K11: 1 | L11: =IF($A11="","",_xlfn.LET(_xlpm.ns,(--($P11="Ready 2 Submit"))+(--($T11="Ready 2 Submit"))+(--($X11="Ready 2 Submit"))+(--($AB11="Ready 2 Submit"))+(--($AF11="Ready 2 Submit")),_xlpm.wd,(--($P11="Waiting on Dealer"))+(--($T11="Waiting on Dealer"))+(--($X11="Waiting on Dealer"))+(--($AB11="Waiting on Dealer"))+(--($AF11="Waiting on Dealer")),_xlpm.sb,(--($P11="Submitted"))+(--($T11="Submitted"))+(--($X11="Submitted"))+(--($AB11="Submitted"))+(--($AF11="Submitted")),_xlpm.ap,(--($P11="Approved"))+(--($T11="Approved"))+(--($X11="Approved"))+(--($AB11="Approved"))+(--($AF11="Approved")),_xlpm.ac,(--($P11="Active"))+(--($T11="Active"))+(--($X11="Active"))+(--($AB11="Active"))+(--($AF11="Active")),_xlpm.dc,(--($P11="Declined"))+(--($T11="Declined"))+(--($X11="Declined"))+(--($AB11="Declined"))+(--($AF11="Declined")),_xlpm.aRS,(--($P11="Active"))*(--($R11="Yes"))+(--($T11="Active"))*(--($V11="Yes"))+(--($X11="Active"))*(--($Z11="Yes"))+(--($AB11="Active"))*(--($AD11="Yes"))+(--($AF11="Active"))*(--($AH11="Yes")),_xlpm.aDn,(--($P11="Active"))*(--($R11="Yes"))*(--((($S11="Yes")+($S11=TRUE))>0))+(--($T11="Active"))*(--($V11="Yes"))*(--((($W11="Yes")+($W11=TRUE))>0))+(--($X11="Active"))*(--($Z11="Yes"))*(--((($AA11="Yes")+($AA11=TRUE))>0))+(--($AB11="Active"))*(--($AD11="Yes"))*(--((($AE11="Yes")+($AE11=TRUE))>0))+(--($AF11="Active"))*(--($AH11="Yes"))*(--((($AI11="Yes")+($AI11=TRUE))>0)),_xlpm.inPlay,_xlpm.ns+_xlpm.wd+_xlpm.sb+_xlpm.ap,IF(AND(_xlpm.ac>0,_xlpm.inPlay=0,_xlpm.aDn=_xlpm.ac),"LIVE DLR",IF(AND(_xlpm.aRS>0,_xlpm.aDn<_xlpm.aRS),"Training",IF(_xlpm.aRS>0,"Active",IF(AND(_xlpm.dc>0,_xlpm.inPlay+_xlpm.ac=0),"Dead",IF(OR($CA11="Yes",$CA11=TRUE),"Rate Sheet",IF(AND($AJ11<>"",$AK11=FALSE),"Waiting on Dealer",IF(_xlpm.sb>0,"Waiting on Lender",IF(AND(_xlpm.ap+_xlpm.ac>0,_xlpm.ns+_xlpm.wd=0),"Rate Sheet","Application Submitted")))))))))) -> Active | M11: 46224 | N11: 46280 | O11: 1. Service 2. Foundation 3. Chowder | P11: Approved | Q11: 46274 | R11: No | S11: No | T11: Active | U11: 46274 | V11: Yes | W11: Yes | X11: Active | Y11: 46231 | Z11: No | AA11: No | AB11: Active | AC11: 46274 | AD11: Yes | AE11: Yes | AF11: N/A | AG11: =IF(OR(AG11="",AG11=0),IF($AF11="Submitted",TODAY(),""),AG11) | AH11: No | AI11: No | AJ11: In process see lender cells....7/23 recieved file share with all the docs needed. Tetra is still pending with SF 8/18/2026 | AK11: TRUE | AL11: {=IF($A11="","",SUMPRODUCT((CHOOSE({1,2,3,4,5},$R11,$V11,$Z11,$AD11,$AH11)="Yes")*(((CHOOSE({1,2,3,4,5},$S11,$W11,$AA11,$AE11,$AI11)="Yes")+(CHOOSE({1,2,3,4,5},$S11,$W11,$AA11,$AE11,$AI11)=TRUE))>0)))} -> 2 | AN11: =IF(OR($A11="",$AM11=""),"",TODAY()-$AM11) | AP11: 227125334 | AQ11: GA,MA,NY | AR11: tetra-finti@sunlightfinancial.com. syG9CRFpYO%7AO!IUr Dealer code: 939375 | AS11: GA | AT11: 36396000 | AU11: GA | AV11: 4112997000256801510 | BA11: 7 | BZ11: Unassigned | CA11: No | CB11: =IF($A11="","",_xlfn.LET(_xlpm.sfp,AND($P11<>"",$P11<>"N/A",$P11<>"No Min RQ"),_xlpm.slp,AND($T11<>"",$T11<>"N/A",$T11<>"No Min RQ"),_xlpm.ffp,AND($X11<>"",$X11<>"N/A",$X11<>"No Min RQ"),_xlpm.chp,AND($AB11<>"",$AB11<>"N/A",$AB11<>"No Min RQ"),_xlpm.usp,AND($AF11<>"",$AF11<>"N/A",$AF11<>"No Min RQ"),_xlpm.n,_xlpm.sfp+_xlpm.slp+_xlpm.ffp+_xlpm.chp+_xlpm.usp,_xlpm.sub,(_xlpm.sfp*($P11="Submitted"))+(_xlpm.slp*($T11="Submitted"))+(_xlpm.ffp*($X11="Submitted"))+(_xlpm.chp*($AB11="Submitted"))+(_xlpm.usp*($AF11="Submitted")),_xlpm.term,(_xlpm.sfp*OR($P11="Approved",$P11="Declined"))+(_xlpm.slp*OR($T11="Approved",$T11="Declined"))+(_xlpm.ffp*OR($X11="Approved",$X11="Declined"))+(_xlpm.chp*OR($AB11="Approved",$AB11="Declined"))+(_xlpm.usp*OR($AF11="Approved",$AF11="Declined")),IF(_xlpm.n=0,"No applicable lenders",IF(_xlpm.sub>0,"Stays with Shaw - lender still Submitted",IF(_xlpm.term=_xlpm.n,"Clear - all applicable lenders Approved or Declined","Stays with Shaw - not all lenders Approved or Declined")))))
A12: Black Sage Construction LLC | B12: Banyan Construction | D12: Brenda LaMont | E12: 801-372-6326 | F12: brenda@banyanbuild.com | G12: Clint Cowley | H12: sales@gowefund.com, clint@gowefund.com | I12: General Contractor | K12: 2 | L12: =IF($A12="","",_xlfn.LET(_xlpm.ns,(--($P12="Ready 2 Submit"))+(--($T12="Ready 2 Submit"))+(--($X12="Ready 2 Submit"))+(--($AB12="Ready 2 Submit"))+(--($AF12="Ready 2 Submit")),_xlpm.wd,(--($P12="Waiting on Dealer"))+(--($T12="Waiting on Dealer"))+(--($X12="Waiting on Dealer"))+(--($AB12="Waiting on Dealer"))+(--($AF12="Waiting on Dealer")),_xlpm.sb,(--($P12="Submitted"))+(--($T12="Submitted"))+(--($X12="Submitted"))+(--($AB12="Submitted"))+(--($AF12="Submitted")),_xlpm.ap,(--($P12="Approved"))+(--($T12="Approved"))+(--($X12="Approved"))+(--($AB12="Approved"))+(--($AF12="Approved")),_xlpm.ac,(--($P12="Active"))+(--($T12="Active"))+(--($X12="Active"))+(--($AB12="Active"))+(--($AF12="Active")),_xlpm.dc,(--($P12="Declined"))+(--($T12="Declined"))+(--($X12="Declined"))+(--($AB12="Declined"))+(--($AF12="Declined")),_xlpm.aRS,(--($P12="Active"))*(--($R12="Yes"))+(--($T12="Active"))*(--($V12="Yes"))+(--($X12="Active"))*(--($Z12="Yes"))+(--($AB12="Active"))*(--($AD12="Yes"))+(--($AF12="Active"))*(--($AH12="Yes")),_xlpm.aDn,(--($P12="Active"))*(--($R12="Yes"))*(--((($S12="Yes")+($S12=TRUE))>0))+(--($T12="Active"))*(--($V12="Yes"))*(--((($W12="Yes")+($W12=TRUE))>0))+(--($X12="Active"))*(--($Z12="Yes"))*(--((($AA12="Yes")+($AA12=TRUE))>0))+(--($AB12="Active"))*(--($AD12="Yes"))*(--((($AE12="Yes")+($AE12=TRUE))>0))+(--($AF12="Active"))*(--($AH12="Yes"))*(--((($AI12="Yes")+($AI12=TRUE))>0)),_xlpm.inPlay,_xlpm.ns+_xlpm.wd+_xlpm.sb+_xlpm.ap,IF(AND(_xlpm.ac>0,_xlpm.inPlay=0,_xlpm.aDn=_xlpm.ac),"LIVE DLR",IF(AND(_xlpm.aRS>0,_xlpm.aDn<_xlpm.aRS),"Training",IF(_xlpm.aRS>0,"Active",IF(AND(_xlpm.dc>0,_xlpm.inPlay+_xlpm.ac=0),"Dead",IF(OR($CA12="Yes",$CA12=TRUE),"Rate Sheet",IF(AND($AJ12<>"",$AK12=FALSE),"Waiting on Dealer",IF(_xlpm.sb>0,"Waiting on Lender",IF(AND(_xlpm.ap+_xlpm.ac>0,_xlpm.ns+_xlpm.wd=0),"Rate Sheet","Application Submitted")))))))))) -> Waiting on Lender | M12: 46225 | N12: 46280 | O12: FF, SF & SL | P12: Submitted | Q12: 46286 | R12: No | S12: No | T12: No Min RQ | U12: =IF(OR(U12="",U12=0),IF($T12="Submitted",TODAY(),""),U12) | V12: No | W12: No | X12: Approved | Y12: 46267 | Z12: No | AA12: No | AB12: N/A | AC12: =IF(OR(AC12="",AC12=0),IF($AB12="Submitted",TODAY(),""),AC12) | AD12: No | AE12: No | AF12: N/A | AG12: =IF(OR(AG12="",AG12=0),IF($AF12="Submitted",TODAY(),""),AG12) | AH12: No | AI12: No | AJ12: IDK how to catagorize in SFC APP. Foundation approved 9/21/26 - owner call done. | AK12: TRUE | AL12: {=IF($A12="","",SUMPRODUCT((CHOOSE({1,2,3,4,5},$R12,$V12,$Z12,$AD12,$AH12)="Yes")*(((CHOOSE({1,2,3,4,5},$S12,$W12,$AA12,$AE12,$AI12)="Yes")+(CHOOSE({1,2,3,4,5},$S12,$W12,$AA12,$AE12,$AI12)=TRUE))>0)))} -> 0 | AM12: 46281 | AN12: =IF(OR($A12="",$AM12=""),"",TODAY()-$AM12) -> 7 | AT12: 36579000 | BA12: 8 | BZ12: Unassigned | CA12: No | CB12: =IF($A12="","",_xlfn.LET(_xlpm.sfp,AND($P12<>"",$P12<>"N/A",$P12<>"No Min RQ"),_xlpm.slp,AND($T12<>"",$T12<>"N/A",$T12<>"No Min RQ"),_xlpm.ffp,AND($X12<>"",$X12<>"N/A",$X12<>"No Min RQ"),_xlpm.chp,AND($AB12<>"",$AB12<>"N/A",$AB12<>"No Min RQ"),_xlpm.usp,AND($AF12<>"",$AF12<>"N/A",$AF12<>"No Min RQ"),_xlpm.n,_xlpm.sfp+_xlpm.slp+_xlpm.ffp+_xlpm.chp+_xlpm.usp,_xlpm.sub,(_xlpm.sfp*($P12="Submitted"))+(_xlpm.slp*($T12="Submitted"))+(_xlpm.ffp*($X12="Submitted"))+(_xlpm.chp*($AB12="Submitted"))+(_xlpm.usp*($AF12="Submitted")),_xlpm.term,(_xlpm.sfp*OR($P12="Approved",$P12="Declined"))+(_xlpm.slp*OR($T12="Approved",$T12="Declined"))+(_xlpm.ffp*OR($X12="Approved",$X12="Declined"))+(_xlpm.chp*OR($AB12="Approved",$AB12="Declined"))+(_xlpm.usp*OR($AF12="Approved",$AF12="Declined")),IF(_xlpm.n=0,"No applicable lenders",IF(_xlpm.sub>0,"Stays with Shaw - lender still Submitted",IF(_xlpm.term=_xlpm.n,"Clear - all applicable lenders Approved or Declined","Stays with Shaw - not all lenders Approved or Declined")))))
A13: Vision Builders | B13: Vision Builders | D13: Nir Adani | E13: 818-699-2829 | F13: niradani@yahoo.com | G13: Clint Cowley | H13: sales@gowefund.com, clint@gowefund.com | I13: Roofing, Windows & Doors, Landscapping, Painting, Hardscaping, Flooring | K13: 2 | L13: =IF($A13="","",_xlfn.LET(_xlpm.ns,(--($P13="Ready 2 Submit"))+(--($T13="Ready 2 Submit"))+(--($X13="Ready 2 Submit"))+(--($AB13="Ready 2 Submit"))+(--($AF13="Ready 2 Submit")),_xlpm.wd,(--($P13="Waiting on Dealer"))+(--($T13="Waiting on Dealer"))+(--($X13="Waiting on Dealer"))+(--($AB13="Waiting on Dealer"))+(--($AF13="Waiting on Dealer")),_xlpm.sb,(--($P13="Submitted"))+(--($T13="Submitted"))+(--($X13="Submitted"))+(--($AB13="Submitted"))+(--($AF13="Submitted")),_xlpm.ap,(--($P13="Approved"))+(--($T13="Approved"))+(--($X13="Approved"))+(--($AB13="Approved"))+(--($AF13="Approved")),_xlpm.ac,(--($P13="Active"))+(--($T13="Active"))+(--($X13="Active"))+(--($AB13="Active"))+(--($AF13="Active")),_xlpm.dc,(--($P13="Declined"))+(--($T13="Declined"))+(--($X13="Declined"))+(--($AB13="Declined"))+(--($AF13="Declined")),_xlpm.aRS,(--($P13="Active"))*(--($R13="Yes"))+(--($T13="Active"))*(--($V13="Yes"))+(--($X13="Active"))*(--($Z13="Yes"))+(--($AB13="Active"))*(--($AD13="Yes"))+(--($AF13="Active"))*(--($AH13="Yes")),_xlpm.aDn,(--($P13="Active"))*(--($R13="Yes"))*(--((($S13="Yes")+($S13=TRUE))>0))+(--($T13="Active"))*(--($V13="Yes"))*(--((($W13="Yes")+($W13=TRUE))>0))+(--($X13="Active"))*(--($Z13="Yes"))*(--((($AA13="Yes")+($AA13=TRUE))>0))+(--($AB13="Active"))*(--($AD13="Yes"))*(--((($AE13="Yes")+($AE13=TRUE))>0))+(--($AF13="Active"))*(--($AH13="Yes"))*(--((($AI13="Yes")+($AI13=TRUE))>0)),_xlpm.inPlay,_xlpm.ns+_xlpm.wd+_xlpm.sb+_xlpm.ap,IF(AND(_xlpm.ac>0,_xlpm.inPlay=0,_xlpm.aDn=_xlpm.ac),"LIVE DLR",IF(AND(_xlpm.aRS>0,_xlpm.aDn<_xlpm.aRS),"Training",IF(_xlpm.aRS>0,"Active",IF(AND(_xlpm.dc>0,_xlpm.inPlay+_xlpm.ac=0),"Dead",IF(OR($CA13="Yes",$CA13=TRUE),"Rate Sheet",IF(AND($AJ13<>"",$AK13=FALSE),"Waiting on Dealer",IF(_xlpm.sb>0,"Waiting on Lender",IF(AND(_xlpm.ap+_xlpm.ac>0,_xlpm.ns+_xlpm.wd=0),"Rate Sheet","Application Submitted")))))))))) -> Dead | M13: 46230 | O13: FF, SF & SL | P13: Declined | Q13: =IF(OR(Q13="",Q13=0),IF($P13="Submitted",TODAY(),""),Q13) | R13: No | S13: No | T13: Declined | U13: =IF(OR(U13="",U13=0),IF($T13="Submitted",TODAY(),""),U13) | V13: No | W13: No | X13: Declined | Y13: =IF(OR(Y13="",Y13=0),IF($X13="Submitted",TODAY(),""),Y13) | Z13: No | AA13: No | AB13: N/A | AC13: =IF(OR(AC13="",AC13=0),IF($AB13="Submitted",TODAY(),""),AC13) | AD13: No | AE13: No | AF13: N/A | AG13: =IF(OR(AG13="",AG13=0),IF($AF13="Submitted",TODAY(),""),AG13) | AH13: No | AI13: No | AJ13: ALL lenders Declined | AK13: TRUE | AL13: {=IF($A13="","",SUMPRODUCT((CHOOSE({1,2,3,4,5},$R13,$V13,$Z13,$AD13,$AH13)="Yes")*(((CHOOSE({1,2,3,4,5},$S13,$W13,$AA13,$AE13,$AI13)="Yes")+(CHOOSE({1,2,3,4,5},$S13,$W13,$AA13,$AE13,$AI13)=TRUE))>0)))} -> 0 | AM13: 46265 | AN13: =IF(OR($A13="",$AM13=""),"",TODAY()-$AM13) -> 23 | BA13: 9 | BZ13: Unassigned | CA13: No | CB13: =IF($A13="","",_xlfn.LET(_xlpm.sfp,AND($P13<>"",$P13<>"N/A",$P13<>"No Min RQ"),_xlpm.slp,AND($T13<>"",$T13<>"N/A",$T13<>"No Min RQ"),_xlpm.ffp,AND($X13<>"",$X13<>"N/A",$X13<>"No Min RQ"),_xlpm.chp,AND($AB13<>"",$AB13<>"N/A",$AB13<>"No Min RQ"),_xlpm.usp,AND($AF13<>"",$AF13<>"N/A",$AF13<>"No Min RQ"),_xlpm.n,_xlpm.sfp+_xlpm.slp+_xlpm.ffp+_xlpm.chp+_xlpm.usp,_xlpm.sub,(_xlpm.sfp*($P13="Submitted"))+(_xlpm.slp*($T13="Submitted"))+(_xlpm.ffp*($X13="Submitted"))+(_xlpm.chp*($AB13="Submitted"))+(_xlpm.usp*($AF13="Submitted")),_xlpm.term,(_xlpm.sfp*OR($P13="Approved",$P13="Declined"))+(_xlpm.slp*OR($T13="Approved",$T13="Declined"))+(_xlpm.ffp*OR($X13="Approved",$X13="Declined"))+(_xlpm.chp*OR($AB13="Approved",$AB13="Declined"))+(_xlpm.usp*OR($AF13="Approved",$AF13="Declined")),IF(_xlpm.n=0,"No applicable lenders",IF(_xlpm.sub>0,"Stays with Shaw - lender still Submitted",IF(_xlpm.term=_xlpm.n,"Clear - all applicable lenders Approved or Declined","Stays with Shaw - not all lenders Approved or Declined")))))
A14: Qntum, LLC | B14: Qntum Roofing | D14: Dallen Gietz | E14: 310-351-5941 | F14: dallen@qntum.com | G14: Steve Stonebraker | H14: stonebraker@getfinti.com | I14: Roofing | K14: 1 | L14: =IF($A14="","",_xlfn.LET(_xlpm.ns,(--($P14="Ready 2 Submit"))+(--($T14="Ready 2 Submit"))+(--($X14="Ready 2 Submit"))+(--($AB14="Ready 2 Submit"))+(--($AF14="Ready 2 Submit")),_xlpm.wd,(--($P14="Waiting on Dealer"))+(--($T14="Waiting on Dealer"))+(--($X14="Waiting on Dealer"))+(--($AB14="Waiting on Dealer"))+(--($AF14="Waiting on Dealer")),_xlpm.sb,(--($P14="Submitted"))+(--($T14="Submitted"))+(--($X14="Submitted"))+(--($AB14="Submitted"))+(--($AF14="Submitted")),_xlpm.ap,(--($P14="Approved"))+(--($T14="Approved"))+(--($X14="Approved"))+(--($AB14="Approved"))+(--($AF14="Approved")),_xlpm.ac,(--($P14="Active"))+(--($T14="Active"))+(--($X14="Active"))+(--($AB14="Active"))+(--($AF14="Active")),_xlpm.dc,(--($P14="Declined"))+(--($T14="Declined"))+(--($X14="Declined"))+(--($AB14="Declined"))+(--($AF14="Declined")),_xlpm.aRS,(--($P14="Active"))*(--($R14="Yes"))+(--($T14="Active"))*(--($V14="Yes"))+(--($X14="Active"))*(--($Z14="Yes"))+(--($AB14="Active"))*(--($AD14="Yes"))+(--($AF14="Active"))*(--($AH14="Yes")),_xlpm.aDn,(--($P14="Active"))*(--($R14="Yes"))*(--((($S14="Yes")+($S14=TRUE))>0))+(--($T14="Active"))*(--($V14="Yes"))*(--((($W14="Yes")+($W14=TRUE))>0))+(--($X14="Active"))*(--($Z14="Yes"))*(--((($AA14="Yes")+($AA14=TRUE))>0))+(--($AB14="Active"))*(--($AD14="Yes"))*(--((($AE14="Yes")+($AE14=TRUE))>0))+(--($AF14="Active"))*(--($AH14="Yes"))*(--((($AI14="Yes")+($AI14=TRUE))>0)),_xlpm.inPlay,_xlpm.ns+_xlpm.wd+_xlpm.sb+_xlpm.ap,IF(AND(_xlpm.ac>0,_xlpm.inPlay=0,_xlpm.aDn=_xlpm.ac),"LIVE DLR",IF(AND(_xlpm.aRS>0,_xlpm.aDn<_xlpm.aRS),"Training",IF(_xlpm.aRS>0,"Active",IF(AND(_xlpm.dc>0,_xlpm.inPlay+_xlpm.ac=0),"Dead",IF(OR($CA14="Yes",$CA14=TRUE),"Rate Sheet",IF(AND($AJ14<>"",$AK14=FALSE),"Waiting on Dealer",IF(_xlpm.sb>0,"Waiting on Lender",IF(AND(_xlpm.ap+_xlpm.ac>0,_xlpm.ns+_xlpm.wd=0),"Rate Sheet","Application Submitted")))))))))) -> Rate Sheet | M14: 46231 | N14: 46280 | O14: SF, SL, FF need positions from Steve | P14: Active | Q14: 46274 | R14: No | S14: No | T14: Active | U14: 46274 | V14: No | W14: No | X14: Declined | Y14: =IF(OR(Y14="",Y14=0),IF($X14="Submitted",TODAY(),""),Y14) | Z14: No | AA14: No | AB14: N/A | AC14: =IF(OR(AC14="",AC14=0),IF($AB14="Submitted",TODAY(),""),AC14) | AD14: No | AE14: No | AF14: N/A | AG14: =IF(OR(AG14="",AG14=0),IF($AF14="Submitted",TODAY(),""),AG14) | AH14: No | AI14: No | AJ14: Submitted to lenders 8/25/26 | AK14: TRUE | AL14: {=IF($A14="","",SUMPRODUCT((CHOOSE({1,2,3,4,5},$R14,$V14,$Z14,$AD14,$AH14)="Yes")*(((CHOOSE({1,2,3,4,5},$S14,$W14,$AA14,$AE14,$AI14)="Yes")+(CHOOSE({1,2,3,4,5},$S14,$W14,$AA14,$AE14,$AI14)=TRUE))>0)))} -> 0 | AM14: 46273 | AN14: =IF(OR($A14="",$AM14=""),"",TODAY()-$AM14) -> 15 | AP14: 227125338 | AQ14: 227125338 | AR14: qntumllc-finti@sunlightfinancial.com; Dealer code: 601067 | BA14: 10 | BZ14: Unassigned | CA14: No | CB14: =IF($A14="","",_xlfn.LET(_xlpm.sfp,AND($P14<>"",$P14<>"N/A",$P14<>"No Min RQ"),_xlpm.slp,AND($T14<>"",$T14<>"N/A",$T14<>"No Min RQ"),_xlpm.ffp,AND($X14<>"",$X14<>"N/A",$X14<>"No Min RQ"),_xlpm.chp,AND($AB14<>"",$AB14<>"N/A",$AB14<>"No Min RQ"),_xlpm.usp,AND($AF14<>"",$AF14<>"N/A",$AF14<>"No Min RQ"),_xlpm.n,_xlpm.sfp+_xlpm.slp+_xlpm.ffp+_xlpm.chp+_xlpm.usp,_xlpm.sub,(_xlpm.sfp*($P14="Submitted"))+(_xlpm.slp*($T14="Submitted"))+(_xlpm.ffp*($X14="Submitted"))+(_xlpm.chp*($AB14="Submitted"))+(_xlpm.usp*($AF14="Submitted")),_xlpm.term,(_xlpm.sfp*OR($P14="Approved",$P14="Declined"))+(_xlpm.slp*OR($T14="Approved",$T14="Declined"))+(_xlpm.ffp*OR($X14="Approved",$X14="Declined"))+(_xlpm.chp*OR($AB14="Approved",$AB14="Declined"))+(_xlpm.usp*OR($AF14="Approved",$AF14="Declined")),IF(_xlpm.n=0,"No applicable lenders",IF(_xlpm.sub>0,"Stays with Shaw - lender still Submitted",IF(_xlpm.term=_xlpm.n,"Clear - all applicable lenders Approved or Declined","Stays with Shaw - not all lenders Approved or Declined")))))
A15: Roof Boyz LLC | B15: Roof Boyz | D15: Brennen Harris | E15: 307-203-9169 | F15: brennen@roof-boyz.com | G15: Evan Young | H15: evanyoung@getfinti.com | I15: Roofing | K15: 1 | L15: =IF($A15="","",_xlfn.LET(_xlpm.ns,(--($P15="Ready 2 Submit"))+(--($T15="Ready 2 Submit"))+(--($X15="Ready 2 Submit"))+(--($AB15="Ready 2 Submit"))+(--($AF15="Ready 2 Submit")),_xlpm.wd,(--($P15="Waiting on Dealer"))+(--($T15="Waiting on Dealer"))+(--($X15="Waiting on Dealer"))+(--($AB15="Waiting on Dealer"))+(--($AF15="Waiting on Dealer")),_xlpm.sb,(--($P15="Submitted"))+(--($T15="Submitted"))+(--($X15="Submitted"))+(--($AB15="Submitted"))+(--($AF15="Submitted")),_xlpm.ap,(--($P15="Approved"))+(--($T15="Approved"))+(--($X15="Approved"))+(--($AB15="Approved"))+(--($AF15="Approved")),_xlpm.ac,(--($P15="Active"))+(--($T15="Active"))+(--($X15="Active"))+(--($AB15="Active"))+(--($AF15="Active")),_xlpm.dc,(--($P15="Declined"))+(--($T15="Declined"))+(--($X15="Declined"))+(--($AB15="Declined"))+(--($AF15="Declined")),_xlpm.aRS,(--($P15="Active"))*(--($R15="Yes"))+(--($T15="Active"))*(--($V15="Yes"))+(--($X15="Active"))*(--($Z15="Yes"))+(--($AB15="Active"))*(--($AD15="Yes"))+(--($AF15="Active"))*(--($AH15="Yes")),_xlpm.aDn,(--($P15="Active"))*(--($R15="Yes"))*(--((($S15="Yes")+($S15=TRUE))>0))+(--($T15="Active"))*(--($V15="Yes"))*(--((($W15="Yes")+($W15=TRUE))>0))+(--($X15="Active"))*(--($Z15="Yes"))*(--((($AA15="Yes")+($AA15=TRUE))>0))+(--($AB15="Active"))*(--($AD15="Yes"))*(--((($AE15="Yes")+($AE15=TRUE))>0))+(--($AF15="Active"))*(--($AH15="Yes"))*(--((($AI15="Yes")+($AI15=TRUE))>0)),_xlpm.inPlay,_xlpm.ns+_xlpm.wd+_xlpm.sb+_xlpm.ap,IF(AND(_xlpm.ac>0,_xlpm.inPlay=0,_xlpm.aDn=_xlpm.ac),"LIVE DLR",IF(AND(_xlpm.aRS>0,_xlpm.aDn<_xlpm.aRS),"Training",IF(_xlpm.aRS>0,"Active",IF(AND(_xlpm.dc>0,_xlpm.inPlay+_xlpm.ac=0),"Dead",IF(OR($CA15="Yes",$CA15=TRUE),"Rate Sheet",IF(AND($AJ15<>"",$AK15=FALSE),"Waiting on Dealer",IF(_xlpm.sb>0,"Waiting on Lender",IF(AND(_xlpm.ap+_xlpm.ac>0,_xlpm.ns+_xlpm.wd=0),"Rate Sheet","Application Submitted")))))))))) -> Rate Sheet | M15: 46234 | N15: 46280 | O15: SF, FF | P15: Active | Q15: 46274 | R15: No | S15: No | T15: Approved | U15: 46274 | V15: No | W15: No | X15: Active | Y15: 45960 | Z15: No | AA15: No | AB15: N/A | AC15: =IF(OR(AC15="",AC15=0),IF($AB15="Submitted",TODAY(),""),AC15) | AD15: No | AE15: No | AF15: N/A | AG15: =IF(OR(AG15="",AG15=0),IF($AF15="Submitted",TODAY(),""),AG15) | AH15: No | AI15: No | AJ15: In process | AK15: TRUE | AL15: {=IF($A15="","",SUMPRODUCT((CHOOSE({1,2,3,4,5},$R15,$V15,$Z15,$AD15,$AH15)="Yes")*(((CHOOSE({1,2,3,4,5},$S15,$W15,$AA15,$AE15,$AI15)="Yes")+(CHOOSE({1,2,3,4,5},$S15,$W15,$AA15,$AE15,$AI15)=TRUE))>0)))} -> 0 | AM15: 46273 | AN15: =IF(OR($A15="",$AM15=""),"",TODAY()-$AM15) -> 15 | AP15: 815133226 | AQ15: AZ | AT15: 34146000 | AU15: AZ | BA15: 11 | BZ15: Unassigned | CA15: No | CB15: =IF($A15="","",_xlfn.LET(_xlpm.sfp,AND($P15<>"",$P15<>"N/A",$P15<>"No Min RQ"),_xlpm.slp,AND($T15<>"",$T15<>"N/A",$T15<>"No Min RQ"),_xlpm.ffp,AND($X15<>"",$X15<>"N/A",$X15<>"No Min RQ"),_xlpm.chp,AND($AB15<>"",$AB15<>"N/A",$AB15<>"No Min RQ"),_xlpm.usp,AND($AF15<>"",$AF15<>"N/A",$AF15<>"No Min RQ"),_xlpm.n,_xlpm.sfp+_xlpm.slp+_xlpm.ffp+_xlpm.chp+_xlpm.usp,_xlpm.sub,(_xlpm.sfp*($P15="Submitted"))+(_xlpm.slp*($T15="Submitted"))+(_xlpm.ffp*($X15="Submitted"))+(_xlpm.chp*($AB15="Submitted"))+(_xlpm.usp*($AF15="Submitted")),_xlpm.term,(_xlpm.sfp*OR($P15="Approved",$P15="Declined"))+(_xlpm.slp*OR($T15="Approved",$T15="Declined"))+(_xlpm.ffp*OR($X15="Approved",$X15="Declined"))+(_xlpm.chp*OR($AB15="Approved",$AB15="Declined"))+(_xlpm.usp*OR($AF15="Approved",$AF15="Declined")),IF(_xlpm.n=0,"No applicable lenders",IF(_xlpm.sub>0,"Stays with Shaw - lender still Submitted",IF(_xlpm.term=_xlpm.n,"Clear - all applicable lenders Approved or Declined","Stays with Shaw - not all lenders Approved or Declined")))))
A16: Agave Roofing LLC | B16: Agave Roofing LLC | C16: Sales Rabbit | D16: Jade Figueroa | E16: 623-321-5734 | F16: info@agaveroofing.com | G16: Steve Stonebraker | H16: stonebraker@getfinti.com | I16: Roofing | K16: 1 | L16: =IF($A16="","",_xlfn.LET(_xlpm.ns,(--($P16="Ready 2 Submit"))+(--($T16="Ready 2 Submit"))+(--($X16="Ready 2 Submit"))+(--($AB16="Ready 2 Submit"))+(--($AF16="Ready 2 Submit")),_xlpm.wd,(--($P16="Waiting on Dealer"))+(--($T16="Waiting on Dealer"))+(--($X16="Waiting on Dealer"))+(--($AB16="Waiting on Dealer"))+(--($AF16="Waiting on Dealer")),_xlpm.sb,(--($P16="Submitted"))+(--($T16="Submitted"))+(--($X16="Submitted"))+(--($AB16="Submitted"))+(--($AF16="Submitted")),_xlpm.ap,(--($P16="Approved"))+(--($T16="Approved"))+(--($X16="Approved"))+(--($AB16="Approved"))+(--($AF16="Approved")),_xlpm.ac,(--($P16="Active"))+(--($T16="Active"))+(--($X16="Active"))+(--($AB16="Active"))+(--($AF16="Active")),_xlpm.dc,(--($P16="Declined"))+(--($T16="Declined"))+(--($X16="Declined"))+(--($AB16="Declined"))+(--($AF16="Declined")),_xlpm.aRS,(--($P16="Active"))*(--($R16="Yes"))+(--($T16="Active"))*(--($V16="Yes"))+(--($X16="Active"))*(--($Z16="Yes"))+(--($AB16="Active"))*(--($AD16="Yes"))+(--($AF16="Active"))*(--($AH16="Yes")),_xlpm.aDn,(--($P16="Active"))*(--($R16="Yes"))*(--((($S16="Yes")+($S16=TRUE))>0))+(--($T16="Active"))*(--($V16="Yes"))*(--((($W16="Yes")+($W16=TRUE))>0))+(--($X16="Active"))*(--($Z16="Yes"))*(--((($AA16="Yes")+($AA16=TRUE))>0))+(--($AB16="Active"))*(--($AD16="Yes"))*(--((($AE16="Yes")+($AE16=TRUE))>0))+(--($AF16="Active"))*(--($AH16="Yes"))*(--((($AI16="Yes")+($AI16=TRUE))>0)),_xlpm.inPlay,_xlpm.ns+_xlpm.wd+_xlpm.sb+_xlpm.ap,IF(AND(_xlpm.ac>0,_xlpm.inPlay=0,_xlpm.aDn=_xlpm.ac),"LIVE DLR",IF(AND(_xlpm.aRS>0,_xlpm.aDn<_xlpm.aRS),"Training",IF(_xlpm.aRS>0,"Active",IF(AND(_xlpm.dc>0,_xlpm.inPlay+_xlpm.ac=0),"Dead",IF(OR($CA16="Yes",$CA16=TRUE),"Rate Sheet",IF(AND($AJ16<>"",$AK16=FALSE),"Waiting on Dealer",IF(_xlpm.sb>0,"Waiting on Lender",IF(AND(_xlpm.ap+_xlpm.ac>0,_xlpm.ns+_xlpm.wd=0),"Rate Sheet","Application Submitted")))))))))) -> Waiting on Dealer | M16: 46237 | N16: 46280 | P16: =IF($A16="","",IF($AK16=TRUE,"Ready 2 Submit","Waiting on Dealer")) -> Waiting on Dealer | Q16: =IF(OR(Q16="",Q16=0),IF($P16="Submitted",TODAY(),""),Q16) | R16: No | S16: No | T16: Declined | U16: =IF(OR(U16="",U16=0),IF($T16="Submitted",TODAY(),""),U16) | V16: No | W16: No | X16: =IF($A16="","",IF($AK16=TRUE,"Ready 2 Submit","Waiting on Dealer")) -> Waiting on Dealer | Y16: =IF(OR(Y16="",Y16=0),IF($X16="Submitted",TODAY(),""),Y16) | Z16: No | AA16: No | AB16: N/A | AC16: =IF(OR(AC16="",AC16=0),IF($AB16="Submitted",TODAY(),""),AC16) | AD16: No | AE16: No | AF16: N/A | AG16: =IF(OR(AG16="",AG16=0),IF($AF16="Submitted",TODAY(),""),AG16) | AH16: No | AI16: No | AJ16: dealer needs to finish application | AK16: FALSE | AL16: {=IF($A16="","",SUMPRODUCT((CHOOSE({1,2,3,4,5},$R16,$V16,$Z16,$AD16,$AH16)="Yes")*(((CHOOSE({1,2,3,4,5},$S16,$W16,$AA16,$AE16,$AI16)="Yes")+(CHOOSE({1,2,3,4,5},$S16,$W16,$AA16,$AE16,$AI16)=TRUE))>0)))} -> 0 | AM16: 46287 | AN16: =IF(OR($A16="",$AM16=""),"",TODAY()-$AM16) -> 1 | BA16: 12 | BZ16: Unassigned | CA16: No | CB16: =IF($A16="","",_xlfn.LET(_xlpm.sfp,AND($P16<>"",$P16<>"N/A",$P16<>"No Min RQ"),_xlpm.slp,AND($T16<>"",$T16<>"N/A",$T16<>"No Min RQ"),_xlpm.ffp,AND($X16<>"",$X16<>"N/A",$X16<>"No Min RQ"),_xlpm.chp,AND($AB16<>"",$AB16<>"N/A",$AB16<>"No Min RQ"),_xlpm.usp,AND($AF16<>"",$AF16<>"N/A",$AF16<>"No Min RQ"),_xlpm.n,_xlpm.sfp+_xlpm.slp+_xlpm.ffp+_xlpm.chp+_xlpm.usp,_xlpm.sub,(_xlpm.sfp*($P16="Submitted"))+(_xlpm.slp*($T16="Submitted"))+(_xlpm.ffp*($X16="Submitted"))+(_xlpm.chp*($AB16="Submitted"))+(_xlpm.usp*($AF16="Submitted")),_xlpm.term,(_xlpm.sfp*OR($P16="Approved",$P16="Declined"))+(_xlpm.slp*OR($T16="Approved",$T16="Declined"))+(_xlpm.ffp*OR($X16="Approved",$X16="Declined"))+(_xlpm.chp*OR($AB16="Approved",$AB16="Declined"))+(_xlpm.usp*OR($AF16="Approved",$AF16="Declined")),IF(_xlpm.n=0,"No applicable lenders",IF(_xlpm.sub>0,"Stays with Shaw - lender still Submitted",IF(_xlpm.term=_xlpm.n,"Clear - all applicable lenders Approved or Declined","Stays with Shaw - not all lenders Approved or Declined")))))
A17: Bluebird Turf Co | B17: Bluebird Turf | D17: Tyler Budge | E17: 801-518-6750 | F17: tyler@bluebirdturfco.com | G17: Spencer Jackson | H17: app.sj@icloud.com | I17: Turf | K17: 3 | L17: =IF($A17="","",_xlfn.LET(_xlpm.ns,(--($P17="Ready 2 Submit"))+(--($T17="Ready 2 Submit"))+(--($X17="Ready 2 Submit"))+(--($AB17="Ready 2 Submit"))+(--($AF17="Ready 2 Submit")),_xlpm.wd,(--($P17="Waiting on Dealer"))+(--($T17="Waiting on Dealer"))+(--($X17="Waiting on Dealer"))+(--($AB17="Waiting on Dealer"))+(--($AF17="Waiting on Dealer")),_xlpm.sb,(--($P17="Submitted"))+(--($T17="Submitted"))+(--($X17="Submitted"))+(--($AB17="Submitted"))+(--($AF17="Submitted")),_xlpm.ap,(--($P17="Approved"))+(--($T17="Approved"))+(--($X17="Approved"))+(--($AB17="Approved"))+(--($AF17="Approved")),_xlpm.ac,(--($P17="Active"))+(--($T17="Active"))+(--($X17="Active"))+(--($AB17="Active"))+(--($AF17="Active")),_xlpm.dc,(--($P17="Declined"))+(--($T17="Declined"))+(--($X17="Declined"))+(--($AB17="Declined"))+(--($AF17="Declined")),_xlpm.aRS,(--($P17="Active"))*(--($R17="Yes"))+(--($T17="Active"))*(--($V17="Yes"))+(--($X17="Active"))*(--($Z17="Yes"))+(--($AB17="Active"))*(--($AD17="Yes"))+(--($AF17="Active"))*(--($AH17="Yes")),_xlpm.aDn,(--($P17="Active"))*(--($R17="Yes"))*(--((($S17="Yes")+($S17=TRUE))>0))+(--($T17="Active"))*(--($V17="Yes"))*(--((($W17="Yes")+($W17=TRUE))>0))+(--($X17="Active"))*(--($Z17="Yes"))*(--((($AA17="Yes")+($AA17=TRUE))>0))+(--($AB17="Active"))*(--($AD17="Yes"))*(--((($AE17="Yes")+($AE17=TRUE))>0))+(--($AF17="Active"))*(--($AH17="Yes"))*(--((($AI17="Yes")+($AI17=TRUE))>0)),_xlpm.inPlay,_xlpm.ns+_xlpm.wd+_xlpm.sb+_xlpm.ap,IF(AND(_xlpm.ac>0,_xlpm.inPlay=0,_xlpm.aDn=_xlpm.ac),"LIVE DLR",IF(AND(_xlpm.aRS>0,_xlpm.aDn<_xlpm.aRS),"Training",IF(_xlpm.aRS>0,"Active",IF(AND(_xlpm.dc>0,_xlpm.inPlay+_xlpm.ac=0),"Dead",IF(OR($CA17="Yes",$CA17=TRUE),"Rate Sheet",IF(AND($AJ17<>"",$AK17=FALSE),"Waiting on Dealer",IF(_xlpm.sb>0,"Waiting on Lender",IF(AND(_xlpm.ap+_xlpm.ac>0,_xlpm.ns+_xlpm.wd=0),"Rate Sheet","Application Submitted")))))))))) -> Rate Sheet | M17: 46239 | N17: 46280 | O17: FF | P17: N/A | Q17: =IF(OR(Q17="",Q17=0),IF($P17="Submitted",TODAY(),""),Q17) | R17: No | S17: No | T17: N/A | U17: =IF(OR(U17="",U17=0),IF($T17="Submitted",TODAY(),""),U17) | V17: No | W17: No | X17: Approved | Y17: 46259 | Z17: No | AA17: No | AB17: N/A | AC17: =IF(OR(AC17="",AC17=0),IF($AB17="Submitted",TODAY(),""),AC17) | AD17: No | AE17: No | AF17: N/A | AG17: =IF(OR(AG17="",AG17=0),IF($AF17="Submitted",TODAY(),""),AG17) | AH17: No | AI17: No | AJ17: Owner call complete - FFC registration approved 9/2/26 | AK17: TRUE | AL17: {=IF($A17="","",SUMPRODUCT((CHOOSE({1,2,3,4,5},$R17,$V17,$Z17,$AD17,$AH17)="Yes")*(((CHOOSE({1,2,3,4,5},$S17,$W17,$AA17,$AE17,$AI17)="Yes")+(CHOOSE({1,2,3,4,5},$S17,$W17,$AA17,$AE17,$AI17)=TRUE))>0)))} -> 0 | AM17: 46274 | AN17: =IF(OR($A17="",$AM17=""),"",TODAY()-$AM17) -> 14 | AT17: 36443000 | BA17: 13 | BZ17: Unassigned | CA17: No | CB17: =IF($A17="","",_xlfn.LET(_xlpm.sfp,AND($P17<>"",$P17<>"N/A",$P17<>"No Min RQ"),_xlpm.slp,AND($T17<>"",$T17<>"N/A",$T17<>"No Min RQ"),_xlpm.ffp,AND($X17<>"",$X17<>"N/A",$X17<>"No Min RQ"),_xlpm.chp,AND($AB17<>"",$AB17<>"N/A",$AB17<>"No Min RQ"),_xlpm.usp,AND($AF17<>"",$AF17<>"N/A",$AF17<>"No Min RQ"),_xlpm.n,_xlpm.sfp+_xlpm.slp+_xlpm.ffp+_xlpm.chp+_xlpm.usp,_xlpm.sub,(_xlpm.sfp*($P17="Submitted"))+(_xlpm.slp*($T17="Submitted"))+(_xlpm.ffp*($X17="Submitted"))+(_xlpm.chp*($AB17="Submitted"))+(_xlpm.usp*($AF17="Submitted")),_xlpm.term,(_xlpm.sfp*OR($P17="Approved",$P17="Declined"))+(_xlpm.slp*OR($T17="Approved",$T17="Declined"))+(_xlpm.ffp*OR($X17="Approved",$X17="Declined"))+(_xlpm.chp*OR($AB17="Approved",$AB17="Declined"))+(_xlpm.usp*OR($AF17="Approved",$AF17="Declined")),IF(_xlpm.n=0,"No applicable lenders",IF(_xlpm.sub>0,"Stays with Shaw - lender still Submitted",IF(_xlpm.term=_xlpm.n,"Clear - all applicable lenders Approved or Declined","Stays with Shaw - not all lenders Approved or Declined")))))
A18: Wires and Wifi, LLC | B18: Wires and Wifi | D18: Kyle Gray | E18: 801-382-9923 | F18: kyle@wiresandwifi.com | G18: David Yates | H18: David.yates@getfinti.com | I18: Electronic Shades, Home Theaters and more | K18: 2 | L18: =IF($A18="","",_xlfn.LET(_xlpm.ns,(--($P18="Ready 2 Submit"))+(--($T18="Ready 2 Submit"))+(--($X18="Ready 2 Submit"))+(--($AB18="Ready 2 Submit"))+(--($AF18="Ready 2 Submit")),_xlpm.wd,(--($P18="Waiting on Dealer"))+(--($T18="Waiting on Dealer"))+(--($X18="Waiting on Dealer"))+(--($AB18="Waiting on Dealer"))+(--($AF18="Waiting on Dealer")),_xlpm.sb,(--($P18="Submitted"))+(--($T18="Submitted"))+(--($X18="Submitted"))+(--($AB18="Submitted"))+(--($AF18="Submitted")),_xlpm.ap,(--($P18="Approved"))+(--($T18="Approved"))+(--($X18="Approved"))+(--($AB18="Approved"))+(--($AF18="Approved")),_xlpm.ac,(--($P18="Active"))+(--($T18="Active"))+(--($X18="Active"))+(--($AB18="Active"))+(--($AF18="Active")),_xlpm.dc,(--($P18="Declined"))+(--($T18="Declined"))+(--($X18="Declined"))+(--($AB18="Declined"))+(--($AF18="Declined")),_xlpm.aRS,(--($P18="Active"))*(--($R18="Yes"))+(--($T18="Active"))*(--($V18="Yes"))+(--($X18="Active"))*(--($Z18="Yes"))+(--($AB18="Active"))*(--($AD18="Yes"))+(--($AF18="Active"))*(--($AH18="Yes")),_xlpm.aDn,(--($P18="Active"))*(--($R18="Yes"))*(--((($S18="Yes")+($S18=TRUE))>0))+(--($T18="Active"))*(--($V18="Yes"))*(--((($W18="Yes")+($W18=TRUE))>0))+(--($X18="Active"))*(--($Z18="Yes"))*(--((($AA18="Yes")+($AA18=TRUE))>0))+(--($AB18="Active"))*(--($AD18="Yes"))*(--((($AE18="Yes")+($AE18=TRUE))>0))+(--($AF18="Active"))*(--($AH18="Yes"))*(--((($AI18="Yes")+($AI18=TRUE))>0)),_xlpm.inPlay,_xlpm.ns+_xlpm.wd+_xlpm.sb+_xlpm.ap,IF(AND(_xlpm.ac>0,_xlpm.inPlay=0,_xlpm.aDn=_xlpm.ac),"LIVE DLR",IF(AND(_xlpm.aRS>0,_xlpm.aDn<_xlpm.aRS),"Training",IF(_xlpm.aRS>0,"Active",IF(AND(_xlpm.dc>0,_xlpm.inPlay+_xlpm.ac=0),"Dead",IF(OR($CA18="Yes",$CA18=TRUE),"Rate Sheet",IF(AND($AJ18<>"",$AK18=FALSE),"Waiting on Dealer",IF(_xlpm.sb>0,"Waiting on Lender",IF(AND(_xlpm.ap+_xlpm.ac>0,_xlpm.ns+_xlpm.wd=0),"Rate Sheet","Application Submitted")))))))))) -> Dead | M18: 46239 | O18: SF, SL, FF | P18: N/A | Q18: =IF(OR(Q18="",Q18=0),IF($P18="Submitted",TODAY(),""),Q18) | R18: N/A | S18: No | T18: N/A | U18: =IF(OR(U18="",U18=0),IF($T18="Submitted",TODAY(),""),U18) | V18: N/A | W18: No | X18: Declined | Y18: =IF(OR(Y18="",Y18=0),IF($X18="Submitted",TODAY(),""),Y18) | Z18: No | AA18: No | AB18: N/A | AC18: =IF(OR(AC18="",AC18=0),IF($AB18="Submitted",TODAY(),""),AC18) | AD18: No | AE18: No | AF18: N/A | AG18: =IF(OR(AG18="",AG18=0),IF($AF18="Submitted",TODAY(),""),AG18) | AH18: No | AI18: No | AJ18: Submitted to FF--Emailed for Voided Check. | AK18: TRUE | AL18: {=IF($A18="","",SUMPRODUCT((CHOOSE({1,2,3,4,5},$R18,$V18,$Z18,$AD18,$AH18)="Yes")*(((CHOOSE({1,2,3,4,5},$S18,$W18,$AA18,$AE18,$AI18)="Yes")+(CHOOSE({1,2,3,4,5},$S18,$W18,$AA18,$AE18,$AI18)=TRUE))>0)))} -> 0 | AM18: 46266 | AN18: =IF(OR($A18="",$AM18=""),"",TODAY()-$AM18) -> 22 | BA18: 14 | BZ18: Unassigned | CA18: No | CB18: =IF($A18="","",_xlfn.LET(_xlpm.sfp,AND($P18<>"",$P18<>"N/A",$P18<>"No Min RQ"),_xlpm.slp,AND($T18<>"",$T18<>"N/A",$T18<>"No Min RQ"),_xlpm.ffp,AND($X18<>"",$X18<>"N/A",$X18<>"No Min RQ"),_xlpm.chp,AND($AB18<>"",$AB18<>"N/A",$AB18<>"No Min RQ"),_xlpm.usp,AND($AF18<>"",$AF18<>"N/A",$AF18<>"No Min RQ"),_xlpm.n,_xlpm.sfp+_xlpm.slp+_xlpm.ffp+_xlpm.chp+_xlpm.usp,_xlpm.sub,(_xlpm.sfp*($P18="Submitted"))+(_xlpm.slp*($T18="Submitted"))+(_xlpm.ffp*($X18="Submitted"))+(_xlpm.chp*($AB18="Submitted"))+(_xlpm.usp*($AF18="Submitted")),_xlpm.term,(_xlpm.sfp*OR($P18="Approved",$P18="Declined"))+(_xlpm.slp*OR($T18="Approved",$T18="Declined"))+(_xlpm.ffp*OR($X18="Approved",$X18="Declined"))+(_xlpm.chp*OR($AB18="Approved",$AB18="Declined"))+(_xlpm.usp*OR($AF18="Approved",$AF18="Declined")),IF(_xlpm.n=0,"No applicable lenders",IF(_xlpm.sub>0,"Stays with Shaw - lender still Submitted",IF(_xlpm.term=_xlpm.n,"Clear - all applicable lenders Approved or Declined","Stays with Shaw - not all lenders Approved or Declined")))))
A19: L.A.B.A LLC | B19: LABA Roofing LLC | D19: Luis Aviles | E19: 940-765-1109 | F19: luis@labaroof.com | G19: Steve Stonebraker | H19: stonebraker@getfinti.com | I19: Roofing | K19: 1 | L19: =IF($A19="","",_xlfn.LET(_xlpm.ns,(--($P19="Ready 2 Submit"))+(--($T19="Ready 2 Submit"))+(--($X19="Ready 2 Submit"))+(--($AB19="Ready 2 Submit"))+(--($AF19="Ready 2 Submit")),_xlpm.wd,(--($P19="Waiting on Dealer"))+(--($T19="Waiting on Dealer"))+(--($X19="Waiting on Dealer"))+(--($AB19="Waiting on Dealer"))+(--($AF19="Waiting on Dealer")),_xlpm.sb,(--($P19="Submitted"))+(--($T19="Submitted"))+(--($X19="Submitted"))+(--($AB19="Submitted"))+(--($AF19="Submitted")),_xlpm.ap,(--($P19="Approved"))+(--($T19="Approved"))+(--($X19="Approved"))+(--($AB19="Approved"))+(--($AF19="Approved")),_xlpm.ac,(--($P19="Active"))+(--($T19="Active"))+(--($X19="Active"))+(--($AB19="Active"))+(--($AF19="Active")),_xlpm.dc,(--($P19="Declined"))+(--($T19="Declined"))+(--($X19="Declined"))+(--($AB19="Declined"))+(--($AF19="Declined")),_xlpm.aRS,(--($P19="Active"))*(--($R19="Yes"))+(--($T19="Active"))*(--($V19="Yes"))+(--($X19="Active"))*(--($Z19="Yes"))+(--($AB19="Active"))*(--($AD19="Yes"))+(--($AF19="Active"))*(--($AH19="Yes")),_xlpm.aDn,(--($P19="Active"))*(--($R19="Yes"))*(--((($S19="Yes")+($S19=TRUE))>0))+(--($T19="Active"))*(--($V19="Yes"))*(--((($W19="Yes")+($W19=TRUE))>0))+(--($X19="Active"))*(--($Z19="Yes"))*(--((($AA19="Yes")+($AA19=TRUE))>0))+(--($AB19="Active"))*(--($AD19="Yes"))*(--((($AE19="Yes")+($AE19=TRUE))>0))+(--($AF19="Active"))*(--($AH19="Yes"))*(--((($AI19="Yes")+($AI19=TRUE))>0)),_xlpm.inPlay,_xlpm.ns+_xlpm.wd+_xlpm.sb+_xlpm.ap,IF(AND(_xlpm.ac>0,_xlpm.inPlay=0,_xlpm.aDn=_xlpm.ac),"LIVE DLR",IF(AND(_xlpm.aRS>0,_xlpm.aDn<_xlpm.aRS),"Training",IF(_xlpm.aRS>0,"Active",IF(AND(_xlpm.dc>0,_xlpm.inPlay+_xlpm.ac=0),"Dead",IF(OR($CA19="Yes",$CA19=TRUE),"Rate Sheet",IF(AND($AJ19<>"",$AK19=FALSE),"Waiting on Dealer",IF(_xlpm.sb>0,"Waiting on Lender",IF(AND(_xlpm.ap+_xlpm.ac>0,_xlpm.ns+_xlpm.wd=0),"Rate Sheet","Application Submitted")))))))))) -> Waiting on Dealer | M19: 46241 | N19: 46280 | O19: SF, SL, FF | P19: Submitted | Q19: 46279 | R19: No | S19: No | T19: Declined | U19: 46274 | V19: No | W19: No | X19: Submitted | Y19: 46274 | Z19: No | AA19: No | AB19: N/A | AC19: =IF(OR(AC19="",AC19=0),IF($AB19="Submitted",TODAY(),""),AC19) | AD19: No | AE19: No | AF19: N/A | AG19: =IF(OR(AG19="",AG19=0),IF($AF19="Submitted",TODAY(),""),AG19) | AH19: No | AI19: No | AJ19: FF owner call complete - FFC needs ownership documentation | AK19: FALSE | AL19: {=IF($A19="","",SUMPRODUCT((CHOOSE({1,2,3,4,5},$R19,$V19,$Z19,$AD19,$AH19)="Yes")*(((CHOOSE({1,2,3,4,5},$S19,$W19,$AA19,$AE19,$AI19)="Yes")+(CHOOSE({1,2,3,4,5},$S19,$W19,$AA19,$AE19,$AI19)=TRUE))>0)))} -> 0 | AM19: 46287 | AN19: =IF(OR($A19="",$AM19=""),"",TODAY()-$AM19) -> 1 | BA19: 15 | BZ19: Unassigned | CA19: No | CB19: =IF($A19="","",_xlfn.LET(_xlpm.sfp,AND($P19<>"",$P19<>"N/A",$P19<>"No Min RQ"),_xlpm.slp,AND($T19<>"",$T19<>"N/A",$T19<>"No Min RQ"),_xlpm.ffp,AND($X19<>"",$X19<>"N/A",$X19<>"No Min RQ"),_xlpm.chp,AND($AB19<>"",$AB19<>"N/A",$AB19<>"No Min RQ"),_xlpm.usp,AND($AF19<>"",$AF19<>"N/A",$AF19<>"No Min RQ"),_xlpm.n,_xlpm.sfp+_xlpm.slp+_xlpm.ffp+_xlpm.chp+_xlpm.usp,_xlpm.sub,(_xlpm.sfp*($P19="Submitted"))+(_xlpm.slp*($T19="Submitted"))+(_xlpm.ffp*($X19="Submitted"))+(_xlpm.chp*($AB19="Submitted"))+(_xlpm.usp*($AF19="Submitted")),_xlpm.term,(_xlpm.sfp*OR($P19="Approved",$P19="Declined"))+(_xlpm.slp*OR($T19="Approved",$T19="Declined"))+(_xlpm.ffp*OR($X19="Approved",$X19="Declined"))+(_xlpm.chp*OR($AB19="Approved",$AB19="Declined"))+(_xlpm.usp*OR($AF19="Approved",$AF19="Declined")),IF(_xlpm.n=0,"No applicable lenders",IF(_xlpm.sub>0,"Stays with Shaw - lender still Submitted",IF(_xlpm.term=_xlpm.n,"Clear - all applicable lenders Approved or Declined","Stays with Shaw - not all lenders Approved or Declined")))))
A20: Supreme Home Services LLC | B20: Supreme Home Roofing and Construction | D20: Tyler Bradshaw | E20: 801-837-9943 | F20: tyler@mysupremehome.com | G20: Evan Young | H20: evanyoung@getfinti.com | I20: Roofing | K20: 3 | L20: =IF($A20="","",_xlfn.LET(_xlpm.ns,(--($P20="Ready 2 Submit"))+(--($T20="Ready 2 Submit"))+(--($X20="Ready 2 Submit"))+(--($AB20="Ready 2 Submit"))+(--($AF20="Ready 2 Submit")),_xlpm.wd,(--($P20="Waiting on Dealer"))+(--($T20="Waiting on Dealer"))+(--($X20="Waiting on Dealer"))+(--($AB20="Waiting on Dealer"))+(--($AF20="Waiting on Dealer")),_xlpm.sb,(--($P20="Submitted"))+(--($T20="Submitted"))+(--($X20="Submitted"))+(--($AB20="Submitted"))+(--($AF20="Submitted")),_xlpm.ap,(--($P20="Approved"))+(--($T20="Approved"))+(--($X20="Approved"))+(--($AB20="Approved"))+(--($AF20="Approved")),_xlpm.ac,(--($P20="Active"))+(--($T20="Active"))+(--($X20="Active"))+(--($AB20="Active"))+(--($AF20="Active")),_xlpm.dc,(--($P20="Declined"))+(--($T20="Declined"))+(--($X20="Declined"))+(--($AB20="Declined"))+(--($AF20="Declined")),_xlpm.aRS,(--($P20="Active"))*(--($R20="Yes"))+(--($T20="Active"))*(--($V20="Yes"))+(--($X20="Active"))*(--($Z20="Yes"))+(--($AB20="Active"))*(--($AD20="Yes"))+(--($AF20="Active"))*(--($AH20="Yes")),_xlpm.aDn,(--($P20="Active"))*(--($R20="Yes"))*(--((($S20="Yes")+($S20=TRUE))>0))+(--($T20="Active"))*(--($V20="Yes"))*(--((($W20="Yes")+($W20=TRUE))>0))+(--($X20="Active"))*(--($Z20="Yes"))*(--((($AA20="Yes")+($AA20=TRUE))>0))+(--($AB20="Active"))*(--($AD20="Yes"))*(--((($AE20="Yes")+($AE20=TRUE))>0))+(--($AF20="Active"))*(--($AH20="Yes"))*(--((($AI20="Yes")+($AI20=TRUE))>0)),_xlpm.inPlay,_xlpm.ns+_xlpm.wd+_xlpm.sb+_xlpm.ap,IF(AND(_xlpm.ac>0,_xlpm.inPlay=0,_xlpm.aDn=_xlpm.ac),"LIVE DLR",IF(AND(_xlpm.aRS>0,_xlpm.aDn<_xlpm.aRS),"Training",IF(_xlpm.aRS>0,"Active",IF(AND(_xlpm.dc>0,_xlpm.inPlay+_xlpm.ac=0),"Dead",IF(OR($CA20="Yes",$CA20=TRUE),"Rate Sheet",IF(AND($AJ20<>"",$AK20=FALSE),"Waiting on Dealer",IF(_xlpm.sb>0,"Waiting on Lender",IF(AND(_xlpm.ap+_xlpm.ac>0,_xlpm.ns+_xlpm.wd=0),"Rate Sheet","Application Submitted")))))))))) -> Dead | M20: 46242 | N20: 46280 | O20: FF, SF. | P20: Declined | Q20: 46279 | R20: No | S20: No | T20: N/A | U20: =IF(OR(U20="",U20=0),IF($T20="Submitted",TODAY(),""),U20) | V20: No | W20: No | X20: Declined | Y20: =IF(OR(Y20="",Y20=0),IF($X20="Submitted",TODAY(),""),Y20) | Z20: No | AA20: No | AB20: N/A | AC20: =IF(OR(AC20="",AC20=0),IF($AB20="Submitted",TODAY(),""),AC20) | AD20: No | AE20: No | AF20: N/A | AG20: =IF(OR(AG20="",AG20=0),IF($AF20="Submitted",TODAY(),""),AG20) | AH20: No | AI20: No | AJ20: Tyler needs to complete SFC email. | AK20: TRUE | AL20: {=IF($A20="","",SUMPRODUCT((CHOOSE({1,2,3,4,5},$R20,$V20,$Z20,$AD20,$AH20)="Yes")*(((CHOOSE({1,2,3,4,5},$S20,$W20,$AA20,$AE20,$AI20)="Yes")+(CHOOSE({1,2,3,4,5},$S20,$W20,$AA20,$AE20,$AI20)=TRUE))>0)))} -> 0 | AM20: 46279 | AN20: =IF(OR($A20="",$AM20=""),"",TODAY()-$AM20) -> 9 | BA20: 16 | BZ20: Unassigned | CA20: No | CB20: =IF($A20="","",_xlfn.LET(_xlpm.sfp,AND($P20<>"",$P20<>"N/A",$P20<>"No Min RQ"),_xlpm.slp,AND($T20<>"",$T20<>"N/A",$T20<>"No Min RQ"),_xlpm.ffp,AND($X20<>"",$X20<>"N/A",$X20<>"No Min RQ"),_xlpm.chp,AND($AB20<>"",$AB20<>"N/A",$AB20<>"No Min RQ"),_xlpm.usp,AND($AF20<>"",$AF20<>"N/A",$AF20<>"No Min RQ"),_xlpm.n,_xlpm.sfp+_xlpm.slp+_xlpm.ffp+_xlpm.chp+_xlpm.usp,_xlpm.sub,(_xlpm.sfp*($P20="Submitted"))+(_xlpm.slp*($T20="Submitted"))+(_xlpm.ffp*($X20="Submitted"))+(_xlpm.chp*($AB20="Submitted"))+(_xlpm.usp*($AF20="Submitted")),_xlpm.term,(_xlpm.sfp*OR($P20="Approved",$P20="Declined"))+(_xlpm.slp*OR($T20="Approved",$T20="Declined"))+(_xlpm.ffp*OR($X20="Approved",$X20="Declined"))+(_xlpm.chp*OR($AB20="Approved",$AB20="Declined"))+(_xlpm.usp*OR($AF20="Approved",$AF20="Declined")),IF(_xlpm.n=0,"No applicable lenders",IF(_xlpm.sub>0,"Stays with Shaw - lender still Submitted",IF(_xlpm.term=_xlpm.n,"Clear - all applicable lenders Approved or Declined","Stays with Shaw - not all lenders Approved or Declined")))))
A21: AZ Insulation & Energy Solutions | B21: AZ Insulation & HVAC Solutions | D21: Robert Ellsworth | E21: 602-320-5111 | F21: rob@az-insulation.com | G21: Tyler Mickelsen | H21: tyler@getfinti.com | I21: HVAC | K21: 1 | L21: =IF($A21="","",_xlfn.LET(_xlpm.ns,(--($P21="Ready 2 Submit"))+(--($T21="Ready 2 Submit"))+(--($X21="Ready 2 Submit"))+(--($AB21="Ready 2 Submit"))+(--($AF21="Ready 2 Submit")),_xlpm.wd,(--($P21="Waiting on Dealer"))+(--($T21="Waiting on Dealer"))+(--($X21="Waiting on Dealer"))+(--($AB21="Waiting on Dealer"))+(--($AF21="Waiting on Dealer")),_xlpm.sb,(--($P21="Submitted"))+(--($T21="Submitted"))+(--($X21="Submitted"))+(--($AB21="Submitted"))+(--($AF21="Submitted")),_xlpm.ap,(--($P21="Approved"))+(--($T21="Approved"))+(--($X21="Approved"))+(--($AB21="Approved"))+(--($AF21="Approved")),_xlpm.ac,(--($P21="Active"))+(--($T21="Active"))+(--($X21="Active"))+(--($AB21="Active"))+(--($AF21="Active")),_xlpm.dc,(--($P21="Declined"))+(--($T21="Declined"))+(--($X21="Declined"))+(--($AB21="Declined"))+(--($AF21="Declined")),_xlpm.aRS,(--($P21="Active"))*(--($R21="Yes"))+(--($T21="Active"))*(--($V21="Yes"))+(--($X21="Active"))*(--($Z21="Yes"))+(--($AB21="Active"))*(--($AD21="Yes"))+(--($AF21="Active"))*(--($AH21="Yes")),_xlpm.aDn,(--($P21="Active"))*(--($R21="Yes"))*(--((($S21="Yes")+($S21=TRUE))>0))+(--($T21="Active"))*(--($V21="Yes"))*(--((($W21="Yes")+($W21=TRUE))>0))+(--($X21="Active"))*(--($Z21="Yes"))*(--((($AA21="Yes")+($AA21=TRUE))>0))+(--($AB21="Active"))*(--($AD21="Yes"))*(--((($AE21="Yes")+($AE21=TRUE))>0))+(--($AF21="Active"))*(--($AH21="Yes"))*(--((($AI21="Yes")+($AI21=TRUE))>0)),_xlpm.inPlay,_xlpm.ns+_xlpm.wd+_xlpm.sb+_xlpm.ap,IF(AND(_xlpm.ac>0,_xlpm.inPlay=0,_xlpm.aDn=_xlpm.ac),"LIVE DLR",IF(AND(_xlpm.aRS>0,_xlpm.aDn<_xlpm.aRS),"Training",IF(_xlpm.aRS>0,"Active",IF(AND(_xlpm.dc>0,_xlpm.inPlay+_xlpm.ac=0),"Dead",IF(OR($CA21="Yes",$CA21=TRUE),"Rate Sheet",IF(AND($AJ21<>"",$AK21=FALSE),"Waiting on Dealer",IF(_xlpm.sb>0,"Waiting on Lender",IF(AND(_xlpm.ap+_xlpm.ac>0,_xlpm.ns+_xlpm.wd=0),"Rate Sheet","Application Submitted")))))))))) -> Training | M21: 46305 | N21: 46280 | O21: SF, SL, FF, Chow | P21: Approved | Q21: 46274 | R21: No | S21: No | T21: Active | U21: 46274 | V21: Yes | W21: Yes | X21: Active | Y21: 46246 | Z21: Yes | AA21: No | AB21: Active | AC21: 46274 | AD21: Yes | AE21: Yes | AF21: N/A | AG21: =IF(OR(AG21="",AG21=0),IF($AF21="Submitted",TODAY(),""),AG21) | AH21: No | AI21: No | AJ21: Active with FF, Sunlight and Chowder, waiting to hear back on SF | AK21: TRUE | AL21: {=IF($A21="","",SUMPRODUCT((CHOOSE({1,2,3,4,5},$R21,$V21,$Z21,$AD21,$AH21)="Yes")*(((CHOOSE({1,2,3,4,5},$S21,$W21,$AA21,$AE21,$AI21)="Yes")+(CHOOSE({1,2,3,4,5},$S21,$W21,$AA21,$AE21,$AI21)=TRUE))>0)))} -> 2 | AN21: =IF(OR($A21="",$AM21=""),"",TODAY()-$AM21) | AP21: 227125336 | AR21: azinsulation-finti@sunlightfinancial.com Dealer code: 796319 | AT21: 36351000 | AV21: 4112997000271972998 | BA21: 17 | BZ21: Unassigned | CA21: No | CB21: =IF($A21="","",_xlfn.LET(_xlpm.sfp,AND($P21<>"",$P21<>"N/A",$P21<>"No Min RQ"),_xlpm.slp,AND($T21<>"",$T21<>"N/A",$T21<>"No Min RQ"),_xlpm.ffp,AND($X21<>"",$X21<>"N/A",$X21<>"No Min RQ"),_xlpm.chp,AND($AB21<>"",$AB21<>"N/A",$AB21<>"No Min RQ"),_xlpm.usp,AND($AF21<>"",$AF21<>"N/A",$AF21<>"No Min RQ"),_xlpm.n,_xlpm.sfp+_xlpm.slp+_xlpm.ffp+_xlpm.chp+_xlpm.usp,_xlpm.sub,(_xlpm.sfp*($P21="Submitted"))+(_xlpm.slp*($T21="Submitted"))+(_xlpm.ffp*($X21="Submitted"))+(_xlpm.chp*($AB21="Submitted"))+(_xlpm.usp*($AF21="Submitted")),_xlpm.term,(_xlpm.sfp*OR($P21="Approved",$P21="Declined"))+(_xlpm.slp*OR($T21="Approved",$T21="Declined"))+(_xlpm.ffp*OR($X21="Approved",$X21="Declined"))+(_xlpm.chp*OR($AB21="Approved",$AB21="Declined"))+(_xlpm.usp*OR($AF21="Approved",$AF21="Declined")),IF(_xlpm.n=0,"No applicable lenders",IF(_xlpm.sub>0,"Stays with Shaw - lender still Submitted",IF(_xlpm.term=_xlpm.n,"Clear - all applicable lenders Approved or Declined","Stays with Shaw - not all lenders Approved or Declined")))))
A22: Dirty Boys Contracting, LLC | B22: Dirty Boys Contracting, LLC | D22: Kelvin Tate | E22: 801-706-0737 | F22: kelvin@dboyscontracting.com | G22: David Yates | H22: David.yates@getfinti.com | I22: excavation, retaining walls, concrete and landscaping. | K22: 3 | L22: =IF($A22="","",_xlfn.LET(_xlpm.ns,(--($P22="Ready 2 Submit"))+(--($T22="Ready 2 Submit"))+(--($X22="Ready 2 Submit"))+(--($AB22="Ready 2 Submit"))+(--($AF22="Ready 2 Submit")),_xlpm.wd,(--($P22="Waiting on Dealer"))+(--($T22="Waiting on Dealer"))+(--($X22="Waiting on Dealer"))+(--($AB22="Waiting on Dealer"))+(--($AF22="Waiting on Dealer")),_xlpm.sb,(--($P22="Submitted"))+(--($T22="Submitted"))+(--($X22="Submitted"))+(--($AB22="Submitted"))+(--($AF22="Submitted")),_xlpm.ap,(--($P22="Approved"))+(--($T22="Approved"))+(--($X22="Approved"))+(--($AB22="Approved"))+(--($AF22="Approved")),_xlpm.ac,(--($P22="Active"))+(--($T22="Active"))+(--($X22="Active"))+(--($AB22="Active"))+(--($AF22="Active")),_xlpm.dc,(--($P22="Declined"))+(--($T22="Declined"))+(--($X22="Declined"))+(--($AB22="Declined"))+(--($AF22="Declined")),_xlpm.aRS,(--($P22="Active"))*(--($R22="Yes"))+(--($T22="Active"))*(--($V22="Yes"))+(--($X22="Active"))*(--($Z22="Yes"))+(--($AB22="Active"))*(--($AD22="Yes"))+(--($AF22="Active"))*(--($AH22="Yes")),_xlpm.aDn,(--($P22="Active"))*(--($R22="Yes"))*(--((($S22="Yes")+($S22=TRUE))>0))+(--($T22="Active"))*(--($V22="Yes"))*(--((($W22="Yes")+($W22=TRUE))>0))+(--($X22="Active"))*(--($Z22="Yes"))*(--((($AA22="Yes")+($AA22=TRUE))>0))+(--($AB22="Active"))*(--($AD22="Yes"))*(--((($AE22="Yes")+($AE22=TRUE))>0))+(--($AF22="Active"))*(--($AH22="Yes"))*(--((($AI22="Yes")+($AI22=TRUE))>0)),_xlpm.inPlay,_xlpm.ns+_xlpm.wd+_xlpm.sb+_xlpm.ap,IF(AND(_xlpm.ac>0,_xlpm.inPlay=0,_xlpm.aDn=_xlpm.ac),"LIVE DLR",IF(AND(_xlpm.aRS>0,_xlpm.aDn<_xlpm.aRS),"Training",IF(_xlpm.aRS>0,"Active",IF(AND(_xlpm.dc>0,_xlpm.inPlay+_xlpm.ac=0),"Dead",IF(OR($CA22="Yes",$CA22=TRUE),"Rate Sheet",IF(AND($AJ22<>"",$AK22=FALSE),"Waiting on Dealer",IF(_xlpm.sb>0,"Waiting on Lender",IF(AND(_xlpm.ap+_xlpm.ac>0,_xlpm.ns+_xlpm.wd=0),"Rate Sheet","Application Submitted")))))))))) -> Waiting on Lender | M22: 46244 | N22: 46280 | O22: SF, SL, FF | P22: Submitted | Q22: 46274 | R22: No | S22: No | T22: No Min RQ | U22: 46274 | V22: No | W22: No | X22: Submitted | Y22: =IF(OR(Y22="",Y22=0),IF($X22="Submitted",TODAY(),""),Y22) -> 46286 | Z22: No | AA22: No | AB22: N/A | AC22: =IF(OR(AC22="",AC22=0),IF($AB22="Submitted",TODAY(),""),AC22) | AD22: No | AE22: No | AF22: N/A | AG22: =IF(OR(AG22="",AG22=0),IF($AF22="Submitted",TODAY(),""),AG22) | AH22: No | AI22: No | AJ22: no date est. only 1 mil a year in rev incomplete application. spoke to owner will send over voided check today when he has time. 8/17/2026 | AK22: TRUE | AL22: {=IF($A22="","",SUMPRODUCT((CHOOSE({1,2,3,4,5},$R22,$V22,$Z22,$AD22,$AH22)="Yes")*(((CHOOSE({1,2,3,4,5},$S22,$W22,$AA22,$AE22,$AI22)="Yes")+(CHOOSE({1,2,3,4,5},$S22,$W22,$AA22,$AE22,$AI22)=TRUE))>0)))} -> 0 | AN22: =IF(OR($A22="",$AM22=""),"",TODAY()-$AM22) | BA22: 18 | BZ22: Unassigned | CA22: No | CB22: =IF($A22="","",_xlfn.LET(_xlpm.sfp,AND($P22<>"",$P22<>"N/A",$P22<>"No Min RQ"),_xlpm.slp,AND($T22<>"",$T22<>"N/A",$T22<>"No Min RQ"),_xlpm.ffp,AND($X22<>"",$X22<>"N/A",$X22<>"No Min RQ"),_xlpm.chp,AND($AB22<>"",$AB22<>"N/A",$AB22<>"No Min RQ"),_xlpm.usp,AND($AF22<>"",$AF22<>"N/A",$AF22<>"No Min RQ"),_xlpm.n,_xlpm.sfp+_xlpm.slp+_xlpm.ffp+_xlpm.chp+_xlpm.usp,_xlpm.sub,(_xlpm.sfp*($P22="Submitted"))+(_xlpm.slp*($T22="Submitted"))+(_xlpm.ffp*($X22="Submitted"))+(_xlpm.chp*($AB22="Submitted"))+(_xlpm.usp*($AF22="Submitted")),_xlpm.term,(_xlpm.sfp*OR($P22="Approved",$P22="Declined"))+(_xlpm.slp*OR($T22="Approved",$T22="Declined"))+(_xlpm.ffp*OR($X22="Approved",$X22="Declined"))+(_xlpm.chp*OR($AB22="Approved",$AB22="Declined"))+(_xlpm.usp*OR($AF22="Approved",$AF22="Declined")),IF(_xlpm.n=0,"No applicable lenders",IF(_xlpm.sub>0,"Stays with Shaw - lender still Submitted",IF(_xlpm.term=_xlpm.n,"Clear - all applicable lenders Approved or Declined","Stays with Shaw - not all lenders Approved or Declined")))))
A23: Fortitude Builders and Restoratin | B23: Fortitude Builders and Restoration | D23: Fernando Delgado | E23: 336-338-1002 | F23: ceo@fbrhome.com | G23: Heriberto Rivera | H23: yennikayadiel@gmail.com | I23: Roofing | K23: 3 | L23: =IF($A23="","",_xlfn.LET(_xlpm.ns,(--($P23="Ready 2 Submit"))+(--($T23="Ready 2 Submit"))+(--($X23="Ready 2 Submit"))+(--($AB23="Ready 2 Submit"))+(--($AF23="Ready 2 Submit")),_xlpm.wd,(--($P23="Waiting on Dealer"))+(--($T23="Waiting on Dealer"))+(--($X23="Waiting on Dealer"))+(--($AB23="Waiting on Dealer"))+(--($AF23="Waiting on Dealer")),_xlpm.sb,(--($P23="Submitted"))+(--($T23="Submitted"))+(--($X23="Submitted"))+(--($AB23="Submitted"))+(--($AF23="Submitted")),_xlpm.ap,(--($P23="Approved"))+(--($T23="Approved"))+(--($X23="Approved"))+(--($AB23="Approved"))+(--($AF23="Approved")),_xlpm.ac,(--($P23="Active"))+(--($T23="Active"))+(--($X23="Active"))+(--($AB23="Active"))+(--($AF23="Active")),_xlpm.dc,(--($P23="Declined"))+(--($T23="Declined"))+(--($X23="Declined"))+(--($AB23="Declined"))+(--($AF23="Declined")),_xlpm.aRS,(--($P23="Active"))*(--($R23="Yes"))+(--($T23="Active"))*(--($V23="Yes"))+(--($X23="Active"))*(--($Z23="Yes"))+(--($AB23="Active"))*(--($AD23="Yes"))+(--($AF23="Active"))*(--($AH23="Yes")),_xlpm.aDn,(--($P23="Active"))*(--($R23="Yes"))*(--((($S23="Yes")+($S23=TRUE))>0))+(--($T23="Active"))*(--($V23="Yes"))*(--((($W23="Yes")+($W23=TRUE))>0))+(--($X23="Active"))*(--($Z23="Yes"))*(--((($AA23="Yes")+($AA23=TRUE))>0))+(--($AB23="Active"))*(--($AD23="Yes"))*(--((($AE23="Yes")+($AE23=TRUE))>0))+(--($AF23="Active"))*(--($AH23="Yes"))*(--((($AI23="Yes")+($AI23=TRUE))>0)),_xlpm.inPlay,_xlpm.ns+_xlpm.wd+_xlpm.sb+_xlpm.ap,IF(AND(_xlpm.ac>0,_xlpm.inPlay=0,_xlpm.aDn=_xlpm.ac),"LIVE DLR",IF(AND(_xlpm.aRS>0,_xlpm.aDn<_xlpm.aRS),"Training",IF(_xlpm.aRS>0,"Active",IF(AND(_xlpm.dc>0,_xlpm.inPlay+_xlpm.ac=0),"Dead",IF(OR($CA23="Yes",$CA23=TRUE),"Rate Sheet",IF(AND($AJ23<>"",$AK23=FALSE),"Waiting on Dealer",IF(_xlpm.sb>0,"Waiting on Lender",IF(AND(_xlpm.ap+_xlpm.ac>0,_xlpm.ns+_xlpm.wd=0),"Rate Sheet","Application Submitted")))))))))) -> Waiting on Dealer | M23: 46245 | N23: 46280 | O23: FF | P23: =IF($A23="","",IF($AK23=TRUE,"Ready 2 Submit","Waiting on Dealer")) -> Waiting on Dealer | Q23: =IF(OR(Q23="",Q23=0),IF($P23="Submitted",TODAY(),""),Q23) | R23: No | S23: No | T23: =IF($A23="","",IF($AK23=TRUE,"Ready 2 Submit","Waiting on Dealer")) -> Waiting on Dealer | U23: =IF(OR(U23="",U23=0),IF($T23="Submitted",TODAY(),""),U23) | V23: No | W23: No | X23: =IF($A23="","",IF($AK23=TRUE,"Ready 2 Submit","Waiting on Dealer")) -> Waiting on Dealer | Y23: =IF(OR(Y23="",Y23=0),IF($X23="Submitted",TODAY(),""),Y23) | Z23: No | AA23: No | AB23: N/A | AC23: =IF(OR(AC23="",AC23=0),IF($AB23="Submitted",TODAY(),""),AC23) | AD23: No | AE23: No | AF23: N/A | AG23: =IF(OR(AG23="",AG23=0),IF($AF23="Submitted",TODAY(),""),AG23) | AH23: No | AI23: No | AJ23: Need est Rev updated | AK23: FALSE | AL23: {=IF($A23="","",SUMPRODUCT((CHOOSE({1,2,3,4,5},$R23,$V23,$Z23,$AD23,$AH23)="Yes")*(((CHOOSE({1,2,3,4,5},$S23,$W23,$AA23,$AE23,$AI23)="Yes")+(CHOOSE({1,2,3,4,5},$S23,$W23,$AA23,$AE23,$AI23)=TRUE))>0)))} -> 0 | AM23: 46287 | AN23: =IF(OR($A23="",$AM23=""),"",TODAY()-$AM23) -> 1 | BA23: 19 | BZ23: Unassigned | CA23: No | CB23: =IF($A23="","",_xlfn.LET(_xlpm.sfp,AND($P23<>"",$P23<>"N/A",$P23<>"No Min RQ"),_xlpm.slp,AND($T23<>"",$T23<>"N/A",$T23<>"No Min RQ"),_xlpm.ffp,AND($X23<>"",$X23<>"N/A",$X23<>"No Min RQ"),_xlpm.chp,AND($AB23<>"",$AB23<>"N/A",$AB23<>"No Min RQ"),_xlpm.usp,AND($AF23<>"",$AF23<>"N/A",$AF23<>"No Min RQ"),_xlpm.n,_xlpm.sfp+_xlpm.slp+_xlpm.ffp+_xlpm.chp+_xlpm.usp,_xlpm.sub,(_xlpm.sfp*($P23="Submitted"))+(_xlpm.slp*($T23="Submitted"))+(_xlpm.ffp*($X23="Submitted"))+(_xlpm.chp*($AB23="Submitted"))+(_xlpm.usp*($AF23="Submitted")),_xlpm.term,(_xlpm.sfp*OR($P23="Approved",$P23="Declined"))+(_xlpm.slp*OR($T23="Approved",$T23="Declined"))+(_xlpm.ffp*OR($X23="Approved",$X23="Declined"))+(_xlpm.chp*OR($AB23="Approved",$AB23="Declined"))+(_xlpm.usp*OR($AF23="Approved",$AF23="Declined")),IF(_xlpm.n=0,"No applicable lenders",IF(_xlpm.sub>0,"Stays with Shaw - lender still Submitted",IF(_xlpm.term=_xlpm.n,"Clear - all applicable lenders Approved or Declined","Stays with Shaw - not all lenders Approved or Declined")))))
A24: roofio, LLC. | B24: roofio LLC | D24: JD DELAROSA | E24: 512-585-0030 | F24: jd@roofio.com | G24: Scott Coombs | H24: scottbcoombs@gmail.com | I24: Roofing | K24: 2 | L24: =IF($A24="","",_xlfn.LET(_xlpm.ns,(--($P24="Ready 2 Submit"))+(--($T24="Ready 2 Submit"))+(--($X24="Ready 2 Submit"))+(--($AB24="Ready 2 Submit"))+(--($AF24="Ready 2 Submit")),_xlpm.wd,(--($P24="Waiting on Dealer"))+(--($T24="Waiting on Dealer"))+(--($X24="Waiting on Dealer"))+(--($AB24="Waiting on Dealer"))+(--($AF24="Waiting on Dealer")),_xlpm.sb,(--($P24="Submitted"))+(--($T24="Submitted"))+(--($X24="Submitted"))+(--($AB24="Submitted"))+(--($AF24="Submitted")),_xlpm.ap,(--($P24="Approved"))+(--($T24="Approved"))+(--($X24="Approved"))+(--($AB24="Approved"))+(--($AF24="Approved")),_xlpm.ac,(--($P24="Active"))+(--($T24="Active"))+(--($X24="Active"))+(--($AB24="Active"))+(--($AF24="Active")),_xlpm.dc,(--($P24="Declined"))+(--($T24="Declined"))+(--($X24="Declined"))+(--($AB24="Declined"))+(--($AF24="Declined")),_xlpm.aRS,(--($P24="Active"))*(--($R24="Yes"))+(--($T24="Active"))*(--($V24="Yes"))+(--($X24="Active"))*(--($Z24="Yes"))+(--($AB24="Active"))*(--($AD24="Yes"))+(--($AF24="Active"))*(--($AH24="Yes")),_xlpm.aDn,(--($P24="Active"))*(--($R24="Yes"))*(--((($S24="Yes")+($S24=TRUE))>0))+(--($T24="Active"))*(--($V24="Yes"))*(--((($W24="Yes")+($W24=TRUE))>0))+(--($X24="Active"))*(--($Z24="Yes"))*(--((($AA24="Yes")+($AA24=TRUE))>0))+(--($AB24="Active"))*(--($AD24="Yes"))*(--((($AE24="Yes")+($AE24=TRUE))>0))+(--($AF24="Active"))*(--($AH24="Yes"))*(--((($AI24="Yes")+($AI24=TRUE))>0)),_xlpm.inPlay,_xlpm.ns+_xlpm.wd+_xlpm.sb+_xlpm.ap,IF(AND(_xlpm.ac>0,_xlpm.inPlay=0,_xlpm.aDn=_xlpm.ac),"LIVE DLR",IF(AND(_xlpm.aRS>0,_xlpm.aDn<_xlpm.aRS),"Training",IF(_xlpm.aRS>0,"Active",IF(AND(_xlpm.dc>0,_xlpm.inPlay+_xlpm.ac=0),"Dead",IF(OR($CA24="Yes",$CA24=TRUE),"Rate Sheet",IF(AND($AJ24<>"",$AK24=FALSE),"Waiting on Dealer",IF(_xlpm.sb>0,"Waiting on Lender",IF(AND(_xlpm.ap+_xlpm.ac>0,_xlpm.ns+_xlpm.wd=0),"Rate Sheet","Application Submitted")))))))))) -> Application Submitted | M24: 46247 | N24: 46280 | O24: FF, SL | P24: =IF($A24="","",IF($AK24=TRUE,"Ready 2 Submit","Waiting on Dealer")) -> Ready 2 Submit | Q24: =IF(OR(Q24="",Q24=0),IF($P24="Submitted",TODAY(),""),Q24) | R24: No | S24: No | T24: Declined | U24: =IF(OR(U24="",U24=0),IF($T24="Submitted",TODAY(),""),U24) | V24: No | W24: No | X24: Declined | Y24: 46275 | Z24: No | AA24: No | AB24: N/A | AC24: =IF(OR(AC24="",AC24=0),IF($AB24="Submitted",TODAY(),""),AC24) | AD24: No | AE24: No | AF24: N/A | AG24: =IF(OR(AG24="",AG24=0),IF($AF24="Submitted",TODAY(),""),AG24) | AH24: No | AI24: No | AJ24: Roofio will provide legal docs proving they didnt do what the lenders think they did | AK24: TRUE | AL24: {=IF($A24="","",SUMPRODUCT((CHOOSE({1,2,3,4,5},$R24,$V24,$Z24,$AD24,$AH24)="Yes")*(((CHOOSE({1,2,3,4,5},$S24,$W24,$AA24,$AE24,$AI24)="Yes")+(CHOOSE({1,2,3,4,5},$S24,$W24,$AA24,$AE24,$AI24)=TRUE))>0)))} -> 0 | AN24: =IF(OR($A24="",$AM24=""),"",TODAY()-$AM24) | BA24: 20 | BZ24: Unassigned | CA24: No | CB24: =IF($A24="","",_xlfn.LET(_xlpm.sfp,AND($P24<>"",$P24<>"N/A",$P24<>"No Min RQ"),_xlpm.slp,AND($T24<>"",$T24<>"N/A",$T24<>"No Min RQ"),_xlpm.ffp,AND($X24<>"",$X24<>"N/A",$X24<>"No Min RQ"),_xlpm.chp,AND($AB24<>"",$AB24<>"N/A",$AB24<>"No Min RQ"),_xlpm.usp,AND($AF24<>"",$AF24<>"N/A",$AF24<>"No Min RQ"),_xlpm.n,_xlpm.sfp+_xlpm.slp+_xlpm.ffp+_xlpm.chp+_xlpm.usp,_xlpm.sub,(_xlpm.sfp*($P24="Submitted"))+(_xlpm.slp*($T24="Submitted"))+(_xlpm.ffp*($X24="Submitted"))+(_xlpm.chp*($AB24="Submitted"))+(_xlpm.usp*($AF24="Submitted")),_xlpm.term,(_xlpm.sfp*OR($P24="Approved",$P24="Declined"))+(_xlpm.slp*OR($T24="Approved",$T24="Declined"))+(_xlpm.ffp*OR($X24="Approved",$X24="Declined"))+(_xlpm.chp*OR($AB24="Approved",$AB24="Declined"))+(_xlpm.usp*OR($AF24="Approved",$AF24="Declined")),IF(_xlpm.n=0,"No applicable lenders",IF(_xlpm.sub>0,"Stays with Shaw - lender still Submitted",IF(_xlpm.term=_xlpm.n,"Clear - all applicable lenders Approved or Declined","Stays with Shaw - not all lenders Approved or Declined")))))
A25: TGR Consultant LLC | B25: Tania | D25: Tania Rendon | E25: 203-980-3370 | F25: tgrconsultantllc@gmail.com | G25: Rob Garcia | H25: robsudden24@icloud.com | K25: 3 | L25: =IF($A25="","",_xlfn.LET(_xlpm.ns,(--($P25="Ready 2 Submit"))+(--($T25="Ready 2 Submit"))+(--($X25="Ready 2 Submit"))+(--($AB25="Ready 2 Submit"))+(--($AF25="Ready 2 Submit")),_xlpm.wd,(--($P25="Waiting on Dealer"))+(--($T25="Waiting on Dealer"))+(--($X25="Waiting on Dealer"))+(--($AB25="Waiting on Dealer"))+(--($AF25="Waiting on Dealer")),_xlpm.sb,(--($P25="Submitted"))+(--($T25="Submitted"))+(--($X25="Submitted"))+(--($AB25="Submitted"))+(--($AF25="Submitted")),_xlpm.ap,(--($P25="Approved"))+(--($T25="Approved"))+(--($X25="Approved"))+(--($AB25="Approved"))+(--($AF25="Approved")),_xlpm.ac,(--($P25="Active"))+(--($T25="Active"))+(--($X25="Active"))+(--($AB25="Active"))+(--($AF25="Active")),_xlpm.dc,(--($P25="Declined"))+(--($T25="Declined"))+(--($X25="Declined"))+(--($AB25="Declined"))+(--($AF25="Declined")),_xlpm.aRS,(--($P25="Active"))*(--($R25="Yes"))+(--($T25="Active"))*(--($V25="Yes"))+(--($X25="Active"))*(--($Z25="Yes"))+(--($AB25="Active"))*(--($AD25="Yes"))+(--($AF25="Active"))*(--($AH25="Yes")),_xlpm.aDn,(--($P25="Active"))*(--($R25="Yes"))*(--((($S25="Yes")+($S25=TRUE))>0))+(--($T25="Active"))*(--($V25="Yes"))*(--((($W25="Yes")+($W25=TRUE))>0))+(--($X25="Active"))*(--($Z25="Yes"))*(--((($AA25="Yes")+($AA25=TRUE))>0))+(--($AB25="Active"))*(--($AD25="Yes"))*(--((($AE25="Yes")+($AE25=TRUE))>0))+(--($AF25="Active"))*(--($AH25="Yes"))*(--((($AI25="Yes")+($AI25=TRUE))>0)),_xlpm.inPlay,_xlpm.ns+_xlpm.wd+_xlpm.sb+_xlpm.ap,IF(AND(_xlpm.ac>0,_xlpm.inPlay=0,_xlpm.aDn=_xlpm.ac),"LIVE DLR",IF(AND(_xlpm.aRS>0,_xlpm.aDn<_xlpm.aRS),"Training",IF(_xlpm.aRS>0,"Active",IF(AND(_xlpm.dc>0,_xlpm.inPlay+_xlpm.ac=0),"Dead",IF(OR($CA25="Yes",$CA25=TRUE),"Rate Sheet",IF(AND($AJ25<>"",$AK25=FALSE),"Waiting on Dealer",IF(_xlpm.sb>0,"Waiting on Lender",IF(AND(_xlpm.ap+_xlpm.ac>0,_xlpm.ns+_xlpm.wd=0),"Rate Sheet","Application Submitted")))))))))) -> Waiting on Dealer | M25: 46247 | N25: 46280 | O25: FF | P25: =IF($A25="","",IF($AK25=TRUE,"Ready 2 Submit","Waiting on Dealer")) -> Waiting on Dealer | Q25: =IF(OR(Q25="",Q25=0),IF($P25="Submitted",TODAY(),""),Q25) | R25: No | S25: No | T25: =IF($A25="","",IF($AK25=TRUE,"Ready 2 Submit","Waiting on Dealer")) -> Waiting on Dealer | U25: =IF(OR(U25="",U25=0),IF($T25="Submitted",TODAY(),""),U25) | V25: No | W25: No | X25: =IF($A25="","",IF($AK25=TRUE,"Ready 2 Submit","Waiting on Dealer")) -> Waiting on Dealer | Y25: =IF(OR(Y25="",Y25=0),IF($X25="Submitted",TODAY(),""),Y25) | Z25: No | AA25: No | AB25: N/A | AC25: =IF(OR(AC25="",AC25=0),IF($AB25="Submitted",TODAY(),""),AC25) | AD25: No | AE25: No | AF25: N/A | AG25: =IF(OR(AG25="",AG25=0),IF($AF25="Submitted",TODAY(),""),AG25) | AH25: No | AI25: No | AJ25: Need website and all missing document uploads | AK25: FALSE | AL25: {=IF($A25="","",SUMPRODUCT((CHOOSE({1,2,3,4,5},$R25,$V25,$Z25,$AD25,$AH25)="Yes")*(((CHOOSE({1,2,3,4,5},$S25,$W25,$AA25,$AE25,$AI25)="Yes")+(CHOOSE({1,2,3,4,5},$S25,$W25,$AA25,$AE25,$AI25)=TRUE))>0)))} -> 0 | AM25: 46287 | AN25: =IF(OR($A25="",$AM25=""),"",TODAY()-$AM25) -> 1 | BA25: 21 | BZ25: Unassigned | CA25: No | CB25: =IF($A25="","",_xlfn.LET(_xlpm.sfp,AND($P25<>"",$P25<>"N/A",$P25<>"No Min RQ"),_xlpm.slp,AND($T25<>"",$T25<>"N/A",$T25<>"No Min RQ"),_xlpm.ffp,AND($X25<>"",$X25<>"N/A",$X25<>"No Min RQ"),_xlpm.chp,AND($AB25<>"",$AB25<>"N/A",$AB25<>"No Min RQ"),_xlpm.usp,AND($AF25<>"",$AF25<>"N/A",$AF25<>"No Min RQ"),_xlpm.n,_xlpm.sfp+_xlpm.slp+_xlpm.ffp+_xlpm.chp+_xlpm.usp,_xlpm.sub,(_xlpm.sfp*($P25="Submitted"))+(_xlpm.slp*($T25="Submitted"))+(_xlpm.ffp*($X25="Submitted"))+(_xlpm.chp*($AB25="Submitted"))+(_xlpm.usp*($AF25="Submitted")),_xlpm.term,(_xlpm.sfp*OR($P25="Approved",$P25="Declined"))+(_xlpm.slp*OR($T25="Approved",$T25="Declined"))+(_xlpm.ffp*OR($X25="Approved",$X25="Declined"))+(_xlpm.chp*OR($AB25="Approved",$AB25="Declined"))+(_xlpm.usp*OR($AF25="Approved",$AF25="Declined")),IF(_xlpm.n=0,"No applicable lenders",IF(_xlpm.sub>0,"Stays with Shaw - lender still Submitted",IF(_xlpm.term=_xlpm.n,"Clear - all applicable lenders Approved or Declined","Stays with Shaw - not all lenders Approved or Declined")))))
A26: DANIEL FREUND | B26: PATRIOT PAINTING AND REMODLEING | D26: DANIEL FREUND | E26: 832-952-8804 | F26: patriotpaintingtexas@gmail.com | G26: Evan Young | H26: evanisayoung@gmail.com | I26: Painting | K26: 2 | L26: =IF($A26="","",_xlfn.LET(_xlpm.ns,(--($P26="Ready 2 Submit"))+(--($T26="Ready 2 Submit"))+(--($X26="Ready 2 Submit"))+(--($AB26="Ready 2 Submit"))+(--($AF26="Ready 2 Submit")),_xlpm.wd,(--($P26="Waiting on Dealer"))+(--($T26="Waiting on Dealer"))+(--($X26="Waiting on Dealer"))+(--($AB26="Waiting on Dealer"))+(--($AF26="Waiting on Dealer")),_xlpm.sb,(--($P26="Submitted"))+(--($T26="Submitted"))+(--($X26="Submitted"))+(--($AB26="Submitted"))+(--($AF26="Submitted")),_xlpm.ap,(--($P26="Approved"))+(--($T26="Approved"))+(--($X26="Approved"))+(--($AB26="Approved"))+(--($AF26="Approved")),_xlpm.ac,(--($P26="Active"))+(--($T26="Active"))+(--($X26="Active"))+(--($AB26="Active"))+(--($AF26="Active")),_xlpm.dc,(--($P26="Declined"))+(--($T26="Declined"))+(--($X26="Declined"))+(--($AB26="Declined"))+(--($AF26="Declined")),_xlpm.aRS,(--($P26="Active"))*(--($R26="Yes"))+(--($T26="Active"))*(--($V26="Yes"))+(--($X26="Active"))*(--($Z26="Yes"))+(--($AB26="Active"))*(--($AD26="Yes"))+(--($AF26="Active"))*(--($AH26="Yes")),_xlpm.aDn,(--($P26="Active"))*(--($R26="Yes"))*(--((($S26="Yes")+($S26=TRUE))>0))+(--($T26="Active"))*(--($V26="Yes"))*(--((($W26="Yes")+($W26=TRUE))>0))+(--($X26="Active"))*(--($Z26="Yes"))*(--((($AA26="Yes")+($AA26=TRUE))>0))+(--($AB26="Active"))*(--($AD26="Yes"))*(--((($AE26="Yes")+($AE26=TRUE))>0))+(--($AF26="Active"))*(--($AH26="Yes"))*(--((($AI26="Yes")+($AI26=TRUE))>0)),_xlpm.inPlay,_xlpm.ns+_xlpm.wd+_xlpm.sb+_xlpm.ap,IF(AND(_xlpm.ac>0,_xlpm.inPlay=0,_xlpm.aDn=_xlpm.ac),"LIVE DLR",IF(AND(_xlpm.aRS>0,_xlpm.aDn<_xlpm.aRS),"Training",IF(_xlpm.aRS>0,"Active",IF(AND(_xlpm.dc>0,_xlpm.inPlay+_xlpm.ac=0),"Dead",IF(OR($CA26="Yes",$CA26=TRUE),"Rate Sheet",IF(AND($AJ26<>"",$AK26=FALSE),"Waiting on Dealer",IF(_xlpm.sb>0,"Waiting on Lender",IF(AND(_xlpm.ap+_xlpm.ac>0,_xlpm.ns+_xlpm.wd=0),"Rate Sheet","Application Submitted")))))))))) -> Waiting on Dealer | M26: 46247 | N26: 46280 | O26: SF, SL, FF | P26: =IF($A26="","",IF($AK26=TRUE,"Ready 2 Submit","Waiting on Dealer")) -> Waiting on Dealer | Q26: =IF(OR(Q26="",Q26=0),IF($P26="Submitted",TODAY(),""),Q26) | R26: No | S26: No | T26: =IF($A26="","",IF($AK26=TRUE,"Ready 2 Submit","Waiting on Dealer")) -> Waiting on Dealer | U26: =IF(OR(U26="",U26=0),IF($T26="Submitted",TODAY(),""),U26) | V26: No | W26: No | X26: =IF($A26="","",IF($AK26=TRUE,"Ready 2 Submit","Waiting on Dealer")) -> Waiting on Dealer | Y26: =IF(OR(Y26="",Y26=0),IF($X26="Submitted",TODAY(),""),Y26) | Z26: No | AA26: No | AB26: N/A | AC26: =IF(OR(AC26="",AC26=0),IF($AB26="Submitted",TODAY(),""),AC26) | AD26: No | AE26: No | AF26: N/A | AG26: =IF(OR(AG26="",AG26=0),IF($AF26="Submitted",TODAY(),""),AG26) | AH26: No | AI26: No | AJ26: Daniel is out of state for work. will get it fixed when he gets back. | AK26: FALSE | AL26: {=IF($A26="","",SUMPRODUCT((CHOOSE({1,2,3,4,5},$R26,$V26,$Z26,$AD26,$AH26)="Yes")*(((CHOOSE({1,2,3,4,5},$S26,$W26,$AA26,$AE26,$AI26)="Yes")+(CHOOSE({1,2,3,4,5},$S26,$W26,$AA26,$AE26,$AI26)=TRUE))>0)))} -> 0 | AM26: 46267 | AN26: =IF(OR($A26="",$AM26=""),"",TODAY()-$AM26) -> 21 | BA26: 22 | BZ26: Unassigned | CA26: No | CB26: =IF($A26="","",_xlfn.LET(_xlpm.sfp,AND($P26<>"",$P26<>"N/A",$P26<>"No Min RQ"),_xlpm.slp,AND($T26<>"",$T26<>"N/A",$T26<>"No Min RQ"),_xlpm.ffp,AND($X26<>"",$X26<>"N/A",$X26<>"No Min RQ"),_xlpm.chp,AND($AB26<>"",$AB26<>"N/A",$AB26<>"No Min RQ"),_xlpm.usp,AND($AF26<>"",$AF26<>"N/A",$AF26<>"No Min RQ"),_xlpm.n,_xlpm.sfp+_xlpm.slp+_xlpm.ffp+_xlpm.chp+_xlpm.usp,_xlpm.sub,(_xlpm.sfp*($P26="Submitted"))+(_xlpm.slp*($T26="Submitted"))+(_xlpm.ffp*($X26="Submitted"))+(_xlpm.chp*($AB26="Submitted"))+(_xlpm.usp*($AF26="Submitted")),_xlpm.term,(_xlpm.sfp*OR($P26="Approved",$P26="Declined"))+(_xlpm.slp*OR($T26="Approved",$T26="Declined"))+(_xlpm.ffp*OR($X26="Approved",$X26="Declined"))+(_xlpm.chp*OR($AB26="Approved",$AB26="Declined"))+(_xlpm.usp*OR($AF26="Approved",$AF26="Declined")),IF(_xlpm.n=0,"No applicable lenders",IF(_xlpm.sub>0,"Stays with Shaw - lender still Submitted",IF(_xlpm.term=_xlpm.n,"Clear - all applicable lenders Approved or Declined","Stays with Shaw - not all lenders Approved or Declined")))))
A27: Expert affordable roofing LLC | B27: Axtion Roofing Contractors LLC | D27: Nathan Dixon | E27: 850-516-0617 | F27: ndixon850@yahoo.com | G27: Ryan Tall | H27: ryantall11@gmail.com | I27: Roofing | K27: 3 | L27: =IF($A27="","",_xlfn.LET(_xlpm.ns,(--($P27="Ready 2 Submit"))+(--($T27="Ready 2 Submit"))+(--($X27="Ready 2 Submit"))+(--($AB27="Ready 2 Submit"))+(--($AF27="Ready 2 Submit")),_xlpm.wd,(--($P27="Waiting on Dealer"))+(--($T27="Waiting on Dealer"))+(--($X27="Waiting on Dealer"))+(--($AB27="Waiting on Dealer"))+(--($AF27="Waiting on Dealer")),_xlpm.sb,(--($P27="Submitted"))+(--($T27="Submitted"))+(--($X27="Submitted"))+(--($AB27="Submitted"))+(--($AF27="Submitted")),_xlpm.ap,(--($P27="Approved"))+(--($T27="Approved"))+(--($X27="Approved"))+(--($AB27="Approved"))+(--($AF27="Approved")),_xlpm.ac,(--($P27="Active"))+(--($T27="Active"))+(--($X27="Active"))+(--($AB27="Active"))+(--($AF27="Active")),_xlpm.dc,(--($P27="Declined"))+(--($T27="Declined"))+(--($X27="Declined"))+(--($AB27="Declined"))+(--($AF27="Declined")),_xlpm.aRS,(--($P27="Active"))*(--($R27="Yes"))+(--($T27="Active"))*(--($V27="Yes"))+(--($X27="Active"))*(--($Z27="Yes"))+(--($AB27="Active"))*(--($AD27="Yes"))+(--($AF27="Active"))*(--($AH27="Yes")),_xlpm.aDn,(--($P27="Active"))*(--($R27="Yes"))*(--((($S27="Yes")+($S27=TRUE))>0))+(--($T27="Active"))*(--($V27="Yes"))*(--((($W27="Yes")+($W27=TRUE))>0))+(--($X27="Active"))*(--($Z27="Yes"))*(--((($AA27="Yes")+($AA27=TRUE))>0))+(--($AB27="Active"))*(--($AD27="Yes"))*(--((($AE27="Yes")+($AE27=TRUE))>0))+(--($AF27="Active"))*(--($AH27="Yes"))*(--((($AI27="Yes")+($AI27=TRUE))>0)),_xlpm.inPlay,_xlpm.ns+_xlpm.wd+_xlpm.sb+_xlpm.ap,IF(AND(_xlpm.ac>0,_xlpm.inPlay=0,_xlpm.aDn=_xlpm.ac),"LIVE DLR",IF(AND(_xlpm.aRS>0,_xlpm.aDn<_xlpm.aRS),"Training",IF(_xlpm.aRS>0,"Active",IF(AND(_xlpm.dc>0,_xlpm.inPlay+_xlpm.ac=0),"Dead",IF(OR($CA27="Yes",$CA27=TRUE),"Rate Sheet",IF(AND($AJ27<>"",$AK27=FALSE),"Waiting on Dealer",IF(_xlpm.sb>0,"Waiting on Lender",IF(AND(_xlpm.ap+_xlpm.ac>0,_xlpm.ns+_xlpm.wd=0),"Rate Sheet","Application Submitted")))))))))) -> Waiting on Dealer | M27: 46248 | N27: 46280 | O27: SF, FF | P27: =IF($A27="","",IF($AK27=TRUE,"Ready 2 Submit","Waiting on Dealer")) -> Waiting on Dealer | Q27: =IF(OR(Q27="",Q27=0),IF($P27="Submitted",TODAY(),""),Q27) | R27: No | S27: No | T27: N/A | U27: =IF(OR(U27="",U27=0),IF($T27="Submitted",TODAY(),""),U27) | V27: No | W27: No | X27: =IF($A27="","",IF($AK27=TRUE,"Ready 2 Submit","Waiting on Dealer")) -> Waiting on Dealer | Y27: =IF(OR(Y27="",Y27=0),IF($X27="Submitted",TODAY(),""),Y27) | Z27: No | AA27: No | AB27: N/A | AC27: =IF(OR(AC27="",AC27=0),IF($AB27="Submitted",TODAY(),""),AC27) | AD27: No | AE27: No | AF27: N/A | AG27: =IF(OR(AG27="",AG27=0),IF($AF27="Submitted",TODAY(),""),AG27) | AH27: No | AI27: No | AJ27: Complete Insights, verify website & reputation link, confirm DBA name, upload 2 bank statements and voided check (Articles of Incorporation field), sign Agreement page and DocuSign, then submit to lenders. | AK27: FALSE | AL27: {=IF($A27="","",SUMPRODUCT((CHOOSE({1,2,3,4,5},$R27,$V27,$Z27,$AD27,$AH27)="Yes")*(((CHOOSE({1,2,3,4,5},$S27,$W27,$AA27,$AE27,$AI27)="Yes")+(CHOOSE({1,2,3,4,5},$S27,$W27,$AA27,$AE27,$AI27)=TRUE))>0)))} -> 0 | AM27: 46287 | AN27: =IF(OR($A27="",$AM27=""),"",TODAY()-$AM27) -> 1 | BA27: 23 | BZ27: Unassigned | CA27: No | CB27: =IF($A27="","",_xlfn.LET(_xlpm.sfp,AND($P27<>"",$P27<>"N/A",$P27<>"No Min RQ"),_xlpm.slp,AND($T27<>"",$T27<>"N/A",$T27<>"No Min RQ"),_xlpm.ffp,AND($X27<>"",$X27<>"N/A",$X27<>"No Min RQ"),_xlpm.chp,AND($AB27<>"",$AB27<>"N/A",$AB27<>"No Min RQ"),_xlpm.usp,AND($AF27<>"",$AF27<>"N/A",$AF27<>"No Min RQ"),_xlpm.n,_xlpm.sfp+_xlpm.slp+_xlpm.ffp+_xlpm.chp+_xlpm.usp,_xlpm.sub,(_xlpm.sfp*($P27="Submitted"))+(_xlpm.slp*($T27="Submitted"))+(_xlpm.ffp*($X27="Submitted"))+(_xlpm.chp*($AB27="Submitted"))+(_xlpm.usp*($AF27="Submitted")),_xlpm.term,(_xlpm.sfp*OR($P27="Approved",$P27="Declined"))+(_xlpm.slp*OR($T27="Approved",$T27="Declined"))+(_xlpm.ffp*OR($X27="Approved",$X27="Declined"))+(_xlpm.chp*OR($AB27="Approved",$AB27="Declined"))+(_xlpm.usp*OR($AF27="Approved",$AF27="Declined")),IF(_xlpm.n=0,"No applicable lenders",IF(_xlpm.sub>0,"Stays with Shaw - lender still Submitted",IF(_xlpm.term=_xlpm.n,"Clear - all applicable lenders Approved or Declined","Stays with Shaw - not all lenders Approved or Declined")))))
A28: BRM ROOFING & CONSTRUCTION SERVICES, INC | B28: BRM ROOFING & CONSTRUCTION SERVICES, INC | D28: Troy Mock | E28: 817-538-7126 | F28: troy.mock@brmconstruction.com | G28: Steve Stonebraker | H28: stonebraker@getfinti.com | I28: Construction | K28: 1 | L28: =IF($A28="","",_xlfn.LET(_xlpm.ns,(--($P28="Ready 2 Submit"))+(--($T28="Ready 2 Submit"))+(--($X28="Ready 2 Submit"))+(--($AB28="Ready 2 Submit"))+(--($AF28="Ready 2 Submit")),_xlpm.wd,(--($P28="Waiting on Dealer"))+(--($T28="Waiting on Dealer"))+(--($X28="Waiting on Dealer"))+(--($AB28="Waiting on Dealer"))+(--($AF28="Waiting on Dealer")),_xlpm.sb,(--($P28="Submitted"))+(--($T28="Submitted"))+(--($X28="Submitted"))+(--($AB28="Submitted"))+(--($AF28="Submitted")),_xlpm.ap,(--($P28="Approved"))+(--($T28="Approved"))+(--($X28="Approved"))+(--($AB28="Approved"))+(--($AF28="Approved")),_xlpm.ac,(--($P28="Active"))+(--($T28="Active"))+(--($X28="Active"))+(--($AB28="Active"))+(--($AF28="Active")),_xlpm.dc,(--($P28="Declined"))+(--($T28="Declined"))+(--($X28="Declined"))+(--($AB28="Declined"))+(--($AF28="Declined")),_xlpm.aRS,(--($P28="Active"))*(--($R28="Yes"))+(--($T28="Active"))*(--($V28="Yes"))+(--($X28="Active"))*(--($Z28="Yes"))+(--($AB28="Active"))*(--($AD28="Yes"))+(--($AF28="Active"))*(--($AH28="Yes")),_xlpm.aDn,(--($P28="Active"))*(--($R28="Yes"))*(--((($S28="Yes")+($S28=TRUE))>0))+(--($T28="Active"))*(--($V28="Yes"))*(--((($W28="Yes")+($W28=TRUE))>0))+(--($X28="Active"))*(--($Z28="Yes"))*(--((($AA28="Yes")+($AA28=TRUE))>0))+(--($AB28="Active"))*(--($AD28="Yes"))*(--((($AE28="Yes")+($AE28=TRUE))>0))+(--($AF28="Active"))*(--($AH28="Yes"))*(--((($AI28="Yes")+($AI28=TRUE))>0)),_xlpm.inPlay,_xlpm.ns+_xlpm.wd+_xlpm.sb+_xlpm.ap,IF(AND(_xlpm.ac>0,_xlpm.inPlay=0,_xlpm.aDn=_xlpm.ac),"LIVE DLR",IF(AND(_xlpm.aRS>0,_xlpm.aDn<_xlpm.aRS),"Training",IF(_xlpm.aRS>0,"Active",IF(AND(_xlpm.dc>0,_xlpm.inPlay+_xlpm.ac=0),"Dead",IF(OR($CA28="Yes",$CA28=TRUE),"Rate Sheet",IF(AND($AJ28<>"",$AK28=FALSE),"Waiting on Dealer",IF(_xlpm.sb>0,"Waiting on Lender",IF(AND(_xlpm.ap+_xlpm.ac>0,_xlpm.ns+_xlpm.wd=0),"Rate Sheet","Application Submitted")))))))))) -> Waiting on Lender | M28: 46249 | N28: 46280 | O28: SF, SL, FF | P28: Submitted | Q28: 46280 | R28: No | S28: No | T28: No Min RQ | U28: =IF(OR(U28="",U28=0),IF($T28="Submitted",TODAY(),""),U28) | V28: No | W28: No | X28: Submitted | Y28: =IF(OR(Y28="",Y28=0),IF($X28="Submitted",TODAY(),""),Y28) -> 46286 | Z28: No | AA28: No | AB28: N/A | AC28: =IF(OR(AC28="",AC28=0),IF($AB28="Submitted",TODAY(),""),AC28) | AD28: No | AE28: No | AF28: N/A | AG28: =IF(OR(AG28="",AG28=0),IF($AF28="Submitted",TODAY(),""),AG28) | AH28: No | AI28: No | AJ28: Need Bank Statments and Voided Check | AK28: TRUE | AL28: {=IF($A28="","",SUMPRODUCT((CHOOSE({1,2,3,4,5},$R28,$V28,$Z28,$AD28,$AH28)="Yes")*(((CHOOSE({1,2,3,4,5},$S28,$W28,$AA28,$AE28,$AI28)="Yes")+(CHOOSE({1,2,3,4,5},$S28,$W28,$AA28,$AE28,$AI28)=TRUE))>0)))} -> 0 | AM28: 46286 | AN28: =IF(OR($A28="",$AM28=""),"",TODAY()-$AM28) -> 2 | BA28: 24 | BZ28: Unassigned | CA28: No | CB28: =IF($A28="","",_xlfn.LET(_xlpm.sfp,AND($P28<>"",$P28<>"N/A",$P28<>"No Min RQ"),_xlpm.slp,AND($T28<>"",$T28<>"N/A",$T28<>"No Min RQ"),_xlpm.ffp,AND($X28<>"",$X28<>"N/A",$X28<>"No Min RQ"),_xlpm.chp,AND($AB28<>"",$AB28<>"N/A",$AB28<>"No Min RQ"),_xlpm.usp,AND($AF28<>"",$AF28<>"N/A",$AF28<>"No Min RQ"),_xlpm.n,_xlpm.sfp+_xlpm.slp+_xlpm.ffp+_xlpm.chp+_xlpm.usp,_xlpm.sub,(_xlpm.sfp*($P28="Submitted"))+(_xlpm.slp*($T28="Submitted"))+(_xlpm.ffp*($X28="Submitted"))+(_xlpm.chp*($AB28="Submitted"))+(_xlpm.usp*($AF28="Submitted")),_xlpm.term,(_xlpm.sfp*OR($P28="Approved",$P28="Declined"))+(_xlpm.slp*OR($T28="Approved",$T28="Declined"))+(_xlpm.ffp*OR($X28="Approved",$X28="Declined"))+(_xlpm.chp*OR($AB28="Approved",$AB28="Declined"))+(_xlpm.usp*OR($AF28="Approved",$AF28="Declined")),IF(_xlpm.n=0,"No applicable lenders",IF(_xlpm.sub>0,"Stays with Shaw - lender still Submitted",IF(_xlpm.term=_xlpm.n,"Clear - all applicable lenders Approved or Declined","Stays with Shaw - not all lenders Approved or Declined")))))
A29: Taves Contracting Services LLC | B29: Taves Fencing | D29: Trevor Taves | E29: 319-540-9542 | F29: trevor@tavesco.com | G29: Scott Williams | H29: scott.williams.aftr@gmail.com | I29: Roofing | L29: =IF($A29="","",_xlfn.LET(_xlpm.ns,(--($P29="Ready 2 Submit"))+(--($T29="Ready 2 Submit"))+(--($X29="Ready 2 Submit"))+(--($AB29="Ready 2 Submit"))+(--($AF29="Ready 2 Submit")),_xlpm.wd,(--($P29="Waiting on Dealer"))+(--($T29="Waiting on Dealer"))+(--($X29="Waiting on Dealer"))+(--($AB29="Waiting on Dealer"))+(--($AF29="Waiting on Dealer")),_xlpm.sb,(--($P29="Submitted"))+(--($T29="Submitted"))+(--($X29="Submitted"))+(--($AB29="Submitted"))+(--($AF29="Submitted")),_xlpm.ap,(--($P29="Approved"))+(--($T29="Approved"))+(--($X29="Approved"))+(--($AB29="Approved"))+(--($AF29="Approved")),_xlpm.ac,(--($P29="Active"))+(--($T29="Active"))+(--($X29="Active"))+(--($AB29="Active"))+(--($AF29="Active")),_xlpm.dc,(--($P29="Declined"))+(--($T29="Declined"))+(--($X29="Declined"))+(--($AB29="Declined"))+(--($AF29="Declined")),_xlpm.aRS,(--($P29="Active"))*(--($R29="Yes"))+(--($T29="Active"))*(--($V29="Yes"))+(--($X29="Active"))*(--($Z29="Yes"))+(--($AB29="Active"))*(--($AD29="Yes"))+(--($AF29="Active"))*(--($AH29="Yes")),_xlpm.aDn,(--($P29="Active"))*(--($R29="Yes"))*(--((($S29="Yes")+($S29=TRUE))>0))+(--($T29="Active"))*(--($V29="Yes"))*(--((($W29="Yes")+($W29=TRUE))>0))+(--($X29="Active"))*(--($Z29="Yes"))*(--((($AA29="Yes")+($AA29=TRUE))>0))+(--($AB29="Active"))*(--($AD29="Yes"))*(--((($AE29="Yes")+($AE29=TRUE))>0))+(--($AF29="Active"))*(--($AH29="Yes"))*(--((($AI29="Yes")+($AI29=TRUE))>0)),_xlpm.inPlay,_xlpm.ns+_xlpm.wd+_xlpm.sb+_xlpm.ap,IF(AND(_xlpm.ac>0,_xlpm.inPlay=0,_xlpm.aDn=_xlpm.ac),"LIVE DLR",IF(AND(_xlpm.aRS>0,_xlpm.aDn<_xlpm.aRS),"Training",IF(_xlpm.aRS>0,"Active",IF(AND(_xlpm.dc>0,_xlpm.inPlay+_xlpm.ac=0),"Dead",IF(OR($CA29="Yes",$CA29=TRUE),"Rate Sheet",IF(AND($AJ29<>"",$AK29=FALSE),"Waiting on Dealer",IF(_xlpm.sb>0,"Waiting on Lender",IF(AND(_xlpm.ap+_xlpm.ac>0,_xlpm.ns+_xlpm.wd=0),"Rate Sheet","Application Submitted")))))))))) -> Waiting on Lender | M29: 46252 | N29: 46255 | P29: Submitted | Q29: 46274 | R29: No | S29: No | T29: Approved | U29: 46274 | V29: No | W29: No | X29: Approved | Y29: 46269 | Z29: No | AA29: No | AB29: N/A | AC29: =IF(OR(AC29="",AC29=0),IF($AB29="Submitted",TODAY(),""),AC29) | AD29: No | AE29: No | AF29: N/A | AG29: =IF(OR(AG29="",AG29=0),IF($AF29="Submitted",TODAY(),""),AG29) | AH29: No | AI29: No | AJ29: Sunlight needs additional documents - sales contract, insurance, July or August bank statement. Foundation approved 9/17/26 - dealer call done. | AK29: TRUE | AL29: {=IF($A29="","",SUMPRODUCT((CHOOSE({1,2,3,4,5},$R29,$V29,$Z29,$AD29,$AH29)="Yes")*(((CHOOSE({1,2,3,4,5},$S29,$W29,$AA29,$AE29,$AI29)="Yes")+(CHOOSE({1,2,3,4,5},$S29,$W29,$AA29,$AE29,$AI29)=TRUE))>0)))} -> 0 | AM29: 46269 | AN29: =IF(OR($A29="",$AM29=""),"",TODAY()-$AM29) -> 19 | AT29: 36564000 | BA29: 25 | BZ29: Unassigned | CA29: No | CB29: =IF($A29="","",_xlfn.LET(_xlpm.sfp,AND($P29<>"",$P29<>"N/A",$P29<>"No Min RQ"),_xlpm.slp,AND($T29<>"",$T29<>"N/A",$T29<>"No Min RQ"),_xlpm.ffp,AND($X29<>"",$X29<>"N/A",$X29<>"No Min RQ"),_xlpm.chp,AND($AB29<>"",$AB29<>"N/A",$AB29<>"No Min RQ"),_xlpm.usp,AND($AF29<>"",$AF29<>"N/A",$AF29<>"No Min RQ"),_xlpm.n,_xlpm.sfp+_xlpm.slp+_xlpm.ffp+_xlpm.chp+_xlpm.usp,_xlpm.sub,(_xlpm.sfp*($P29="Submitted"))+(_xlpm.slp*($T29="Submitted"))+(_xlpm.ffp*($X29="Submitted"))+(_xlpm.chp*($AB29="Submitted"))+(_xlpm.usp*($AF29="Submitted")),_xlpm.term,(_xlpm.sfp*OR($P29="Approved",$P29="Declined"))+(_xlpm.slp*OR($T29="Approved",$T29="Declined"))+(_xlpm.ffp*OR($X29="Approved",$X29="Declined"))+(_xlpm.chp*OR($AB29="Approved",$AB29="Declined"))+(_xlpm.usp*OR($AF29="Approved",$AF29="Declined")),IF(_xlpm.n=0,"No applicable lenders",IF(_xlpm.sub>0,"Stays with Shaw - lender still Submitted",IF(_xlpm.term=_xlpm.n,"Clear - all applicable lenders Approved or Declined","Stays with Shaw - not all lenders Approved or Declined")))))
A30: Tite Home LLC | B30: Tite Home | D30: Tyler Story | E30: 480-559-1212 | F30: tyler@titehome.com | G30: Tyler Story | H30: tylerstory32@gmail.com | I30: HVAC & solar | K30: 2 | L30: =IF($A30="","",_xlfn.LET(_xlpm.ns,(--($P30="Ready 2 Submit"))+(--($T30="Ready 2 Submit"))+(--($X30="Ready 2 Submit"))+(--($AB30="Ready 2 Submit"))+(--($AF30="Ready 2 Submit")),_xlpm.wd,(--($P30="Waiting on Dealer"))+(--($T30="Waiting on Dealer"))+(--($X30="Waiting on Dealer"))+(--($AB30="Waiting on Dealer"))+(--($AF30="Waiting on Dealer")),_xlpm.sb,(--($P30="Submitted"))+(--($T30="Submitted"))+(--($X30="Submitted"))+(--($AB30="Submitted"))+(--($AF30="Submitted")),_xlpm.ap,(--($P30="Approved"))+(--($T30="Approved"))+(--($X30="Approved"))+(--($AB30="Approved"))+(--($AF30="Approved")),_xlpm.ac,(--($P30="Active"))+(--($T30="Active"))+(--($X30="Active"))+(--($AB30="Active"))+(--($AF30="Active")),_xlpm.dc,(--($P30="Declined"))+(--($T30="Declined"))+(--($X30="Declined"))+(--($AB30="Declined"))+(--($AF30="Declined")),_xlpm.aRS,(--($P30="Active"))*(--($R30="Yes"))+(--($T30="Active"))*(--($V30="Yes"))+(--($X30="Active"))*(--($Z30="Yes"))+(--($AB30="Active"))*(--($AD30="Yes"))+(--($AF30="Active"))*(--($AH30="Yes")),_xlpm.aDn,(--($P30="Active"))*(--($R30="Yes"))*(--((($S30="Yes")+($S30=TRUE))>0))+(--($T30="Active"))*(--($V30="Yes"))*(--((($W30="Yes")+($W30=TRUE))>0))+(--($X30="Active"))*(--($Z30="Yes"))*(--((($AA30="Yes")+($AA30=TRUE))>0))+(--($AB30="Active"))*(--($AD30="Yes"))*(--((($AE30="Yes")+($AE30=TRUE))>0))+(--($AF30="Active"))*(--($AH30="Yes"))*(--((($AI30="Yes")+($AI30=TRUE))>0)),_xlpm.inPlay,_xlpm.ns+_xlpm.wd+_xlpm.sb+_xlpm.ap,IF(AND(_xlpm.ac>0,_xlpm.inPlay=0,_xlpm.aDn=_xlpm.ac),"LIVE DLR",IF(AND(_xlpm.aRS>0,_xlpm.aDn<_xlpm.aRS),"Training",IF(_xlpm.aRS>0,"Active",IF(AND(_xlpm.dc>0,_xlpm.inPlay+_xlpm.ac=0),"Dead",IF(OR($CA30="Yes",$CA30=TRUE),"Rate Sheet",IF(AND($AJ30<>"",$AK30=FALSE),"Waiting on Dealer",IF(_xlpm.sb>0,"Waiting on Lender",IF(AND(_xlpm.ap+_xlpm.ac>0,_xlpm.ns+_xlpm.wd=0),"Rate Sheet","Application Submitted")))))))))) -> Waiting on Lender | M30: 46258 | N30: 46258 | O30: SF | P30: Submitted | Q30: 46274 | R30: No | S30: No | T30: N/A | U30: =IF(OR(U30="",U30=0),IF($T30="Submitted",TODAY(),""),U30) | V30: No | W30: No | X30: Approved | Y30: 45194 | Z30: No | AA30: No | AB30: Submitted | AC30: =IF(OR(AC30="",AC30=0),IF($AB30="Submitted",TODAY(),""),AC30) -> 46287 | AD30: No | AE30: No | AF30: N/A | AG30: =IF(OR(AG30="",AG30=0),IF($AF30="Submitted",TODAY(),""),AG30) | AH30: No | AI30: No | AJ30: waiting for voided check and business license from Tyler (for Chowder), also waiting to hear back from SF on their decision, may need to reapply | AK30: TRUE | AL30: {=IF($A30="","",SUMPRODUCT((CHOOSE({1,2,3,4,5},$R30,$V30,$Z30,$AD30,$AH30)="Yes")*(((CHOOSE({1,2,3,4,5},$S30,$W30,$AA30,$AE30,$AI30)="Yes")+(CHOOSE({1,2,3,4,5},$S30,$W30,$AA30,$AE30,$AI30)=TRUE))>0)))} -> 0 | AM30: 46287 | AN30: =IF(OR($A30="",$AM30=""),"",TODAY()-$AM30) -> 1 | AT30: 19023000 | BA30: 26 | BZ30: Unassigned | CA30: No | CB30: =IF($A30="","",_xlfn.LET(_xlpm.sfp,AND($P30<>"",$P30<>"N/A",$P30<>"No Min RQ"),_xlpm.slp,AND($T30<>"",$T30<>"N/A",$T30<>"No Min RQ"),_xlpm.ffp,AND($X30<>"",$X30<>"N/A",$X30<>"No Min RQ"),_xlpm.chp,AND($AB30<>"",$AB30<>"N/A",$AB30<>"No Min RQ"),_xlpm.usp,AND($AF30<>"",$AF30<>"N/A",$AF30<>"No Min RQ"),_xlpm.n,_xlpm.sfp+_xlpm.slp+_xlpm.ffp+_xlpm.chp+_xlpm.usp,_xlpm.sub,(_xlpm.sfp*($P30="Submitted"))+(_xlpm.slp*($T30="Submitted"))+(_xlpm.ffp*($X30="Submitted"))+(_xlpm.chp*($AB30="Submitted"))+(_xlpm.usp*($AF30="Submitted")),_xlpm.term,(_xlpm.sfp*OR($P30="Approved",$P30="Declined"))+(_xlpm.slp*OR($T30="Approved",$T30="Declined"))+(_xlpm.ffp*OR($X30="Approved",$X30="Declined"))+(_xlpm.chp*OR($AB30="Approved",$AB30="Declined"))+(_xlpm.usp*OR($AF30="Approved",$AF30="Declined")),IF(_xlpm.n=0,"No applicable lenders",IF(_xlpm.sub>0,"Stays with Shaw - lender still Submitted",IF(_xlpm.term=_xlpm.n,"Clear - all applicable lenders Approved or Declined","Stays with Shaw - not all lenders Approved or Declined")))))
A31: House to Home Remodeling Inc. | B31: N/A | G31: Clint Cowley | H31: ccowley@gowefund.com | I31: roofing, landscaping, hardscaping, interior/exterior paint, windows, doors, mold remediation | L31: =IF($A31="","",_xlfn.LET(_xlpm.ns,(--($P31="Ready 2 Submit"))+(--($T31="Ready 2 Submit"))+(--($X31="Ready 2 Submit"))+(--($AB31="Ready 2 Submit"))+(--($AF31="Ready 2 Submit")),_xlpm.wd,(--($P31="Waiting on Dealer"))+(--($T31="Waiting on Dealer"))+(--($X31="Waiting on Dealer"))+(--($AB31="Waiting on Dealer"))+(--($AF31="Waiting on Dealer")),_xlpm.sb,(--($P31="Submitted"))+(--($T31="Submitted"))+(--($X31="Submitted"))+(--($AB31="Submitted"))+(--($AF31="Submitted")),_xlpm.ap,(--($P31="Approved"))+(--($T31="Approved"))+(--($X31="Approved"))+(--($AB31="Approved"))+(--($AF31="Approved")),_xlpm.ac,(--($P31="Active"))+(--($T31="Active"))+(--($X31="Active"))+(--($AB31="Active"))+(--($AF31="Active")),_xlpm.dc,(--($P31="Declined"))+(--($T31="Declined"))+(--($X31="Declined"))+(--($AB31="Declined"))+(--($AF31="Declined")),_xlpm.aRS,(--($P31="Active"))*(--($R31="Yes"))+(--($T31="Active"))*(--($V31="Yes"))+(--($X31="Active"))*(--($Z31="Yes"))+(--($AB31="Active"))*(--($AD31="Yes"))+(--($AF31="Active"))*(--($AH31="Yes")),_xlpm.aDn,(--($P31="Active"))*(--($R31="Yes"))*(--((($S31="Yes")+($S31=TRUE))>0))+(--($T31="Active"))*(--($V31="Yes"))*(--((($W31="Yes")+($W31=TRUE))>0))+(--($X31="Active"))*(--($Z31="Yes"))*(--((($AA31="Yes")+($AA31=TRUE))>0))+(--($AB31="Active"))*(--($AD31="Yes"))*(--((($AE31="Yes")+($AE31=TRUE))>0))+(--($AF31="Active"))*(--($AH31="Yes"))*(--((($AI31="Yes")+($AI31=TRUE))>0)),_xlpm.inPlay,_xlpm.ns+_xlpm.wd+_xlpm.sb+_xlpm.ap,IF(AND(_xlpm.ac>0,_xlpm.inPlay=0,_xlpm.aDn=_xlpm.ac),"LIVE DLR",IF(AND(_xlpm.aRS>0,_xlpm.aDn<_xlpm.aRS),"Training",IF(_xlpm.aRS>0,"Active",IF(AND(_xlpm.dc>0,_xlpm.inPlay+_xlpm.ac=0),"Dead",IF(OR($CA31="Yes",$CA31=TRUE),"Rate Sheet",IF(AND($AJ31<>"",$AK31=FALSE),"Waiting on Dealer",IF(_xlpm.sb>0,"Waiting on Lender",IF(AND(_xlpm.ap+_xlpm.ac>0,_xlpm.ns+_xlpm.wd=0),"Rate Sheet","Application Submitted")))))))))) -> Dead | M31: 46216 | N31: 46216 | O31: SL, SV, FF | P31: Declined | Q31: =IF(OR(Q31="",Q31=0),IF($P31="Submitted",TODAY(),""),Q31) | R31: Yes | S31: Yes | T31: Declined | U31: =IF(OR(U31="",U31=0),IF($T31="Submitted",TODAY(),""),U31) | V31: No | W31: No | X31: Declined | Y31: =IF(OR(Y31="",Y31=0),IF($X31="Submitted",TODAY(),""),Y31) | Z31: No | AA31: No | AB31: N/A | AC31: =IF(OR(AC31="",AC31=0),IF($AB31="Submitted",TODAY(),""),AC31) | AD31: No | AE31: No | AF31: N/A | AG31: =IF(OR(AG31="",AG31=0),IF($AF31="Submitted",TODAY(),""),AG31) | AH31: No | AI31: No | AJ31: Sent to lenders and sent dlr "lenders submitted" email. | AK31: TRUE | AL31: {=IF($A31="","",SUMPRODUCT((CHOOSE({1,2,3,4,5},$R31,$V31,$Z31,$AD31,$AH31)="Yes")*(((CHOOSE({1,2,3,4,5},$S31,$W31,$AA31,$AE31,$AI31)="Yes")+(CHOOSE({1,2,3,4,5},$S31,$W31,$AA31,$AE31,$AI31)=TRUE))>0)))} -> 1 | AN31: =IF(OR($A31="",$AM31=""),"",TODAY()-$AM31) | BA31: 27 | BZ31: Unassigned | CA31: No | CB31: =IF($A31="","",_xlfn.LET(_xlpm.sfp,AND($P31<>"",$P31<>"N/A",$P31<>"No Min RQ"),_xlpm.slp,AND($T31<>"",$T31<>"N/A",$T31<>"No Min RQ"),_xlpm.ffp,AND($X31<>"",$X31<>"N/A",$X31<>"No Min RQ"),_xlpm.chp,AND($AB31<>"",$AB31<>"N/A",$AB31<>"No Min RQ"),_xlpm.usp,AND($AF31<>"",$AF31<>"N/A",$AF31<>"No Min RQ"),_xlpm.n,_xlpm.sfp+_xlpm.slp+_xlpm.ffp+_xlpm.chp+_xlpm.usp,_xlpm.sub,(_xlpm.sfp*($P31="Submitted"))+(_xlpm.slp*($T31="Submitted"))+(_xlpm.ffp*($X31="Submitted"))+(_xlpm.chp*($AB31="Submitted"))+(_xlpm.usp*($AF31="Submitted")),_xlpm.term,(_xlpm.sfp*OR($P31="Approved",$P31="Declined"))+(_xlpm.slp*OR($T31="Approved",$T31="Declined"))+(_xlpm.ffp*OR($X31="Approved",$X31="Declined"))+(_xlpm.chp*OR($AB31="Approved",$AB31="Declined"))+(_xlpm.usp*OR($AF31="Approved",$AF31="Declined")),IF(_xlpm.n=0,"No applicable lenders",IF(_xlpm.sub>0,"Stays with Shaw - lender still Submitted",IF(_xlpm.term=_xlpm.n,"Clear - all applicable lenders Approved or Declined","Stays with Shaw - not all lenders Approved or Declined")))))
A32: Iron Ridge Group LLC | B32: Iron Ridge HVAC | D32: Brennen Lesollen | E32: 385-775-4294 | F32: lesollen.87@gmail.com | G32: Steve Stonebraker | H32: stonebraker@getfinti.com | I32: HVAC | L32: =IF($A32="","",_xlfn.LET(_xlpm.ns,(--($P32="Ready 2 Submit"))+(--($T32="Ready 2 Submit"))+(--($X32="Ready 2 Submit"))+(--($AB32="Ready 2 Submit"))+(--($AF32="Ready 2 Submit")),_xlpm.wd,(--($P32="Waiting on Dealer"))+(--($T32="Waiting on Dealer"))+(--($X32="Waiting on Dealer"))+(--($AB32="Waiting on Dealer"))+(--($AF32="Waiting on Dealer")),_xlpm.sb,(--($P32="Submitted"))+(--($T32="Submitted"))+(--($X32="Submitted"))+(--($AB32="Submitted"))+(--($AF32="Submitted")),_xlpm.ap,(--($P32="Approved"))+(--($T32="Approved"))+(--($X32="Approved"))+(--($AB32="Approved"))+(--($AF32="Approved")),_xlpm.ac,(--($P32="Active"))+(--($T32="Active"))+(--($X32="Active"))+(--($AB32="Active"))+(--($AF32="Active")),_xlpm.dc,(--($P32="Declined"))+(--($T32="Declined"))+(--($X32="Declined"))+(--($AB32="Declined"))+(--($AF32="Declined")),_xlpm.aRS,(--($P32="Active"))*(--($R32="Yes"))+(--($T32="Active"))*(--($V32="Yes"))+(--($X32="Active"))*(--($Z32="Yes"))+(--($AB32="Active"))*(--($AD32="Yes"))+(--($AF32="Active"))*(--($AH32="Yes")),_xlpm.aDn,(--($P32="Active"))*(--($R32="Yes"))*(--((($S32="Yes")+($S32=TRUE))>0))+(--($T32="Active"))*(--($V32="Yes"))*(--((($W32="Yes")+($W32=TRUE))>0))+(--($X32="Active"))*(--($Z32="Yes"))*(--((($AA32="Yes")+($AA32=TRUE))>0))+(--($AB32="Active"))*(--($AD32="Yes"))*(--((($AE32="Yes")+($AE32=TRUE))>0))+(--($AF32="Active"))*(--($AH32="Yes"))*(--((($AI32="Yes")+($AI32=TRUE))>0)),_xlpm.inPlay,_xlpm.ns+_xlpm.wd+_xlpm.sb+_xlpm.ap,IF(AND(_xlpm.ac>0,_xlpm.inPlay=0,_xlpm.aDn=_xlpm.ac),"LIVE DLR",IF(AND(_xlpm.aRS>0,_xlpm.aDn<_xlpm.aRS),"Training",IF(_xlpm.aRS>0,"Active",IF(AND(_xlpm.dc>0,_xlpm.inPlay+_xlpm.ac=0),"Dead",IF(OR($CA32="Yes",$CA32=TRUE),"Rate Sheet",IF(AND($AJ32<>"",$AK32=FALSE),"Waiting on Dealer",IF(_xlpm.sb>0,"Waiting on Lender",IF(AND(_xlpm.ap+_xlpm.ac>0,_xlpm.ns+_xlpm.wd=0),"Rate Sheet","Application Submitted")))))))))) -> Application Submitted | M32: 46153 | N32: 46280 | O32: 1. Foundation Finance | P32: No Min RQ | Q32: =IF(OR(Q32="",Q32=0),IF($P32="Submitted",TODAY(),""),Q32) | R32: No | S32: No | T32: No Min RQ | U32: =IF(OR(U32="",U32=0),IF($T32="Submitted",TODAY(),""),U32) | V32: No | W32: No | X32: No Min RQ | Y32: 46132 | Z32: Yes | AA32: Yes | AB32: N/A | AC32: =IF(OR(AC32="",AC32=0),IF($AB32="Submitted",TODAY(),""),AC32) | AD32: No | AE32: No | AF32: N/A | AG32: =IF(OR(AG32="",AG32=0),IF($AF32="Submitted",TODAY(),""),AG32) | AH32: No | AI32: No | AJ32: Need voided check and contractor's license for Chowder | AK32: TRUE | AL32: {=IF($A32="","",SUMPRODUCT((CHOOSE({1,2,3,4,5},$R32,$V32,$Z32,$AD32,$AH32)="Yes")*(((CHOOSE({1,2,3,4,5},$S32,$W32,$AA32,$AE32,$AI32)="Yes")+(CHOOSE({1,2,3,4,5},$S32,$W32,$AA32,$AE32,$AI32)=TRUE))>0)))} -> 1 | AM32: 46281 | AN32: =IF(OR($A32="",$AM32=""),"",TODAY()-$AM32) -> 7 | AT32: 35327000 | BA32: 28 | BZ32: Unassigned | CA32: No | CB32: =IF($A32="","",_xlfn.LET(_xlpm.sfp,AND($P32<>"",$P32<>"N/A",$P32<>"No Min RQ"),_xlpm.slp,AND($T32<>"",$T32<>"N/A",$T32<>"No Min RQ"),_xlpm.ffp,AND($X32<>"",$X32<>"N/A",$X32<>"No Min RQ"),_xlpm.chp,AND($AB32<>"",$AB32<>"N/A",$AB32<>"No Min RQ"),_xlpm.usp,AND($AF32<>"",$AF32<>"N/A",$AF32<>"No Min RQ"),_xlpm.n,_xlpm.sfp+_xlpm.slp+_xlpm.ffp+_xlpm.chp+_xlpm.usp,_xlpm.sub,(_xlpm.sfp*($P32="Submitted"))+(_xlpm.slp*($T32="Submitted"))+(_xlpm.ffp*($X32="Submitted"))+(_xlpm.chp*($AB32="Submitted"))+(_xlpm.usp*($AF32="Submitted")),_xlpm.term,(_xlpm.sfp*OR($P32="Approved",$P32="Declined"))+(_xlpm.slp*OR($T32="Approved",$T32="Declined"))+(_xlpm.ffp*OR($X32="Approved",$X32="Declined"))+(_xlpm.chp*OR($AB32="Approved",$AB32="Declined"))+(_xlpm.usp*OR($AF32="Approved",$AF32="Declined")),IF(_xlpm.n=0,"No applicable lenders",IF(_xlpm.sub>0,"Stays with Shaw - lender still Submitted",IF(_xlpm.term=_xlpm.n,"Clear - all applicable lenders Approved or Declined","Stays with Shaw - not all lenders Approved or Declined")))))
A33: Natural Construction LLC | B33: Natural Construction LLC | D33: Daniel Haynal | E33: 479-644-5506 | F33: dhaynal@usnaturalenergy.com | G33: Trevor Young | H33: Trevor.young@getfinti.com | I33: Roofing | K33: 1 | L33: =IF($A33="","",_xlfn.LET(_xlpm.ns,(--($P33="Ready 2 Submit"))+(--($T33="Ready 2 Submit"))+(--($X33="Ready 2 Submit"))+(--($AB33="Ready 2 Submit"))+(--($AF33="Ready 2 Submit")),_xlpm.wd,(--($P33="Waiting on Dealer"))+(--($T33="Waiting on Dealer"))+(--($X33="Waiting on Dealer"))+(--($AB33="Waiting on Dealer"))+(--($AF33="Waiting on Dealer")),_xlpm.sb,(--($P33="Submitted"))+(--($T33="Submitted"))+(--($X33="Submitted"))+(--($AB33="Submitted"))+(--($AF33="Submitted")),_xlpm.ap,(--($P33="Approved"))+(--($T33="Approved"))+(--($X33="Approved"))+(--($AB33="Approved"))+(--($AF33="Approved")),_xlpm.ac,(--($P33="Active"))+(--($T33="Active"))+(--($X33="Active"))+(--($AB33="Active"))+(--($AF33="Active")),_xlpm.dc,(--($P33="Declined"))+(--($T33="Declined"))+(--($X33="Declined"))+(--($AB33="Declined"))+(--($AF33="Declined")),_xlpm.aRS,(--($P33="Active"))*(--($R33="Yes"))+(--($T33="Active"))*(--($V33="Yes"))+(--($X33="Active"))*(--($Z33="Yes"))+(--($AB33="Active"))*(--($AD33="Yes"))+(--($AF33="Active"))*(--($AH33="Yes")),_xlpm.aDn,(--($P33="Active"))*(--($R33="Yes"))*(--((($S33="Yes")+($S33=TRUE))>0))+(--($T33="Active"))*(--($V33="Yes"))*(--((($W33="Yes")+($W33=TRUE))>0))+(--($X33="Active"))*(--($Z33="Yes"))*(--((($AA33="Yes")+($AA33=TRUE))>0))+(--($AB33="Active"))*(--($AD33="Yes"))*(--((($AE33="Yes")+($AE33=TRUE))>0))+(--($AF33="Active"))*(--($AH33="Yes"))*(--((($AI33="Yes")+($AI33=TRUE))>0)),_xlpm.inPlay,_xlpm.ns+_xlpm.wd+_xlpm.sb+_xlpm.ap,IF(AND(_xlpm.ac>0,_xlpm.inPlay=0,_xlpm.aDn=_xlpm.ac),"LIVE DLR",IF(AND(_xlpm.aRS>0,_xlpm.aDn<_xlpm.aRS),"Training",IF(_xlpm.aRS>0,"Active",IF(AND(_xlpm.dc>0,_xlpm.inPlay+_xlpm.ac=0),"Dead",IF(OR($CA33="Yes",$CA33=TRUE),"Rate Sheet",IF(AND($AJ33<>"",$AK33=FALSE),"Waiting on Dealer",IF(_xlpm.sb>0,"Waiting on Lender",IF(AND(_xlpm.ap+_xlpm.ac>0,_xlpm.ns+_xlpm.wd=0),"Rate Sheet","Application Submitted")))))))))) -> Waiting on Lender | M33: 46262 | N33: 46280 | O33: FF | P33: Ready 2 Submit | Q33: 46274 | R33: No | S33: No | T33: Active | U33: 46274 | V33: No | W33: No | X33: Submitted | Y33: 46274 | Z33: No | AA33: No | AB33: N/A | AC33: =IF(OR(AC33="",AC33=0),IF($AB33="Submitted",TODAY(),""),AC33) | AD33: No | AE33: No | AF33: N/A | AG33: =IF(OR(AG33="",AG33=0),IF($AF33="Submitted",TODAY(),""),AG33) | AH33: No | AI33: No | AJ33: Complete dealer call for Foundation - FFC has attempted 1st owner call, no answer | AK33: TRUE | AL33: {=IF($A33="","",SUMPRODUCT((CHOOSE({1,2,3,4,5},$R33,$V33,$Z33,$AD33,$AH33)="Yes")*(((CHOOSE({1,2,3,4,5},$S33,$W33,$AA33,$AE33,$AI33)="Yes")+(CHOOSE({1,2,3,4,5},$S33,$W33,$AA33,$AE33,$AI33)=TRUE))>0)))} -> 0 | AM33: 46266 | AN33: =IF(OR($A33="",$AM33=""),"",TODAY()-$AM33) -> 22 | AP33: 815134282 | AR33: Username: naturalconstruction-finti@sunlightfinancial.com.slf. PW: syG9CRFpYO%7AO!IUr Dealer code: 365324 | BA33: 29 | BZ33: Unassigned | CA33: No | CB33: =IF($A33="","",_xlfn.LET(_xlpm.sfp,AND($P33<>"",$P33<>"N/A",$P33<>"No Min RQ"),_xlpm.slp,AND($T33<>"",$T33<>"N/A",$T33<>"No Min RQ"),_xlpm.ffp,AND($X33<>"",$X33<>"N/A",$X33<>"No Min RQ"),_xlpm.chp,AND($AB33<>"",$AB33<>"N/A",$AB33<>"No Min RQ"),_xlpm.usp,AND($AF33<>"",$AF33<>"N/A",$AF33<>"No Min RQ"),_xlpm.n,_xlpm.sfp+_xlpm.slp+_xlpm.ffp+_xlpm.chp+_xlpm.usp,_xlpm.sub,(_xlpm.sfp*($P33="Submitted"))+(_xlpm.slp*($T33="Submitted"))+(_xlpm.ffp*($X33="Submitted"))+(_xlpm.chp*($AB33="Submitted"))+(_xlpm.usp*($AF33="Submitted")),_xlpm.term,(_xlpm.sfp*OR($P33="Approved",$P33="Declined"))+(_xlpm.slp*OR($T33="Approved",$T33="Declined"))+(_xlpm.ffp*OR($X33="Approved",$X33="Declined"))+(_xlpm.chp*OR($AB33="Approved",$AB33="Declined"))+(_xlpm.usp*OR($AF33="Approved",$AF33="Declined")),IF(_xlpm.n=0,"No applicable lenders",IF(_xlpm.sub>0,"Stays with Shaw - lender still Submitted",IF(_xlpm.term=_xlpm.n,"Clear - all applicable lenders Approved or Declined","Stays with Shaw - not all lenders Approved or Declined")))))
A34: Chaseco Air Conditioning | B34: Chaseco Air Conditioning | D34: Chase Robinson | E34: 480-696-9556 | F34: chaseco24@gmail.com | G34: Shawn Hanks | H34: Shawn@getfinti.com | I34: HVAC | K34: 3 | L34: =IF($A34="","",_xlfn.LET(_xlpm.ns,(--($P34="Ready 2 Submit"))+(--($T34="Ready 2 Submit"))+(--($X34="Ready 2 Submit"))+(--($AB34="Ready 2 Submit"))+(--($AF34="Ready 2 Submit")),_xlpm.wd,(--($P34="Waiting on Dealer"))+(--($T34="Waiting on Dealer"))+(--($X34="Waiting on Dealer"))+(--($AB34="Waiting on Dealer"))+(--($AF34="Waiting on Dealer")),_xlpm.sb,(--($P34="Submitted"))+(--($T34="Submitted"))+(--($X34="Submitted"))+(--($AB34="Submitted"))+(--($AF34="Submitted")),_xlpm.ap,(--($P34="Approved"))+(--($T34="Approved"))+(--($X34="Approved"))+(--($AB34="Approved"))+(--($AF34="Approved")),_xlpm.ac,(--($P34="Active"))+(--($T34="Active"))+(--($X34="Active"))+(--($AB34="Active"))+(--($AF34="Active")),_xlpm.dc,(--($P34="Declined"))+(--($T34="Declined"))+(--($X34="Declined"))+(--($AB34="Declined"))+(--($AF34="Declined")),_xlpm.aRS,(--($P34="Active"))*(--($R34="Yes"))+(--($T34="Active"))*(--($V34="Yes"))+(--($X34="Active"))*(--($Z34="Yes"))+(--($AB34="Active"))*(--($AD34="Yes"))+(--($AF34="Active"))*(--($AH34="Yes")),_xlpm.aDn,(--($P34="Active"))*(--($R34="Yes"))*(--((($S34="Yes")+($S34=TRUE))>0))+(--($T34="Active"))*(--($V34="Yes"))*(--((($W34="Yes")+($W34=TRUE))>0))+(--($X34="Active"))*(--($Z34="Yes"))*(--((($AA34="Yes")+($AA34=TRUE))>0))+(--($AB34="Active"))*(--($AD34="Yes"))*(--((($AE34="Yes")+($AE34=TRUE))>0))+(--($AF34="Active"))*(--($AH34="Yes"))*(--((($AI34="Yes")+($AI34=TRUE))>0)),_xlpm.inPlay,_xlpm.ns+_xlpm.wd+_xlpm.sb+_xlpm.ap,IF(AND(_xlpm.ac>0,_xlpm.inPlay=0,_xlpm.aDn=_xlpm.ac),"LIVE DLR",IF(AND(_xlpm.aRS>0,_xlpm.aDn<_xlpm.aRS),"Training",IF(_xlpm.aRS>0,"Active",IF(AND(_xlpm.dc>0,_xlpm.inPlay+_xlpm.ac=0),"Dead",IF(OR($CA34="Yes",$CA34=TRUE),"Rate Sheet",IF(AND($AJ34<>"",$AK34=FALSE),"Waiting on Dealer",IF(_xlpm.sb>0,"Waiting on Lender",IF(AND(_xlpm.ap+_xlpm.ac>0,_xlpm.ns+_xlpm.wd=0),"Rate Sheet","Application Submitted")))))))))) -> Active | M34: 46266 | N34: 46280 | O34: SF, FF, CH | P34: Declined | Q34: 46274 | R34: No | S34: No | T34: Declined | U34: 46279 | V34: No | W34: No | X34: Submitted | Y34: 46274 | Z34: No | AA34: No | AB34: Active | AC34: 46274 | AD34: Yes | AE34: Yes | AF34: N/A | AG34: =IF(OR(AG34="",AG34=0),IF($AF34="Submitted",TODAY(),""),AG34) | AH34: No | AI34: No | AJ34: Need bank statements for Sunlight; FF owner call complete - FFC now waiting on answer to a clarifying question | AK34: TRUE | AL34: {=IF($A34="","",SUMPRODUCT((CHOOSE({1,2,3,4,5},$R34,$V34,$Z34,$AD34,$AH34)="Yes")*(((CHOOSE({1,2,3,4,5},$S34,$W34,$AA34,$AE34,$AI34)="Yes")+(CHOOSE({1,2,3,4,5},$S34,$W34,$AA34,$AE34,$AI34)=TRUE))>0)))} -> 1 | AM34: 46276 | AN34: =IF(OR($A34="",$AM34=""),"",TODAY()-$AM34) -> 12 | BA34: 30 | BZ34: Unassigned | CA34: No | CB34: =IF($A34="","",_xlfn.LET(_xlpm.sfp,AND($P34<>"",$P34<>"N/A",$P34<>"No Min RQ"),_xlpm.slp,AND($T34<>"",$T34<>"N/A",$T34<>"No Min RQ"),_xlpm.ffp,AND($X34<>"",$X34<>"N/A",$X34<>"No Min RQ"),_xlpm.chp,AND($AB34<>"",$AB34<>"N/A",$AB34<>"No Min RQ"),_xlpm.usp,AND($AF34<>"",$AF34<>"N/A",$AF34<>"No Min RQ"),_xlpm.n,_xlpm.sfp+_xlpm.slp+_xlpm.ffp+_xlpm.chp+_xlpm.usp,_xlpm.sub,(_xlpm.sfp*($P34="Submitted"))+(_xlpm.slp*($T34="Submitted"))+(_xlpm.ffp*($X34="Submitted"))+(_xlpm.chp*($AB34="Submitted"))+(_xlpm.usp*($AF34="Submitted")),_xlpm.term,(_xlpm.sfp*OR($P34="Approved",$P34="Declined"))+(_xlpm.slp*OR($T34="Approved",$T34="Declined"))+(_xlpm.ffp*OR($X34="Approved",$X34="Declined"))+(_xlpm.chp*OR($AB34="Approved",$AB34="Declined"))+(_xlpm.usp*OR($AF34="Approved",$AF34="Declined")),IF(_xlpm.n=0,"No applicable lenders",IF(_xlpm.sub>0,"Stays with Shaw - lender still Submitted",IF(_xlpm.term=_xlpm.n,"Clear - all applicable lenders Approved or Declined","Stays with Shaw - not all lenders Approved or Declined")))))
A35: Bestway Heating & Air LLC | B35: Bestway Heating & Air LLC | D35: Brandon Burton | E35: 214-315-4240 | F35: bestway2012@outlook.com | G35: Trevor Young | H35: trevor.young@getfinti.com | I35: HVAC | K35: 2 | L35: =IF($A35="","",_xlfn.LET(_xlpm.ns,(--($P35="Ready 2 Submit"))+(--($T35="Ready 2 Submit"))+(--($X35="Ready 2 Submit"))+(--($AB35="Ready 2 Submit"))+(--($AF35="Ready 2 Submit")),_xlpm.wd,(--($P35="Waiting on Dealer"))+(--($T35="Waiting on Dealer"))+(--($X35="Waiting on Dealer"))+(--($AB35="Waiting on Dealer"))+(--($AF35="Waiting on Dealer")),_xlpm.sb,(--($P35="Submitted"))+(--($T35="Submitted"))+(--($X35="Submitted"))+(--($AB35="Submitted"))+(--($AF35="Submitted")),_xlpm.ap,(--($P35="Approved"))+(--($T35="Approved"))+(--($X35="Approved"))+(--($AB35="Approved"))+(--($AF35="Approved")),_xlpm.ac,(--($P35="Active"))+(--($T35="Active"))+(--($X35="Active"))+(--($AB35="Active"))+(--($AF35="Active")),_xlpm.dc,(--($P35="Declined"))+(--($T35="Declined"))+(--($X35="Declined"))+(--($AB35="Declined"))+(--($AF35="Declined")),_xlpm.aRS,(--($P35="Active"))*(--($R35="Yes"))+(--($T35="Active"))*(--($V35="Yes"))+(--($X35="Active"))*(--($Z35="Yes"))+(--($AB35="Active"))*(--($AD35="Yes"))+(--($AF35="Active"))*(--($AH35="Yes")),_xlpm.aDn,(--($P35="Active"))*(--($R35="Yes"))*(--((($S35="Yes")+($S35=TRUE))>0))+(--($T35="Active"))*(--($V35="Yes"))*(--((($W35="Yes")+($W35=TRUE))>0))+(--($X35="Active"))*(--($Z35="Yes"))*(--((($AA35="Yes")+($AA35=TRUE))>0))+(--($AB35="Active"))*(--($AD35="Yes"))*(--((($AE35="Yes")+($AE35=TRUE))>0))+(--($AF35="Active"))*(--($AH35="Yes"))*(--((($AI35="Yes")+($AI35=TRUE))>0)),_xlpm.inPlay,_xlpm.ns+_xlpm.wd+_xlpm.sb+_xlpm.ap,IF(AND(_xlpm.ac>0,_xlpm.inPlay=0,_xlpm.aDn=_xlpm.ac),"LIVE DLR",IF(AND(_xlpm.aRS>0,_xlpm.aDn<_xlpm.aRS),"Training",IF(_xlpm.aRS>0,"Active",IF(AND(_xlpm.dc>0,_xlpm.inPlay+_xlpm.ac=0),"Dead",IF(OR($CA35="Yes",$CA35=TRUE),"Rate Sheet",IF(AND($AJ35<>"",$AK35=FALSE),"Waiting on Dealer",IF(_xlpm.sb>0,"Waiting on Lender",IF(AND(_xlpm.ap+_xlpm.ac>0,_xlpm.ns+_xlpm.wd=0),"Rate Sheet","Application Submitted")))))))))) -> Waiting on Dealer | M35: 46268 | N35: 46280 | O35: SF, SL, FF, CH | P35: =IF($A35="","",IF($AK35=TRUE,"Ready 2 Submit","Waiting on Dealer")) -> Waiting on Dealer | Q35: =IF(OR(Q35="",Q35=0),IF($P35="Submitted",TODAY(),""),Q35) | R35: No | S35: No | T35: =IF($A35="","",IF($AK35=TRUE,"Ready 2 Submit","Waiting on Dealer")) -> Waiting on Dealer | U35: =IF(OR(U35="",U35=0),IF($T35="Submitted",TODAY(),""),U35) | V35: No | W35: No | X35: =IF($A35="","",IF($AK35=TRUE,"Ready 2 Submit","Waiting on Dealer")) -> Waiting on Dealer | Y35: =IF(OR(Y35="",Y35=0),IF($X35="Submitted",TODAY(),""),Y35) | Z35: No | AA35: No | AB35: =IF($A35="","",IF($AK35=TRUE,"Ready 2 Submit","Waiting on Dealer")) -> Waiting on Dealer | AC35: =IF(OR(AC35="",AC35=0),IF($AB35="Submitted",TODAY(),""),AC35) | AD35: No | AE35: No | AF35: N/A | AG35: =IF(OR(AG35="",AG35=0),IF($AF35="Submitted",TODAY(),""),AG35) | AH35: No | AI35: No | AJ35: Voided Check and Bank Statements | AK35: FALSE | AL35: {=IF($A35="","",SUMPRODUCT((CHOOSE({1,2,3,4,5},$R35,$V35,$Z35,$AD35,$AH35)="Yes")*(((CHOOSE({1,2,3,4,5},$S35,$W35,$AA35,$AE35,$AI35)="Yes")+(CHOOSE({1,2,3,4,5},$S35,$W35,$AA35,$AE35,$AI35)=TRUE))>0)))} -> 0 | AM35: 46287 | AN35: =IF(OR($A35="",$AM35=""),"",TODAY()-$AM35) -> 1 | BA35: 31 | BZ35: Unassigned | CA35: No | CB35: =IF($A35="","",_xlfn.LET(_xlpm.sfp,AND($P35<>"",$P35<>"N/A",$P35<>"No Min RQ"),_xlpm.slp,AND($T35<>"",$T35<>"N/A",$T35<>"No Min RQ"),_xlpm.ffp,AND($X35<>"",$X35<>"N/A",$X35<>"No Min RQ"),_xlpm.chp,AND($AB35<>"",$AB35<>"N/A",$AB35<>"No Min RQ"),_xlpm.usp,AND($AF35<>"",$AF35<>"N/A",$AF35<>"No Min RQ"),_xlpm.n,_xlpm.sfp+_xlpm.slp+_xlpm.ffp+_xlpm.chp+_xlpm.usp,_xlpm.sub,(_xlpm.sfp*($P35="Submitted"))+(_xlpm.slp*($T35="Submitted"))+(_xlpm.ffp*($X35="Submitted"))+(_xlpm.chp*($AB35="Submitted"))+(_xlpm.usp*($AF35="Submitted")),_xlpm.term,(_xlpm.sfp*OR($P35="Approved",$P35="Declined"))+(_xlpm.slp*OR($T35="Approved",$T35="Declined"))+(_xlpm.ffp*OR($X35="Approved",$X35="Declined"))+(_xlpm.chp*OR($AB35="Approved",$AB35="Declined"))+(_xlpm.usp*OR($AF35="Approved",$AF35="Declined")),IF(_xlpm.n=0,"No applicable lenders",IF(_xlpm.sub>0,"Stays with Shaw - lender still Submitted",IF(_xlpm.term=_xlpm.n,"Clear - all applicable lenders Approved or Declined","Stays with Shaw - not all lenders Approved or Declined")))))
A36: R3VIVE LLC | B36: R3VIVE LLC | D36: Gage Weaver | E36: 8016953085 | F36: info@getr3vive.com | G36: Scott Coombs | H36: scottbcoombs@gmail.com | I36: Roofing | K36: 3 | L36: =IF($A36="","",_xlfn.LET(_xlpm.ns,(--($P36="Ready 2 Submit"))+(--($T36="Ready 2 Submit"))+(--($X36="Ready 2 Submit"))+(--($AB36="Ready 2 Submit"))+(--($AF36="Ready 2 Submit")),_xlpm.wd,(--($P36="Waiting on Dealer"))+(--($T36="Waiting on Dealer"))+(--($X36="Waiting on Dealer"))+(--($AB36="Waiting on Dealer"))+(--($AF36="Waiting on Dealer")),_xlpm.sb,(--($P36="Submitted"))+(--($T36="Submitted"))+(--($X36="Submitted"))+(--($AB36="Submitted"))+(--($AF36="Submitted")),_xlpm.ap,(--($P36="Approved"))+(--($T36="Approved"))+(--($X36="Approved"))+(--($AB36="Approved"))+(--($AF36="Approved")),_xlpm.ac,(--($P36="Active"))+(--($T36="Active"))+(--($X36="Active"))+(--($AB36="Active"))+(--($AF36="Active")),_xlpm.dc,(--($P36="Declined"))+(--($T36="Declined"))+(--($X36="Declined"))+(--($AB36="Declined"))+(--($AF36="Declined")),_xlpm.aRS,(--($P36="Active"))*(--($R36="Yes"))+(--($T36="Active"))*(--($V36="Yes"))+(--($X36="Active"))*(--($Z36="Yes"))+(--($AB36="Active"))*(--($AD36="Yes"))+(--($AF36="Active"))*(--($AH36="Yes")),_xlpm.aDn,(--($P36="Active"))*(--($R36="Yes"))*(--((($S36="Yes")+($S36=TRUE))>0))+(--($T36="Active"))*(--($V36="Yes"))*(--((($W36="Yes")+($W36=TRUE))>0))+(--($X36="Active"))*(--($Z36="Yes"))*(--((($AA36="Yes")+($AA36=TRUE))>0))+(--($AB36="Active"))*(--($AD36="Yes"))*(--((($AE36="Yes")+($AE36=TRUE))>0))+(--($AF36="Active"))*(--($AH36="Yes"))*(--((($AI36="Yes")+($AI36=TRUE))>0)),_xlpm.inPlay,_xlpm.ns+_xlpm.wd+_xlpm.sb+_xlpm.ap,IF(AND(_xlpm.ac>0,_xlpm.inPlay=0,_xlpm.aDn=_xlpm.ac),"LIVE DLR",IF(AND(_xlpm.aRS>0,_xlpm.aDn<_xlpm.aRS),"Training",IF(_xlpm.aRS>0,"Active",IF(AND(_xlpm.dc>0,_xlpm.inPlay+_xlpm.ac=0),"Dead",IF(OR($CA36="Yes",$CA36=TRUE),"Rate Sheet",IF(AND($AJ36<>"",$AK36=FALSE),"Waiting on Dealer",IF(_xlpm.sb>0,"Waiting on Lender",IF(AND(_xlpm.ap+_xlpm.ac>0,_xlpm.ns+_xlpm.wd=0),"Rate Sheet","Application Submitted")))))))))) -> Waiting on Lender | M36: 46272 | N36: 46280 | O36: SF, FF | P36: Submitted | Q36: 46274 | R36: No | S36: No | T36: No Min RQ | U36: =IF(OR(U36="",U36=0),IF($T36="Submitted",TODAY(),""),U36) | V36: No | W36: No | X36: Approved | Y36: 46273 | Z36: No | AA36: No | AB36: N/A | AC36: =IF(OR(AC36="",AC36=0),IF($AB36="Submitted",TODAY(),""),AC36) | AD36: No | AE36: No | AF36: N/A | AG36: =IF(OR(AG36="",AG36=0),IF($AF36="Submitted",TODAY(),""),AG36) | AH36: No | AI36: No | AJ36: Need a service contract | AK36: TRUE | AL36: {=IF($A36="","",SUMPRODUCT((CHOOSE({1,2,3,4,5},$R36,$V36,$Z36,$AD36,$AH36)="Yes")*(((CHOOSE({1,2,3,4,5},$S36,$W36,$AA36,$AE36,$AI36)="Yes")+(CHOOSE({1,2,3,4,5},$S36,$W36,$AA36,$AE36,$AI36)=TRUE))>0)))} -> 0 | AN36: =IF(OR($A36="",$AM36=""),"",TODAY()-$AM36) | AT36: 36556000 | BA36: 32 | BZ36: Unassigned | CA36: No | CB36: =IF($A36="","",_xlfn.LET(_xlpm.sfp,AND($P36<>"",$P36<>"N/A",$P36<>"No Min RQ"),_xlpm.slp,AND($T36<>"",$T36<>"N/A",$T36<>"No Min RQ"),_xlpm.ffp,AND($X36<>"",$X36<>"N/A",$X36<>"No Min RQ"),_xlpm.chp,AND($AB36<>"",$AB36<>"N/A",$AB36<>"No Min RQ"),_xlpm.usp,AND($AF36<>"",$AF36<>"N/A",$AF36<>"No Min RQ"),_xlpm.n,_xlpm.sfp+_xlpm.slp+_xlpm.ffp+_xlpm.chp+_xlpm.usp,_xlpm.sub,(_xlpm.sfp*($P36="Submitted"))+(_xlpm.slp*($T36="Submitted"))+(_xlpm.ffp*($X36="Submitted"))+(_xlpm.chp*($AB36="Submitted"))+(_xlpm.usp*($AF36="Submitted")),_xlpm.term,(_xlpm.sfp*OR($P36="Approved",$P36="Declined"))+(_xlpm.slp*OR($T36="Approved",$T36="Declined"))+(_xlpm.ffp*OR($X36="Approved",$X36="Declined"))+(_xlpm.chp*OR($AB36="Approved",$AB36="Declined"))+(_xlpm.usp*OR($AF36="Approved",$AF36="Declined")),IF(_xlpm.n=0,"No applicable lenders",IF(_xlpm.sub>0,"Stays with Shaw - lender still Submitted",IF(_xlpm.term=_xlpm.n,"Clear - all applicable lenders Approved or Declined","Stays with Shaw - not all lenders Approved or Declined")))))
A37: Golden Nail Roofing LLC | B37: Golden Nail Roofing LLC | C37: Sales Rabbit | D37: Christian Rodriguez | E37: 972-821-7429 | F37: goldennailroofingllc@gmail.com | G37: sales Rabbit | H37: sales rabbit | I37: Roofing | J37: OK, TX | K37: 1 | L37: =IF($A37="","",_xlfn.LET(_xlpm.ns,(--($P37="Ready 2 Submit"))+(--($T37="Ready 2 Submit"))+(--($X37="Ready 2 Submit"))+(--($AB37="Ready 2 Submit"))+(--($AF37="Ready 2 Submit")),_xlpm.wd,(--($P37="Waiting on Dealer"))+(--($T37="Waiting on Dealer"))+(--($X37="Waiting on Dealer"))+(--($AB37="Waiting on Dealer"))+(--($AF37="Waiting on Dealer")),_xlpm.sb,(--($P37="Submitted"))+(--($T37="Submitted"))+(--($X37="Submitted"))+(--($AB37="Submitted"))+(--($AF37="Submitted")),_xlpm.ap,(--($P37="Approved"))+(--($T37="Approved"))+(--($X37="Approved"))+(--($AB37="Approved"))+(--($AF37="Approved")),_xlpm.ac,(--($P37="Active"))+(--($T37="Active"))+(--($X37="Active"))+(--($AB37="Active"))+(--($AF37="Active")),_xlpm.dc,(--($P37="Declined"))+(--($T37="Declined"))+(--($X37="Declined"))+(--($AB37="Declined"))+(--($AF37="Declined")),_xlpm.aRS,(--($P37="Active"))*(--($R37="Yes"))+(--($T37="Active"))*(--($V37="Yes"))+(--($X37="Active"))*(--($Z37="Yes"))+(--($AB37="Active"))*(--($AD37="Yes"))+(--($AF37="Active"))*(--($AH37="Yes")),_xlpm.aDn,(--($P37="Active"))*(--($R37="Yes"))*(--((($S37="Yes")+($S37=TRUE))>0))+(--($T37="Active"))*(--($V37="Yes"))*(--((($W37="Yes")+($W37=TRUE))>0))+(--($X37="Active"))*(--($Z37="Yes"))*(--((($AA37="Yes")+($AA37=TRUE))>0))+(--($AB37="Active"))*(--($AD37="Yes"))*(--((($AE37="Yes")+($AE37=TRUE))>0))+(--($AF37="Active"))*(--($AH37="Yes"))*(--((($AI37="Yes")+($AI37=TRUE))>0)),_xlpm.inPlay,_xlpm.ns+_xlpm.wd+_xlpm.sb+_xlpm.ap,IF(AND(_xlpm.ac>0,_xlpm.inPlay=0,_xlpm.aDn=_xlpm.ac),"LIVE DLR",IF(AND(_xlpm.aRS>0,_xlpm.aDn<_xlpm.aRS),"Training",IF(_xlpm.aRS>0,"Active",IF(AND(_xlpm.dc>0,_xlpm.inPlay+_xlpm.ac=0),"Dead",IF(OR($CA37="Yes",$CA37=TRUE),"Rate Sheet",IF(AND($AJ37<>"",$AK37=FALSE),"Waiting on Dealer",IF(_xlpm.sb>0,"Waiting on Lender",IF(AND(_xlpm.ap+_xlpm.ac>0,_xlpm.ns+_xlpm.wd=0),"Rate Sheet","Application Submitted")))))))))) -> Waiting on Dealer | M37: 46274 | N37: 46280 | O37: SF, SL, FF | P37: =IF($A37="","",IF($AK37=TRUE,"Ready 2 Submit","Waiting on Dealer")) -> Waiting on Dealer | Q37: =IF(OR(Q37="",Q37=0),IF($P37="Submitted",TODAY(),""),Q37) | R37: No | S37: No | T37: =IF($A37="","",IF($AK37=TRUE,"Ready 2 Submit","Waiting on Dealer")) -> Waiting on Dealer | U37: =IF(OR(U37="",U37=0),IF($T37="Submitted",TODAY(),""),U37) | V37: No | W37: No | X37: =IF($A37="","",IF($AK37=TRUE,"Ready 2 Submit","Waiting on Dealer")) -> Waiting on Dealer | Y37: =IF(OR(Y37="",Y37=0),IF($X37="Submitted",TODAY(),""),Y37) | Z37: No | AA37: No | AB37: N/A | AC37: =IF(OR(AC37="",AC37=0),IF($AB37="Submitted",TODAY(),""),AC37) | AD37: No | AE37: No | AF37: N/A | AG37: =IF(OR(AG37="",AG37=0),IF($AF37="Submitted",TODAY(),""),AG37) | AH37: No | AI37: No | AJ37: Finish Application | Agreements | AK37: FALSE | AL37: {=IF($A37="","",SUMPRODUCT((CHOOSE({1,2,3,4,5},$R37,$V37,$Z37,$AD37,$AH37)="Yes")*(((CHOOSE({1,2,3,4,5},$S37,$W37,$AA37,$AE37,$AI37)="Yes")+(CHOOSE({1,2,3,4,5},$S37,$W37,$AA37,$AE37,$AI37)=TRUE))>0)))} -> 0 | AM37: 46287 | AN37: =IF(OR($A37="",$AM37=""),"",TODAY()-$AM37) -> 1 | BA37: 33 | BZ37: Unassigned | CA37: No | CB37: =IF($A37="","",_xlfn.LET(_xlpm.sfp,AND($P37<>"",$P37<>"N/A",$P37<>"No Min RQ"),_xlpm.slp,AND($T37<>"",$T37<>"N/A",$T37<>"No Min RQ"),_xlpm.ffp,AND($X37<>"",$X37<>"N/A",$X37<>"No Min RQ"),_xlpm.chp,AND($AB37<>"",$AB37<>"N/A",$AB37<>"No Min RQ"),_xlpm.usp,AND($AF37<>"",$AF37<>"N/A",$AF37<>"No Min RQ"),_xlpm.n,_xlpm.sfp+_xlpm.slp+_xlpm.ffp+_xlpm.chp+_xlpm.usp,_xlpm.sub,(_xlpm.sfp*($P37="Submitted"))+(_xlpm.slp*($T37="Submitted"))+(_xlpm.ffp*($X37="Submitted"))+(_xlpm.chp*($AB37="Submitted"))+(_xlpm.usp*($AF37="Submitted")),_xlpm.term,(_xlpm.sfp*OR($P37="Approved",$P37="Declined"))+(_xlpm.slp*OR($T37="Approved",$T37="Declined"))+(_xlpm.ffp*OR($X37="Approved",$X37="Declined"))+(_xlpm.chp*OR($AB37="Approved",$AB37="Declined"))+(_xlpm.usp*OR($AF37="Approved",$AF37="Declined")),IF(_xlpm.n=0,"No applicable lenders",IF(_xlpm.sub>0,"Stays with Shaw - lender still Submitted",IF(_xlpm.term=_xlpm.n,"Clear - all applicable lenders Approved or Declined","Stays with Shaw - not all lenders Approved or Declined")))))
A38: Goodco Soulutions LLC | B38: Goodco Soulutions LLC | D38: Daniel Reed | E38: 808-234-9569 | F38: djr.aloha@gmail.com | G38: Doug Yates | H38: doug.yates@getfinti.com | I38: solar panel removal & reinstallation | K38: 2 | L38: =IF($A38="","",_xlfn.LET(_xlpm.ns,(--($P38="Ready 2 Submit"))+(--($T38="Ready 2 Submit"))+(--($X38="Ready 2 Submit"))+(--($AB38="Ready 2 Submit"))+(--($AF38="Ready 2 Submit")),_xlpm.wd,(--($P38="Waiting on Dealer"))+(--($T38="Waiting on Dealer"))+(--($X38="Waiting on Dealer"))+(--($AB38="Waiting on Dealer"))+(--($AF38="Waiting on Dealer")),_xlpm.sb,(--($P38="Submitted"))+(--($T38="Submitted"))+(--($X38="Submitted"))+(--($AB38="Submitted"))+(--($AF38="Submitted")),_xlpm.ap,(--($P38="Approved"))+(--($T38="Approved"))+(--($X38="Approved"))+(--($AB38="Approved"))+(--($AF38="Approved")),_xlpm.ac,(--($P38="Active"))+(--($T38="Active"))+(--($X38="Active"))+(--($AB38="Active"))+(--($AF38="Active")),_xlpm.dc,(--($P38="Declined"))+(--($T38="Declined"))+(--($X38="Declined"))+(--($AB38="Declined"))+(--($AF38="Declined")),_xlpm.aRS,(--($P38="Active"))*(--($R38="Yes"))+(--($T38="Active"))*(--($V38="Yes"))+(--($X38="Active"))*(--($Z38="Yes"))+(--($AB38="Active"))*(--($AD38="Yes"))+(--($AF38="Active"))*(--($AH38="Yes")),_xlpm.aDn,(--($P38="Active"))*(--($R38="Yes"))*(--((($S38="Yes")+($S38=TRUE))>0))+(--($T38="Active"))*(--($V38="Yes"))*(--((($W38="Yes")+($W38=TRUE))>0))+(--($X38="Active"))*(--($Z38="Yes"))*(--((($AA38="Yes")+($AA38=TRUE))>0))+(--($AB38="Active"))*(--($AD38="Yes"))*(--((($AE38="Yes")+($AE38=TRUE))>0))+(--($AF38="Active"))*(--($AH38="Yes"))*(--((($AI38="Yes")+($AI38=TRUE))>0)),_xlpm.inPlay,_xlpm.ns+_xlpm.wd+_xlpm.sb+_xlpm.ap,IF(AND(_xlpm.ac>0,_xlpm.inPlay=0,_xlpm.aDn=_xlpm.ac),"LIVE DLR",IF(AND(_xlpm.aRS>0,_xlpm.aDn<_xlpm.aRS),"Training",IF(_xlpm.aRS>0,"Active",IF(AND(_xlpm.dc>0,_xlpm.inPlay+_xlpm.ac=0),"Dead",IF(OR($CA38="Yes",$CA38=TRUE),"Rate Sheet",IF(AND($AJ38<>"",$AK38=FALSE),"Waiting on Dealer",IF(_xlpm.sb>0,"Waiting on Lender",IF(AND(_xlpm.ap+_xlpm.ac>0,_xlpm.ns+_xlpm.wd=0),"Rate Sheet","Application Submitted")))))))))) -> Waiting on Dealer | M38: 46274 | N38: 46280 | O38: SF, SL, FF | P38: =IF($A38="","",IF($AK38=TRUE,"Ready 2 Submit","Waiting on Dealer")) -> Waiting on Dealer | Q38: =IF(OR(Q38="",Q38=0),IF($P38="Submitted",TODAY(),""),Q38) | R38: No | S38: No | T38: =IF($A38="","",IF($AK38=TRUE,"Ready 2 Submit","Waiting on Dealer")) -> Waiting on Dealer | U38: =IF(OR(U38="",U38=0),IF($T38="Submitted",TODAY(),""),U38) | V38: No | W38: No | X38: =IF($A38="","",IF($AK38=TRUE,"Ready 2 Submit","Waiting on Dealer")) -> Waiting on Dealer | Y38: =IF(OR(Y38="",Y38=0),IF($X38="Submitted",TODAY(),""),Y38) | Z38: No | AA38: No | AB38: N/A | AC38: =IF(OR(AC38="",AC38=0),IF($AB38="Submitted",TODAY(),""),AC38) | AD38: No | AE38: No | AF38: N/A | AG38: =IF(OR(AG38="",AG38=0),IF($AF38="Submitted",TODAY(),""),AG38) | AH38: No | AI38: No | AJ38: Merchant needs to update website to include roofing and remove solar, then let us know when it's complete | AK38: FALSE | AL38: {=IF($A38="","",SUMPRODUCT((CHOOSE({1,2,3,4,5},$R38,$V38,$Z38,$AD38,$AH38)="Yes")*(((CHOOSE({1,2,3,4,5},$S38,$W38,$AA38,$AE38,$AI38)="Yes")+(CHOOSE({1,2,3,4,5},$S38,$W38,$AA38,$AE38,$AI38)=TRUE))>0)))} -> 0 | AM38: 46287 | AN38: =IF(OR($A38="",$AM38=""),"",TODAY()-$AM38) -> 1 | BA38: 34 | BZ38: Unassigned | CA38: No | CB38: =IF($A38="","",_xlfn.LET(_xlpm.sfp,AND($P38<>"",$P38<>"N/A",$P38<>"No Min RQ"),_xlpm.slp,AND($T38<>"",$T38<>"N/A",$T38<>"No Min RQ"),_xlpm.ffp,AND($X38<>"",$X38<>"N/A",$X38<>"No Min RQ"),_xlpm.chp,AND($AB38<>"",$AB38<>"N/A",$AB38<>"No Min RQ"),_xlpm.usp,AND($AF38<>"",$AF38<>"N/A",$AF38<>"No Min RQ"),_xlpm.n,_xlpm.sfp+_xlpm.slp+_xlpm.ffp+_xlpm.chp+_xlpm.usp,_xlpm.sub,(_xlpm.sfp*($P38="Submitted"))+(_xlpm.slp*($T38="Submitted"))+(_xlpm.ffp*($X38="Submitted"))+(_xlpm.chp*($AB38="Submitted"))+(_xlpm.usp*($AF38="Submitted")),_xlpm.term,(_xlpm.sfp*OR($P38="Approved",$P38="Declined"))+(_xlpm.slp*OR($T38="Approved",$T38="Declined"))+(_xlpm.ffp*OR($X38="Approved",$X38="Declined"))+(_xlpm.chp*OR($AB38="Approved",$AB38="Declined"))+(_xlpm.usp*OR($AF38="Approved",$AF38="Declined")),IF(_xlpm.n=0,"No applicable lenders",IF(_xlpm.sub>0,"Stays with Shaw - lender still Submitted",IF(_xlpm.term=_xlpm.n,"Clear - all applicable lenders Approved or Declined","Stays with Shaw - not all lenders Approved or Declined")))))
A39: Landscaping experts llc | B39: Landscaping experts llc | D39: Lesli Castro | E39: 312-804-4323 | F39: landscapingexpertsllc.boss@gmail.com | G39: Scott Coombs | H39: scottbcoombs@gmail.com | I39: Home Improvment, Landscaping | J39: UT | K39: 1 | L39: =IF($A39="","",_xlfn.LET(_xlpm.ns,(--($P39="Ready 2 Submit"))+(--($T39="Ready 2 Submit"))+(--($X39="Ready 2 Submit"))+(--($AB39="Ready 2 Submit"))+(--($AF39="Ready 2 Submit")),_xlpm.wd,(--($P39="Waiting on Dealer"))+(--($T39="Waiting on Dealer"))+(--($X39="Waiting on Dealer"))+(--($AB39="Waiting on Dealer"))+(--($AF39="Waiting on Dealer")),_xlpm.sb,(--($P39="Submitted"))+(--($T39="Submitted"))+(--($X39="Submitted"))+(--($AB39="Submitted"))+(--($AF39="Submitted")),_xlpm.ap,(--($P39="Approved"))+(--($T39="Approved"))+(--($X39="Approved"))+(--($AB39="Approved"))+(--($AF39="Approved")),_xlpm.ac,(--($P39="Active"))+(--($T39="Active"))+(--($X39="Active"))+(--($AB39="Active"))+(--($AF39="Active")),_xlpm.dc,(--($P39="Declined"))+(--($T39="Declined"))+(--($X39="Declined"))+(--($AB39="Declined"))+(--($AF39="Declined")),_xlpm.aRS,(--($P39="Active"))*(--($R39="Yes"))+(--($T39="Active"))*(--($V39="Yes"))+(--($X39="Active"))*(--($Z39="Yes"))+(--($AB39="Active"))*(--($AD39="Yes"))+(--($AF39="Active"))*(--($AH39="Yes")),_xlpm.aDn,(--($P39="Active"))*(--($R39="Yes"))*(--((($S39="Yes")+($S39=TRUE))>0))+(--($T39="Active"))*(--($V39="Yes"))*(--((($W39="Yes")+($W39=TRUE))>0))+(--($X39="Active"))*(--($Z39="Yes"))*(--((($AA39="Yes")+($AA39=TRUE))>0))+(--($AB39="Active"))*(--($AD39="Yes"))*(--((($AE39="Yes")+($AE39=TRUE))>0))+(--($AF39="Active"))*(--($AH39="Yes"))*(--((($AI39="Yes")+($AI39=TRUE))>0)),_xlpm.inPlay,_xlpm.ns+_xlpm.wd+_xlpm.sb+_xlpm.ap,IF(AND(_xlpm.ac>0,_xlpm.inPlay=0,_xlpm.aDn=_xlpm.ac),"LIVE DLR",IF(AND(_xlpm.aRS>0,_xlpm.aDn<_xlpm.aRS),"Training",IF(_xlpm.aRS>0,"Active",IF(AND(_xlpm.dc>0,_xlpm.inPlay+_xlpm.ac=0),"Dead",IF(OR($CA39="Yes",$CA39=TRUE),"Rate Sheet",IF(AND($AJ39<>"",$AK39=FALSE),"Waiting on Dealer",IF(_xlpm.sb>0,"Waiting on Lender",IF(AND(_xlpm.ap+_xlpm.ac>0,_xlpm.ns+_xlpm.wd=0),"Rate Sheet","Application Submitted")))))))))) -> Waiting on Dealer | M39: 46274 | N39: 46280 | O39: SF, SL, FF | P39: =IF($A39="","",IF($AK39=TRUE,"Ready 2 Submit","Waiting on Dealer")) -> Waiting on Dealer | Q39: =IF(OR(Q39="",Q39=0),IF($P39="Submitted",TODAY(),""),Q39) | R39: No | S39: No | T39: =IF($A39="","",IF($AK39=TRUE,"Ready 2 Submit","Waiting on Dealer")) -> Waiting on Dealer | U39: =IF(OR(U39="",U39=0),IF($T39="Submitted",TODAY(),""),U39) | V39: No | W39: No | X39: =IF($A39="","",IF($AK39=TRUE,"Ready 2 Submit","Waiting on Dealer")) -> Waiting on Dealer | Y39: =IF(OR(Y39="",Y39=0),IF($X39="Submitted",TODAY(),""),Y39) | Z39: No | AA39: No | AB39: N/A | AC39: =IF(OR(AC39="",AC39=0),IF($AB39="Submitted",TODAY(),""),AC39) | AD39: No | AE39: No | AF39: N/A | AG39: =IF(OR(AG39="",AG39=0),IF($AF39="Submitted",TODAY(),""),AG39) | AH39: No | AI39: No | AJ39: upload all docs | Agreements | AK39: FALSE | AL39: {=IF($A39="","",SUMPRODUCT((CHOOSE({1,2,3,4,5},$R39,$V39,$Z39,$AD39,$AH39)="Yes")*(((CHOOSE({1,2,3,4,5},$S39,$W39,$AA39,$AE39,$AI39)="Yes")+(CHOOSE({1,2,3,4,5},$S39,$W39,$AA39,$AE39,$AI39)=TRUE))>0)))} -> 0 | AM39: 46287 | AN39: =IF(OR($A39="",$AM39=""),"",TODAY()-$AM39) -> 1 | BA39: 35 | BZ39: Unassigned | CA39: No | CB39: =IF($A39="","",_xlfn.LET(_xlpm.sfp,AND($P39<>"",$P39<>"N/A",$P39<>"No Min RQ"),_xlpm.slp,AND($T39<>"",$T39<>"N/A",$T39<>"No Min RQ"),_xlpm.ffp,AND($X39<>"",$X39<>"N/A",$X39<>"No Min RQ"),_xlpm.chp,AND($AB39<>"",$AB39<>"N/A",$AB39<>"No Min RQ"),_xlpm.usp,AND($AF39<>"",$AF39<>"N/A",$AF39<>"No Min RQ"),_xlpm.n,_xlpm.sfp+_xlpm.slp+_xlpm.ffp+_xlpm.chp+_xlpm.usp,_xlpm.sub,(_xlpm.sfp*($P39="Submitted"))+(_xlpm.slp*($T39="Submitted"))+(_xlpm.ffp*($X39="Submitted"))+(_xlpm.chp*($AB39="Submitted"))+(_xlpm.usp*($AF39="Submitted")),_xlpm.term,(_xlpm.sfp*OR($P39="Approved",$P39="Declined"))+(_xlpm.slp*OR($T39="Approved",$T39="Declined"))+(_xlpm.ffp*OR($X39="Approved",$X39="Declined"))+(_xlpm.chp*OR($AB39="Approved",$AB39="Declined"))+(_xlpm.usp*OR($AF39="Approved",$AF39="Declined")),IF(_xlpm.n=0,"No applicable lenders",IF(_xlpm.sub>0,"Stays with Shaw - lender still Submitted",IF(_xlpm.term=_xlpm.n,"Clear - all applicable lenders Approved or Declined","Stays with Shaw - not all lenders Approved or Declined")))))
A40: Elite roofing and remodeling | D40: Jared Davis | E40: 4808620353 | F40: eliterrjd@gmail.com | G40: Scott Coombs | H40: scottbcoombs@gmail.com | I40: roofing, Home improvment | J40: AZ | K40: 2 | L40: =IF($A40="","",_xlfn.LET(_xlpm.ns,(--($P40="Ready 2 Submit"))+(--($T40="Ready 2 Submit"))+(--($X40="Ready 2 Submit"))+(--($AB40="Ready 2 Submit"))+(--($AF40="Ready 2 Submit")),_xlpm.wd,(--($P40="Waiting on Dealer"))+(--($T40="Waiting on Dealer"))+(--($X40="Waiting on Dealer"))+(--($AB40="Waiting on Dealer"))+(--($AF40="Waiting on Dealer")),_xlpm.sb,(--($P40="Submitted"))+(--($T40="Submitted"))+(--($X40="Submitted"))+(--($AB40="Submitted"))+(--($AF40="Submitted")),_xlpm.ap,(--($P40="Approved"))+(--($T40="Approved"))+(--($X40="Approved"))+(--($AB40="Approved"))+(--($AF40="Approved")),_xlpm.ac,(--($P40="Active"))+(--($T40="Active"))+(--($X40="Active"))+(--($AB40="Active"))+(--($AF40="Active")),_xlpm.dc,(--($P40="Declined"))+(--($T40="Declined"))+(--($X40="Declined"))+(--($AB40="Declined"))+(--($AF40="Declined")),_xlpm.aRS,(--($P40="Active"))*(--($R40="Yes"))+(--($T40="Active"))*(--($V40="Yes"))+(--($X40="Active"))*(--($Z40="Yes"))+(--($AB40="Active"))*(--($AD40="Yes"))+(--($AF40="Active"))*(--($AH40="Yes")),_xlpm.aDn,(--($P40="Active"))*(--($R40="Yes"))*(--((($S40="Yes")+($S40=TRUE))>0))+(--($T40="Active"))*(--($V40="Yes"))*(--((($W40="Yes")+($W40=TRUE))>0))+(--($X40="Active"))*(--($Z40="Yes"))*(--((($AA40="Yes")+($AA40=TRUE))>0))+(--($AB40="Active"))*(--($AD40="Yes"))*(--((($AE40="Yes")+($AE40=TRUE))>0))+(--($AF40="Active"))*(--($AH40="Yes"))*(--((($AI40="Yes")+($AI40=TRUE))>0)),_xlpm.inPlay,_xlpm.ns+_xlpm.wd+_xlpm.sb+_xlpm.ap,IF(AND(_xlpm.ac>0,_xlpm.inPlay=0,_xlpm.aDn=_xlpm.ac),"LIVE DLR",IF(AND(_xlpm.aRS>0,_xlpm.aDn<_xlpm.aRS),"Training",IF(_xlpm.aRS>0,"Active",IF(AND(_xlpm.dc>0,_xlpm.inPlay+_xlpm.ac=0),"Dead",IF(OR($CA40="Yes",$CA40=TRUE),"Rate Sheet",IF(AND($AJ40<>"",$AK40=FALSE),"Waiting on Dealer",IF(_xlpm.sb>0,"Waiting on Lender",IF(AND(_xlpm.ap+_xlpm.ac>0,_xlpm.ns+_xlpm.wd=0),"Rate Sheet","Application Submitted")))))))))) -> Waiting on Lender | M40: 46276 | N40: 46280 | O40: SF, SL, FF | P40: Submitted | Q40: =IF(OR(Q40="",Q40=0),IF($P40="Submitted",TODAY(),""),Q40) -> 46287 | R40: No | S40: No | T40: Submitted | U40: =IF(OR(U40="",U40=0),IF($T40="Submitted",TODAY(),""),U40) -> 46287 | V40: No | W40: No | X40: Submitted | Y40: =IF(OR(Y40="",Y40=0),IF($X40="Submitted",TODAY(),""),Y40) -> 46287 | Z40: No | AA40: No | AB40: N/A | AC40: =IF(OR(AC40="",AC40=0),IF($AB40="Submitted",TODAY(),""),AC40) | AD40: No | AE40: No | AF40: N/A | AG40: =IF(OR(AG40="",AG40=0),IF($AF40="Submitted",TODAY(),""),AG40) | AH40: No | AI40: No | AJ40: verify insurance for Sunlight | AK40: TRUE | AL40: {=IF($A40="","",SUMPRODUCT((CHOOSE({1,2,3,4,5},$R40,$V40,$Z40,$AD40,$AH40)="Yes")*(((CHOOSE({1,2,3,4,5},$S40,$W40,$AA40,$AE40,$AI40)="Yes")+(CHOOSE({1,2,3,4,5},$S40,$W40,$AA40,$AE40,$AI40)=TRUE))>0)))} -> 0 | AM40: 46287 | AN40: =IF(OR($A40="",$AM40=""),"",TODAY()-$AM40) -> 1 | BA40: 36 | BZ40: Unassigned | CA40: No | CB40: =IF($A40="","",_xlfn.LET(_xlpm.sfp,AND($P40<>"",$P40<>"N/A",$P40<>"No Min RQ"),_xlpm.slp,AND($T40<>"",$T40<>"N/A",$T40<>"No Min RQ"),_xlpm.ffp,AND($X40<>"",$X40<>"N/A",$X40<>"No Min RQ"),_xlpm.chp,AND($AB40<>"",$AB40<>"N/A",$AB40<>"No Min RQ"),_xlpm.usp,AND($AF40<>"",$AF40<>"N/A",$AF40<>"No Min RQ"),_xlpm.n,_xlpm.sfp+_xlpm.slp+_xlpm.ffp+_xlpm.chp+_xlpm.usp,_xlpm.sub,(_xlpm.sfp*($P40="Submitted"))+(_xlpm.slp*($T40="Submitted"))+(_xlpm.ffp*($X40="Submitted"))+(_xlpm.chp*($AB40="Submitted"))+(_xlpm.usp*($AF40="Submitted")),_xlpm.term,(_xlpm.sfp*OR($P40="Approved",$P40="Declined"))+(_xlpm.slp*OR($T40="Approved",$T40="Declined"))+(_xlpm.ffp*OR($X40="Approved",$X40="Declined"))+(_xlpm.chp*OR($AB40="Approved",$AB40="Declined"))+(_xlpm.usp*OR($AF40="Approved",$AF40="Declined")),IF(_xlpm.n=0,"No applicable lenders",IF(_xlpm.sub>0,"Stays with Shaw - lender still Submitted",IF(_xlpm.term=_xlpm.n,"Clear - all applicable lenders Approved or Declined","Stays with Shaw - not all lenders Approved or Declined")))))
A41: Everhome LLC | D41: Thomas Brady | E41: 9012198862 | F41: court@everhomepros.com | G41: Scott Coombs | H41: scottbcoombs@gmail.com | I41: ROOFING, HVAC | K41: 2 | L41: =IF($A41="","",_xlfn.LET(_xlpm.ns,(--($P41="Ready 2 Submit"))+(--($T41="Ready 2 Submit"))+(--($X41="Ready 2 Submit"))+(--($AB41="Ready 2 Submit"))+(--($AF41="Ready 2 Submit")),_xlpm.wd,(--($P41="Waiting on Dealer"))+(--($T41="Waiting on Dealer"))+(--($X41="Waiting on Dealer"))+(--($AB41="Waiting on Dealer"))+(--($AF41="Waiting on Dealer")),_xlpm.sb,(--($P41="Submitted"))+(--($T41="Submitted"))+(--($X41="Submitted"))+(--($AB41="Submitted"))+(--($AF41="Submitted")),_xlpm.ap,(--($P41="Approved"))+(--($T41="Approved"))+(--($X41="Approved"))+(--($AB41="Approved"))+(--($AF41="Approved")),_xlpm.ac,(--($P41="Active"))+(--($T41="Active"))+(--($X41="Active"))+(--($AB41="Active"))+(--($AF41="Active")),_xlpm.dc,(--($P41="Declined"))+(--($T41="Declined"))+(--($X41="Declined"))+(--($AB41="Declined"))+(--($AF41="Declined")),_xlpm.aRS,(--($P41="Active"))*(--($R41="Yes"))+(--($T41="Active"))*(--($V41="Yes"))+(--($X41="Active"))*(--($Z41="Yes"))+(--($AB41="Active"))*(--($AD41="Yes"))+(--($AF41="Active"))*(--($AH41="Yes")),_xlpm.aDn,(--($P41="Active"))*(--($R41="Yes"))*(--((($S41="Yes")+($S41=TRUE))>0))+(--($T41="Active"))*(--($V41="Yes"))*(--((($W41="Yes")+($W41=TRUE))>0))+(--($X41="Active"))*(--($Z41="Yes"))*(--((($AA41="Yes")+($AA41=TRUE))>0))+(--($AB41="Active"))*(--($AD41="Yes"))*(--((($AE41="Yes")+($AE41=TRUE))>0))+(--($AF41="Active"))*(--($AH41="Yes"))*(--((($AI41="Yes")+($AI41=TRUE))>0)),_xlpm.inPlay,_xlpm.ns+_xlpm.wd+_xlpm.sb+_xlpm.ap,IF(AND(_xlpm.ac>0,_xlpm.inPlay=0,_xlpm.aDn=_xlpm.ac),"LIVE DLR",IF(AND(_xlpm.aRS>0,_xlpm.aDn<_xlpm.aRS),"Training",IF(_xlpm.aRS>0,"Active",IF(AND(_xlpm.dc>0,_xlpm.inPlay+_xlpm.ac=0),"Dead",IF(OR($CA41="Yes",$CA41=TRUE),"Rate Sheet",IF(AND($AJ41<>"",$AK41=FALSE),"Waiting on Dealer",IF(_xlpm.sb>0,"Waiting on Lender",IF(AND(_xlpm.ap+_xlpm.ac>0,_xlpm.ns+_xlpm.wd=0),"Rate Sheet","Application Submitted")))))))))) -> Waiting on Dealer | M41: 46279 | N41: 46280 | O41: SF, SL, FF, CH | P41: =IF($A41="","",IF($AK41=TRUE,"Ready 2 Submit","Waiting on Dealer")) -> Waiting on Dealer | Q41: =IF(OR(Q41="",Q41=0),IF($P41="Submitted",TODAY(),""),Q41) | R41: No | S41: No | T41: =IF($A41="","",IF($AK41=TRUE,"Ready 2 Submit","Waiting on Dealer")) -> Waiting on Dealer | U41: =IF(OR(U41="",U41=0),IF($T41="Submitted",TODAY(),""),U41) | V41: No | W41: No | X41: =IF($A41="","",IF($AK41=TRUE,"Ready 2 Submit","Waiting on Dealer")) -> Waiting on Dealer | Y41: =IF(OR(Y41="",Y41=0),IF($X41="Submitted",TODAY(),""),Y41) | Z41: No | AA41: No | AB41: =IF($A41="","",IF($AK41=TRUE,"Ready 2 Submit","Waiting on Dealer")) -> Waiting on Dealer | AC41: =IF(OR(AC41="",AC41=0),IF($AB41="Submitted",TODAY(),""),AC41) | AD41: No | AE41: No | AF41: =IF($A41="","",IF($AK41=TRUE,"Ready 2 Submit","Waiting on Dealer")) -> Waiting on Dealer | AG41: =IF(OR(AG41="",AG41=0),IF($AF41="Submitted",TODAY(),""),AG41) | AH41: No | AI41: No | AJ41: All Docs Upload | Agreements | Finish Application | AK41: FALSE | AL41: {=IF($A41="","",SUMPRODUCT((CHOOSE({1,2,3,4,5},$R41,$V41,$Z41,$AD41,$AH41)="Yes")*(((CHOOSE({1,2,3,4,5},$S41,$W41,$AA41,$AE41,$AI41)="Yes")+(CHOOSE({1,2,3,4,5},$S41,$W41,$AA41,$AE41,$AI41)=TRUE))>0)))} -> 0 | AM41: 46287 | AN41: =IF(OR($A41="",$AM41=""),"",TODAY()-$AM41) -> 1 | BA41: 37 | BZ41: Unassigned | CA41: No | CB41: =IF($A41="","",_xlfn.LET(_xlpm.sfp,AND($P41<>"",$P41<>"N/A",$P41<>"No Min RQ"),_xlpm.slp,AND($T41<>"",$T41<>"N/A",$T41<>"No Min RQ"),_xlpm.ffp,AND($X41<>"",$X41<>"N/A",$X41<>"No Min RQ"),_xlpm.chp,AND($AB41<>"",$AB41<>"N/A",$AB41<>"No Min RQ"),_xlpm.usp,AND($AF41<>"",$AF41<>"N/A",$AF41<>"No Min RQ"),_xlpm.n,_xlpm.sfp+_xlpm.slp+_xlpm.ffp+_xlpm.chp+_xlpm.usp,_xlpm.sub,(_xlpm.sfp*($P41="Submitted"))+(_xlpm.slp*($T41="Submitted"))+(_xlpm.ffp*($X41="Submitted"))+(_xlpm.chp*($AB41="Submitted"))+(_xlpm.usp*($AF41="Submitted")),_xlpm.term,(_xlpm.sfp*OR($P41="Approved",$P41="Declined"))+(_xlpm.slp*OR($T41="Approved",$T41="Declined"))+(_xlpm.ffp*OR($X41="Approved",$X41="Declined"))+(_xlpm.chp*OR($AB41="Approved",$AB41="Declined"))+(_xlpm.usp*OR($AF41="Approved",$AF41="Declined")),IF(_xlpm.n=0,"No applicable lenders",IF(_xlpm.sub>0,"Stays with Shaw - lender still Submitted",IF(_xlpm.term=_xlpm.n,"Clear - all applicable lenders Approved or Declined","Stays with Shaw - not all lenders Approved or Declined")))))
A42: GH Cutting EDGE LLC | B42: GH Cutting EDGE LLC | D42: George Freeman | E42: 8632066995 | F42: ghcuttingedgellc@gmail.com | G42: Rob Garcia | H42: robsudden24@icloud.com | I42: Kitchen | K42: 3 | L42: =IF($A42="","",_xlfn.LET(_xlpm.ns,(--($P42="Ready 2 Submit"))+(--($T42="Ready 2 Submit"))+(--($X42="Ready 2 Submit"))+(--($AB42="Ready 2 Submit"))+(--($AF42="Ready 2 Submit")),_xlpm.wd,(--($P42="Waiting on Dealer"))+(--($T42="Waiting on Dealer"))+(--($X42="Waiting on Dealer"))+(--($AB42="Waiting on Dealer"))+(--($AF42="Waiting on Dealer")),_xlpm.sb,(--($P42="Submitted"))+(--($T42="Submitted"))+(--($X42="Submitted"))+(--($AB42="Submitted"))+(--($AF42="Submitted")),_xlpm.ap,(--($P42="Approved"))+(--($T42="Approved"))+(--($X42="Approved"))+(--($AB42="Approved"))+(--($AF42="Approved")),_xlpm.ac,(--($P42="Active"))+(--($T42="Active"))+(--($X42="Active"))+(--($AB42="Active"))+(--($AF42="Active")),_xlpm.dc,(--($P42="Declined"))+(--($T42="Declined"))+(--($X42="Declined"))+(--($AB42="Declined"))+(--($AF42="Declined")),_xlpm.aRS,(--($P42="Active"))*(--($R42="Yes"))+(--($T42="Active"))*(--($V42="Yes"))+(--($X42="Active"))*(--($Z42="Yes"))+(--($AB42="Active"))*(--($AD42="Yes"))+(--($AF42="Active"))*(--($AH42="Yes")),_xlpm.aDn,(--($P42="Active"))*(--($R42="Yes"))*(--((($S42="Yes")+($S42=TRUE))>0))+(--($T42="Active"))*(--($V42="Yes"))*(--((($W42="Yes")+($W42=TRUE))>0))+(--($X42="Active"))*(--($Z42="Yes"))*(--((($AA42="Yes")+($AA42=TRUE))>0))+(--($AB42="Active"))*(--($AD42="Yes"))*(--((($AE42="Yes")+($AE42=TRUE))>0))+(--($AF42="Active"))*(--($AH42="Yes"))*(--((($AI42="Yes")+($AI42=TRUE))>0)),_xlpm.inPlay,_xlpm.ns+_xlpm.wd+_xlpm.sb+_xlpm.ap,IF(AND(_xlpm.ac>0,_xlpm.inPlay=0,_xlpm.aDn=_xlpm.ac),"LIVE DLR",IF(AND(_xlpm.aRS>0,_xlpm.aDn<_xlpm.aRS),"Training",IF(_xlpm.aRS>0,"Active",IF(AND(_xlpm.dc>0,_xlpm.inPlay+_xlpm.ac=0),"Dead",IF(OR($CA42="Yes",$CA42=TRUE),"Rate Sheet",IF(AND($AJ42<>"",$AK42=FALSE),"Waiting on Dealer",IF(_xlpm.sb>0,"Waiting on Lender",IF(AND(_xlpm.ap+_xlpm.ac>0,_xlpm.ns+_xlpm.wd=0),"Rate Sheet","Application Submitted")))))))))) -> Waiting on Dealer | M42: 46279 | N42: 46280 | O42: FF | P42: N/A | Q42: =IF(OR(Q42="",Q42=0),IF($P42="Submitted",TODAY(),""),Q42) | R42: No | S42: No | T42: N/A | U42: =IF(OR(U42="",U42=0),IF($T42="Submitted",TODAY(),""),U42) | V42: No | W42: No | X42: =IF($A42="","",IF($AK42=TRUE,"Ready 2 Submit","Waiting on Dealer")) -> Waiting on Dealer | Y42: =IF(OR(Y42="",Y42=0),IF($X42="Submitted",TODAY(),""),Y42) | Z42: No | AA42: No | AB42: N/A | AC42: =IF(OR(AC42="",AC42=0),IF($AB42="Submitted",TODAY(),""),AC42) | AD42: No | AE42: No | AF42: N/A | AG42: =IF(OR(AG42="",AG42=0),IF($AF42="Submitted",TODAY(),""),AG42) | AH42: No | AI42: No | AJ42: ALL DOCS | agreements | AK42: FALSE | AL42: {=IF($A42="","",SUMPRODUCT((CHOOSE({1,2,3,4,5},$R42,$V42,$Z42,$AD42,$AH42)="Yes")*(((CHOOSE({1,2,3,4,5},$S42,$W42,$AA42,$AE42,$AI42)="Yes")+(CHOOSE({1,2,3,4,5},$S42,$W42,$AA42,$AE42,$AI42)=TRUE))>0)))} -> 0 | AM42: 46287 | AN42: =IF(OR($A42="",$AM42=""),"",TODAY()-$AM42) -> 1 | BA42: 38 | BZ42: Unassigned | CA42: No | CB42: =IF($A42="","",_xlfn.LET(_xlpm.sfp,AND($P42<>"",$P42<>"N/A",$P42<>"No Min RQ"),_xlpm.slp,AND($T42<>"",$T42<>"N/A",$T42<>"No Min RQ"),_xlpm.ffp,AND($X42<>"",$X42<>"N/A",$X42<>"No Min RQ"),_xlpm.chp,AND($AB42<>"",$AB42<>"N/A",$AB42<>"No Min RQ"),_xlpm.usp,AND($AF42<>"",$AF42<>"N/A",$AF42<>"No Min RQ"),_xlpm.n,_xlpm.sfp+_xlpm.slp+_xlpm.ffp+_xlpm.chp+_xlpm.usp,_xlpm.sub,(_xlpm.sfp*($P42="Submitted"))+(_xlpm.slp*($T42="Submitted"))+(_xlpm.ffp*($X42="Submitted"))+(_xlpm.chp*($AB42="Submitted"))+(_xlpm.usp*($AF42="Submitted")),_xlpm.term,(_xlpm.sfp*OR($P42="Approved",$P42="Declined"))+(_xlpm.slp*OR($T42="Approved",$T42="Declined"))+(_xlpm.ffp*OR($X42="Approved",$X42="Declined"))+(_xlpm.chp*OR($AB42="Approved",$AB42="Declined"))+(_xlpm.usp*OR($AF42="Approved",$AF42="Declined")),IF(_xlpm.n=0,"No applicable lenders",IF(_xlpm.sub>0,"Stays with Shaw - lender still Submitted",IF(_xlpm.term=_xlpm.n,"Clear - all applicable lenders Approved or Declined","Stays with Shaw - not all lenders Approved or Declined")))))
A43: Bolton Heating & Air | B43: Bolton Heating & Air | D43: Jo Bolton | E43: 214-909-7615 | F43: info@boltonac.com | G43: Payden Yates | H43: payden.yates@getfinti.com | I43: HVAC | K43: 1 | L43: =IF($A43="","",_xlfn.LET(_xlpm.ns,(--($P43="Ready 2 Submit"))+(--($T43="Ready 2 Submit"))+(--($X43="Ready 2 Submit"))+(--($AB43="Ready 2 Submit"))+(--($AF43="Ready 2 Submit")),_xlpm.wd,(--($P43="Waiting on Dealer"))+(--($T43="Waiting on Dealer"))+(--($X43="Waiting on Dealer"))+(--($AB43="Waiting on Dealer"))+(--($AF43="Waiting on Dealer")),_xlpm.sb,(--($P43="Submitted"))+(--($T43="Submitted"))+(--($X43="Submitted"))+(--($AB43="Submitted"))+(--($AF43="Submitted")),_xlpm.ap,(--($P43="Approved"))+(--($T43="Approved"))+(--($X43="Approved"))+(--($AB43="Approved"))+(--($AF43="Approved")),_xlpm.ac,(--($P43="Active"))+(--($T43="Active"))+(--($X43="Active"))+(--($AB43="Active"))+(--($AF43="Active")),_xlpm.dc,(--($P43="Declined"))+(--($T43="Declined"))+(--($X43="Declined"))+(--($AB43="Declined"))+(--($AF43="Declined")),_xlpm.aRS,(--($P43="Active"))*(--($R43="Yes"))+(--($T43="Active"))*(--($V43="Yes"))+(--($X43="Active"))*(--($Z43="Yes"))+(--($AB43="Active"))*(--($AD43="Yes"))+(--($AF43="Active"))*(--($AH43="Yes")),_xlpm.aDn,(--($P43="Active"))*(--($R43="Yes"))*(--((($S43="Yes")+($S43=TRUE))>0))+(--($T43="Active"))*(--($V43="Yes"))*(--((($W43="Yes")+($W43=TRUE))>0))+(--($X43="Active"))*(--($Z43="Yes"))*(--((($AA43="Yes")+($AA43=TRUE))>0))+(--($AB43="Active"))*(--($AD43="Yes"))*(--((($AE43="Yes")+($AE43=TRUE))>0))+(--($AF43="Active"))*(--($AH43="Yes"))*(--((($AI43="Yes")+($AI43=TRUE))>0)),_xlpm.inPlay,_xlpm.ns+_xlpm.wd+_xlpm.sb+_xlpm.ap,IF(AND(_xlpm.ac>0,_xlpm.inPlay=0,_xlpm.aDn=_xlpm.ac),"LIVE DLR",IF(AND(_xlpm.aRS>0,_xlpm.aDn<_xlpm.aRS),"Training",IF(_xlpm.aRS>0,"Active",IF(AND(_xlpm.dc>0,_xlpm.inPlay+_xlpm.ac=0),"Dead",IF(OR($CA43="Yes",$CA43=TRUE),"Rate Sheet",IF(AND($AJ43<>"",$AK43=FALSE),"Waiting on Dealer",IF(_xlpm.sb>0,"Waiting on Lender",IF(AND(_xlpm.ap+_xlpm.ac>0,_xlpm.ns+_xlpm.wd=0),"Rate Sheet","Application Submitted")))))))))) -> Waiting on Dealer | M43: 46279 | N43: 46280 | O43: SF, SL, FF, CH | P43: =IF($A43="","",IF($AK43=TRUE,"Ready 2 Submit","Waiting on Dealer")) -> Waiting on Dealer | Q43: =IF(OR(Q43="",Q43=0),IF($P43="Submitted",TODAY(),""),Q43) | R43: No | S43: No | T43: =IF($A43="","",IF($AK43=TRUE,"Ready 2 Submit","Waiting on Dealer")) -> Waiting on Dealer | U43: =IF(OR(U43="",U43=0),IF($T43="Submitted",TODAY(),""),U43) | V43: No | W43: No | X43: =IF($A43="","",IF($AK43=TRUE,"Ready 2 Submit","Waiting on Dealer")) -> Waiting on Dealer | Y43: =IF(OR(Y43="",Y43=0),IF($X43="Submitted",TODAY(),""),Y43) | Z43: No | AA43: No | AB43: =IF($A43="","",IF($AK43=TRUE,"Ready 2 Submit","Waiting on Dealer")) -> Waiting on Dealer | AC43: =IF(OR(AC43="",AC43=0),IF($AB43="Submitted",TODAY(),""),AC43) | AD43: No | AE43: No | AF43: N/A | AG43: =IF(OR(AG43="",AG43=0),IF($AF43="Submitted",TODAY(),""),AG43) | AH43: No | AI43: No | AJ43: Banking and all docs | AK43: FALSE | AL43: {=IF($A43="","",SUMPRODUCT((CHOOSE({1,2,3,4,5},$R43,$V43,$Z43,$AD43,$AH43)="Yes")*(((CHOOSE({1,2,3,4,5},$S43,$W43,$AA43,$AE43,$AI43)="Yes")+(CHOOSE({1,2,3,4,5},$S43,$W43,$AA43,$AE43,$AI43)=TRUE))>0)))} -> 0 | AM43: 46287 | AN43: =IF(OR($A43="",$AM43=""),"",TODAY()-$AM43) -> 1 | BA43: 39 | BZ43: Unassigned | CA43: No | CB43: =IF($A43="","",_xlfn.LET(_xlpm.sfp,AND($P43<>"",$P43<>"N/A",$P43<>"No Min RQ"),_xlpm.slp,AND($T43<>"",$T43<>"N/A",$T43<>"No Min RQ"),_xlpm.ffp,AND($X43<>"",$X43<>"N/A",$X43<>"No Min RQ"),_xlpm.chp,AND($AB43<>"",$AB43<>"N/A",$AB43<>"No Min RQ"),_xlpm.usp,AND($AF43<>"",$AF43<>"N/A",$AF43<>"No Min RQ"),_xlpm.n,_xlpm.sfp+_xlpm.slp+_xlpm.ffp+_xlpm.chp+_xlpm.usp,_xlpm.sub,(_xlpm.sfp*($P43="Submitted"))+(_xlpm.slp*($T43="Submitted"))+(_xlpm.ffp*($X43="Submitted"))+(_xlpm.chp*($AB43="Submitted"))+(_xlpm.usp*($AF43="Submitted")),_xlpm.term,(_xlpm.sfp*OR($P43="Approved",$P43="Declined"))+(_xlpm.slp*OR($T43="Approved",$T43="Declined"))+(_xlpm.ffp*OR($X43="Approved",$X43="Declined"))+(_xlpm.chp*OR($AB43="Approved",$AB43="Declined"))+(_xlpm.usp*OR($AF43="Approved",$AF43="Declined")),IF(_xlpm.n=0,"No applicable lenders",IF(_xlpm.sub>0,"Stays with Shaw - lender still Submitted",IF(_xlpm.term=_xlpm.n,"Clear - all applicable lenders Approved or Declined","Stays with Shaw - not all lenders Approved or Declined")))))
A44: AllSet Home LLC | B44: AllSet Home | D44: Christopher Lee | E44: 509-713-5507 | F44: info@allsethome.com | G44: Steve Stonebraker | H44: stonebraker@getfinti.com | I44: HVAC | K44: 1 | L44: =IF($A44="","",_xlfn.LET(_xlpm.ns,(--($P44="Ready 2 Submit"))+(--($T44="Ready 2 Submit"))+(--($X44="Ready 2 Submit"))+(--($AB44="Ready 2 Submit"))+(--($AF44="Ready 2 Submit")),_xlpm.wd,(--($P44="Waiting on Dealer"))+(--($T44="Waiting on Dealer"))+(--($X44="Waiting on Dealer"))+(--($AB44="Waiting on Dealer"))+(--($AF44="Waiting on Dealer")),_xlpm.sb,(--($P44="Submitted"))+(--($T44="Submitted"))+(--($X44="Submitted"))+(--($AB44="Submitted"))+(--($AF44="Submitted")),_xlpm.ap,(--($P44="Approved"))+(--($T44="Approved"))+(--($X44="Approved"))+(--($AB44="Approved"))+(--($AF44="Approved")),_xlpm.ac,(--($P44="Active"))+(--($T44="Active"))+(--($X44="Active"))+(--($AB44="Active"))+(--($AF44="Active")),_xlpm.dc,(--($P44="Declined"))+(--($T44="Declined"))+(--($X44="Declined"))+(--($AB44="Declined"))+(--($AF44="Declined")),_xlpm.aRS,(--($P44="Active"))*(--($R44="Yes"))+(--($T44="Active"))*(--($V44="Yes"))+(--($X44="Active"))*(--($Z44="Yes"))+(--($AB44="Active"))*(--($AD44="Yes"))+(--($AF44="Active"))*(--($AH44="Yes")),_xlpm.aDn,(--($P44="Active"))*(--($R44="Yes"))*(--((($S44="Yes")+($S44=TRUE))>0))+(--($T44="Active"))*(--($V44="Yes"))*(--((($W44="Yes")+($W44=TRUE))>0))+(--($X44="Active"))*(--($Z44="Yes"))*(--((($AA44="Yes")+($AA44=TRUE))>0))+(--($AB44="Active"))*(--($AD44="Yes"))*(--((($AE44="Yes")+($AE44=TRUE))>0))+(--($AF44="Active"))*(--($AH44="Yes"))*(--((($AI44="Yes")+($AI44=TRUE))>0)),_xlpm.inPlay,_xlpm.ns+_xlpm.wd+_xlpm.sb+_xlpm.ap,IF(AND(_xlpm.ac>0,_xlpm.inPlay=0,_xlpm.aDn=_xlpm.ac),"LIVE DLR",IF(AND(_xlpm.aRS>0,_xlpm.aDn<_xlpm.aRS),"Training",IF(_xlpm.aRS>0,"Active",IF(AND(_xlpm.dc>0,_xlpm.inPlay+_xlpm.ac=0),"Dead",IF(OR($CA44="Yes",$CA44=TRUE),"Rate Sheet",IF(AND($AJ44<>"",$AK44=FALSE),"Waiting on Dealer",IF(_xlpm.sb>0,"Waiting on Lender",IF(AND(_xlpm.ap+_xlpm.ac>0,_xlpm.ns+_xlpm.wd=0),"Rate Sheet","Application Submitted")))))))))) -> Waiting on Lender | M44: 46280 | N44: 46280 | O44: SF, FF, CH | P44: Submitted | Q44: 46281 | R44: No | S44: No | T44: N/A | U44: =IF(OR(U44="",U44=0),IF($T44="Submitted",TODAY(),""),U44) | V44: No | W44: No | X44: Submitted | Y44: 46280 | Z44: No | AA44: No | AB44: Approved | AC44: 46280 | AD44: No | AE44: No | AF44: N/A | AG44: =IF(OR(AG44="",AG44=0),IF($AF44="Submitted",TODAY(),""),AG44) | AH44: No | AI44: No | AJ44: waiting on contractor agreement to be signed and returned to Chowder | AK44: TRUE | AL44: {=IF($A44="","",SUMPRODUCT((CHOOSE({1,2,3,4,5},$R44,$V44,$Z44,$AD44,$AH44)="Yes")*(((CHOOSE({1,2,3,4,5},$S44,$W44,$AA44,$AE44,$AI44)="Yes")+(CHOOSE({1,2,3,4,5},$S44,$W44,$AA44,$AE44,$AI44)=TRUE))>0)))} -> 0 | AN44: =IF(OR($A44="",$AM44=""),"",TODAY()-$AM44) | BZ44: Unassigned | CA44: No | CB44: =IF($A44="","",_xlfn.LET(_xlpm.sfp,AND($P44<>"",$P44<>"N/A",$P44<>"No Min RQ"),_xlpm.slp,AND($T44<>"",$T44<>"N/A",$T44<>"No Min RQ"),_xlpm.ffp,AND($X44<>"",$X44<>"N/A",$X44<>"No Min RQ"),_xlpm.chp,AND($AB44<>"",$AB44<>"N/A",$AB44<>"No Min RQ"),_xlpm.usp,AND($AF44<>"",$AF44<>"N/A",$AF44<>"No Min RQ"),_xlpm.n,_xlpm.sfp+_xlpm.slp+_xlpm.ffp+_xlpm.chp+_xlpm.usp,_xlpm.sub,(_xlpm.sfp*($P44="Submitted"))+(_xlpm.slp*($T44="Submitted"))+(_xlpm.ffp*($X44="Submitted"))+(_xlpm.chp*($AB44="Submitted"))+(_xlpm.usp*($AF44="Submitted")),_xlpm.term,(_xlpm.sfp*OR($P44="Approved",$P44="Declined"))+(_xlpm.slp*OR($T44="Approved",$T44="Declined"))+(_xlpm.ffp*OR($X44="Approved",$X44="Declined"))+(_xlpm.chp*OR($AB44="Approved",$AB44="Declined"))+(_xlpm.usp*OR($AF44="Approved",$AF44="Declined")),IF(_xlpm.n=0,"No applicable lenders",IF(_xlpm.sub>0,"Stays with Shaw - lender still Submitted",IF(_xlpm.term=_xlpm.n,"Clear - all applicable lenders Approved or Declined","Stays with Shaw - not all lenders Approved or Declined")))))
A45: Top Roofing LLC | D45: Samantha Clemons | E45: 270-427-8236 | F45: staydry@toproofing.ky | G45: Mark Robichaud | H45: markchmand@gmail.com | I45: Roofing | K45: 2 | L45: =IF($A45="","",_xlfn.LET(_xlpm.ns,(--($P45="Ready 2 Submit"))+(--($T45="Ready 2 Submit"))+(--($X45="Ready 2 Submit"))+(--($AB45="Ready 2 Submit"))+(--($AF45="Ready 2 Submit")),_xlpm.wd,(--($P45="Waiting on Dealer"))+(--($T45="Waiting on Dealer"))+(--($X45="Waiting on Dealer"))+(--($AB45="Waiting on Dealer"))+(--($AF45="Waiting on Dealer")),_xlpm.sb,(--($P45="Submitted"))+(--($T45="Submitted"))+(--($X45="Submitted"))+(--($AB45="Submitted"))+(--($AF45="Submitted")),_xlpm.ap,(--($P45="Approved"))+(--($T45="Approved"))+(--($X45="Approved"))+(--($AB45="Approved"))+(--($AF45="Approved")),_xlpm.ac,(--($P45="Active"))+(--($T45="Active"))+(--($X45="Active"))+(--($AB45="Active"))+(--($AF45="Active")),_xlpm.dc,(--($P45="Declined"))+(--($T45="Declined"))+(--($X45="Declined"))+(--($AB45="Declined"))+(--($AF45="Declined")),_xlpm.aRS,(--($P45="Active"))*(--($R45="Yes"))+(--($T45="Active"))*(--($V45="Yes"))+(--($X45="Active"))*(--($Z45="Yes"))+(--($AB45="Active"))*(--($AD45="Yes"))+(--($AF45="Active"))*(--($AH45="Yes")),_xlpm.aDn,(--($P45="Active"))*(--($R45="Yes"))*(--((($S45="Yes")+($S45=TRUE))>0))+(--($T45="Active"))*(--($V45="Yes"))*(--((($W45="Yes")+($W45=TRUE))>0))+(--($X45="Active"))*(--($Z45="Yes"))*(--((($AA45="Yes")+($AA45=TRUE))>0))+(--($AB45="Active"))*(--($AD45="Yes"))*(--((($AE45="Yes")+($AE45=TRUE))>0))+(--($AF45="Active"))*(--($AH45="Yes"))*(--((($AI45="Yes")+($AI45=TRUE))>0)),_xlpm.inPlay,_xlpm.ns+_xlpm.wd+_xlpm.sb+_xlpm.ap,IF(AND(_xlpm.ac>0,_xlpm.inPlay=0,_xlpm.aDn=_xlpm.ac),"LIVE DLR",IF(AND(_xlpm.aRS>0,_xlpm.aDn<_xlpm.aRS),"Training",IF(_xlpm.aRS>0,"Active",IF(AND(_xlpm.dc>0,_xlpm.inPlay+_xlpm.ac=0),"Dead",IF(OR($CA45="Yes",$CA45=TRUE),"Rate Sheet",IF(AND($AJ45<>"",$AK45=FALSE),"Waiting on Dealer",IF(_xlpm.sb>0,"Waiting on Lender",IF(AND(_xlpm.ap+_xlpm.ac>0,_xlpm.ns+_xlpm.wd=0),"Rate Sheet","Application Submitted")))))))))) -> Waiting on Lender | M45: 46280 | N45: 46280 | O45: SF, SL, FF | P45: Submitted | Q45: 46280 | R45: No | S45: No | T45: Approved | U45: 46281 | V45: No | W45: No | X45: Submitted | Y45: 46280 | Z45: No | AA45: No | AB45: N/A | AC45: =IF(OR(AC45="",AC45=0),IF($AB45="Submitted",TODAY(),""),AC45) | AD45: No | AE45: No | AF45: N/A | AG45: =IF(OR(AG45="",AG45=0),IF($AF45="Submitted",TODAY(),""),AG45) | AH45: No | AI45: No | AJ45: Prior year annual revenue | Agreements | AK45: TRUE | AL45: {=IF($A45="","",SUMPRODUCT((CHOOSE({1,2,3,4,5},$R45,$V45,$Z45,$AD45,$AH45)="Yes")*(((CHOOSE({1,2,3,4,5},$S45,$W45,$AA45,$AE45,$AI45)="Yes")+(CHOOSE({1,2,3,4,5},$S45,$W45,$AA45,$AE45,$AI45)=TRUE))>0)))} -> 0 | AM45: 46280 | AN45: =IF(OR($A45="",$AM45=""),"",TODAY()-$AM45) -> 8 | BZ45: Unassigned | CA45: No | CB45: =IF($A45="","",_xlfn.LET(_xlpm.sfp,AND($P45<>"",$P45<>"N/A",$P45<>"No Min RQ"),_xlpm.slp,AND($T45<>"",$T45<>"N/A",$T45<>"No Min RQ"),_xlpm.ffp,AND($X45<>"",$X45<>"N/A",$X45<>"No Min RQ"),_xlpm.chp,AND($AB45<>"",$AB45<>"N/A",$AB45<>"No Min RQ"),_xlpm.usp,AND($AF45<>"",$AF45<>"N/A",$AF45<>"No Min RQ"),_xlpm.n,_xlpm.sfp+_xlpm.slp+_xlpm.ffp+_xlpm.chp+_xlpm.usp,_xlpm.sub,(_xlpm.sfp*($P45="Submitted"))+(_xlpm.slp*($T45="Submitted"))+(_xlpm.ffp*($X45="Submitted"))+(_xlpm.chp*($AB45="Submitted"))+(_xlpm.usp*($AF45="Submitted")),_xlpm.term,(_xlpm.sfp*OR($P45="Approved",$P45="Declined"))+(_xlpm.slp*OR($T45="Approved",$T45="Declined"))+(_xlpm.ffp*OR($X45="Approved",$X45="Declined"))+(_xlpm.chp*OR($AB45="Approved",$AB45="Declined"))+(_xlpm.usp*OR($AF45="Approved",$AF45="Declined")),IF(_xlpm.n=0,"No applicable lenders",IF(_xlpm.sub>0,"Stays with Shaw - lender still Submitted",IF(_xlpm.term=_xlpm.n,"Clear - all applicable lenders Approved or Declined","Stays with Shaw - not all lenders Approved or Declined")))))
